Workbook

Sheet Dashboard
A1: 🏛 PhilGEPS Procurement Monitoring Dashboard | S1: 🏛 PhilGEPS Procurement Monitoring Dashboard
A2: Philippine Government Electronic Procurement System | Real-Time Bid Monitoring | S2: Philippine Government Electronic Procurement System | Real-Time Bid Monitoring
A3: =TODAY() -> 46193
A5: 📋 | D5: 📅 | G5: 📆 | J5: 💰 | M5: 🟢 | P5: ⚠️ | S5: 📤
A6: Total Bids Today | D6: Total Bids This Week | G6: Total Bids This Month | J6: Total ABC Value (₱) | M6: Active Bids | P6: Closing in 7 Days | S6: Pending
A7: =COUNTIFS('Bid Monitoring'!A:A,TODAY()) -> 2 | D7: =COUNTIFS('Bid Monitoring'!A:A,">="&TODAY()-WEEKDAY(TODAY(),2)+1,'Bid Monitoring'!A:A,"<="&TODAY()-WEEKDAY(TODAY(),2)+7) -> 6 | G7: =COUNTIFS('Bid Monitoring'!A:A,">="&DATE(YEAR(TODAY()),MONTH(TODAY()),1),'Bid Monitoring'!A:A,"<="&EOMONTH(TODAY(),0)) -> 32 | J7: =IFERROR(SUMIF('Bid Monitoring'!N:N,"<>Cancelled",'Bid Monitoring'!H:H),0) -> 35076413 | M7: =COUNTIF('Bid Monitoring'!N:N,"Pending")+COUNTIF('Bid Monitoring'!N:N,"Interested")+COUNTIF('Bid Monitoring'!N:N,"For Review")+COUNTIF('Bid Monitoring'!N:N,"For Canvas")+COUNTIF('Bid Monitoring'!N:N,"Under Evaluation")+COUNTIF('Bid Monitoring'!N:N,"Preparing Documents")+COUNTIF('Bid Monitoring'!N:N,"New")+COUNTIF('Bid Monitoring'!N:N,"Submitting") -> 18 | P7: =COUNTIFS('Bid Monitoring'!I:I,">="&TODAY(),'Bid Monitoring'!I:I,"<="&TODAY()+7) -> 8 | S7: =COUNTIF('Bid Monitoring'!N:N,"Pending") -> 2
A9: 📤 | D9: 🔍 | G9: 🏆 | J9: ❌ | M9: 🚫 | P9: 📊
A10: Submitted | D10: Under Evaluation | G10: Awarded / Won | J10: Lost | M10: Cancelled | P10: Success Rate
A11: =COUNTIF('Bid Monitoring'!N:N,"Submitted") -> 4 | D11: =COUNTIF('Bid Monitoring'!N:N,"Under Evaluation") -> 2 | G11: =COUNTIF('Bid Monitoring'!N:N,"Awarded") -> 0 | J11: =COUNTIF('Bid Monitoring'!N:N,"Lost") -> 0 | M11: =COUNTIF('Bid Monitoring'!N:N,"Cancelled") -> 8 | P11: =IFERROR(COUNTIF('Bid Monitoring'!N:N,"Awarded")/COUNTIF('Bid Monitoring'!N:N,"Submitted"),0) -> 0
A14: 🚨 HIGH PRIORITY FLAGS — ABC > ₱5,000,000 & Closing > 10 Days
A15: # | B15: Reference Number | C15: Project Title | D15: Procuring Entity | E15: Region | F15: ABC (₱) | G15: Closing Date | H15: Days Left | I15: Category | J15: Status
A16: 1 | B16: ⬅ Add data in "Bid Monitoring" sheet — High-priority bids (ABC > ₱5M, Closing > 10 days) will appear here automatically
A17: 2
A18: 3
A19: 4
A20: 5
A21: 6
A22: 7
A23: 8
A24: 9
A25: 10
A27: 📊 Analytics & Reporting Charts
A28: 📈 Opportunities by Region [Charts will render after adding data to Bid Monitoring sheet] | J28: 📈 Opportunities by Category [Charts will render after adding data to Bid Monitoring sheet]
A45: 📈 Monthly Opportunity Trend [Charts will render after adding data to Bid Monitoring sheet] | J45: 📈 ABC Value by Region (₱) [Charts will render after adding data to Bid Monitoring sheet]
A62: 📈 Active vs Closed Opportunities [Charts will render after adding data to Bid Monitoring sheet] | J62: 📈 Bid Status Distribution [Charts will render after adding data to Bid Monitoring sheet]

Sheet Bid Monitoring
A1: 📋 BID MONITORING MASTERLIST — PhilGEPS Procurement Opportunities
A2: Date Monitored | B2: Reference Number | C2: Procuring Entity | D2: Project Title | E2: Category | F2: Region | G2: Province | H2: ABC (₱) | I2: Closing Date | J2: Closing Time | K2: Days Remaining | L2: Priority Level | M2: Assigned To | N2: Status | O2: Remarks | P2: Date Submitted | Q2: Bid Amount | R2: Result | S2: Opportunity Score | T2: ABC Flag >5M+10days | U2: Recommendation | V2: RFQ FILE
A3: 46180 | B3: 13023463 | C3: CARAGA REGIONAL HOSPITAL | D3: SUPPLY AND DELIVERY OF VARIOUS INKS AND CONSUMABLES UNDER SINGLE YEAR FRAMEWORK AGREEMENT | E3: Office Supplies | F3: CARAGA | G3: SURIGAO DEL NORTE | H3: 4091665 | I3: 46196 | J3: 0.41666667 | K3: =IF(I3="","",I3-TODAY()) -> 3 | L3: =IF(I3="","",IF(I3-TODAY()<=3,"High",IF(I3-TODAY()<=7,"Medium","Low"))) -> High | N3: Pending | O3: FOR REVIEW | R3: Pending | S3: =IF(H3="","",IFERROR(IF(H3>5000000,30,IF(H3>=1000000,20,10))+IF(I3-TODAY()>14,30,IF(I3-TODAY()>=7,20,10))+IF(R3="Won",40,IF(R3="Lost",10,20)),"")) -> 50 | T3: =IF(OR(H3="",I3=""),"",IF(AND(H3>5000000,I3-TODAY()>10),"🚨 FLAG","—")) -> — | U3: =IF(S3="","",IF(S3>=70,"✅ Highly Recommended",IF(S3>=50,"🔶 Consider","❌ Low Priority"))) -> 🔶 Consider | V3: E:\za\Agencies\May 30, 2026\CRH\A. TECHNICAL SPECS.pdf
A4: 46180 | B4: 13037704 | C4: CABADBARAN SOUTH CENTRAL ELEMENTARY SCHOOL - CABADBARAN CITY | D4: PR No.: 2026-06-001 sbfp Q-2026-05-001 SBFP Rice for SBFP 2026 | E4: Food Stuff | F4: CARAGA | G4: AGUSAN DEL NORTE | H4: 371200 | I4: 46183 | J4: 0.33333333 | K4: =IF(I10="","",I10-TODAY()) -> -12 | L4: Low | N4: Cancelled | O4: Cancelled by sir omar | R4: Cancelled | S4: =IF(H10="","",IFERROR(IF(H10>5000000,30,IF(H10>=1000000,20,10))+IF(I10-TODAY()>14,30,IF(I10-TODAY()>=7,20,10))+IF(R10="Won",40,IF(R10="Lost",10,20)),"")) -> 40 | T4: =IF(OR(H10="",I10=""),"",IF(AND(H10>5000000,I10-TODAY()>10),"🚨 FLAG","—")) -> — | U4: =IF(S10="","",IF(S10>=70,"✅ Highly Recommended",IF(S10>=50,"🔶 Consider","❌ Low Priority"))) -> ❌ Low Priority
A5: 46180 | B5: 13037984 | C5: CABADBARAN SOUTH CENTRAL ELEMENTARY SCHOOL - CABADBARAN CITY | D5: PR No.: 2026-06-001 sbfp Q-2026-05-003 SBFP VEGETABLES for SBFP | E5: Food Stuff | F5: CARAGA | G5: AGUSAN DEL NORTE | H5: 349756 | I5: 46181 | J5: 0.33333333 | K5: =IF(I11="","",I11-TODAY()) -> -11 | L5: Low | N5: Cancelled | O5: Cancelled by sir omar | R5: Cancelled | S5: =IF(H11="","",IFERROR(IF(H11>5000000,30,IF(H11>=1000000,20,10))+IF(I11-TODAY()>14,30,IF(I11-TODAY()>=7,20,10))+IF(R11="Won",40,IF(R11="Lost",10,20)),"")) -> 40 | T5: =IF(OR(H11="",I11=""),"",IF(AND(H11>5000000,I11-TODAY()>10),"🚨 FLAG","—")) -> — | U5: =IF(S11="","",IF(S11>=70,"✅ Highly Recommended",IF(S11>=50,"🔶 Consider","❌ Low Priority"))) -> ❌ Low Priority
A6: 46180 | B6: 13037836 | C6: CABADBARAN SOUTH CENTRAL ELEMENTARY SCHOOL - CABADBARAN CITY | D6: PR No.: 2026-06-002 sbfp Q-2026-05-002 SBFP MEAT for SBFP 2026 | E6: Food Stuff | F6: CARAGA | G6: AGUSAN DEL NORTE | H6: 407930 | I6: 46181 | J6: 0.33333333 | K6: =IF(I12="","",I12-TODAY()) -> -11 | L6: Low | N6: Cancelled | O6: Cancelled by sir omar | R6: Cancelled | S6: =IF(H12="","",IFERROR(IF(H12>5000000,30,IF(H12>=1000000,20,10))+IF(I12-TODAY()>14,30,IF(I12-TODAY()>=7,20,10))+IF(R12="Won",40,IF(R12="Lost",10,20)),"")) -> 40 | T6: =IF(OR(H12="",I12=""),"",IF(AND(H12>5000000,I12-TODAY()>10),"🚨 FLAG","—")) -> — | U6: =IF(S12="","",IF(S12>=70,"✅ Highly Recommended",IF(S12>=50,"🔶 Consider","❌ Low Priority"))) -> ❌ Low Priority
A7: 46180 | B7: 13032498 | C7: CARAGA STATE UNIVERSITY - CABADBARAN CAMPUS | D7: PROVISION OF 2ND QUARTER OFFICE SUPPLIES FOR USE BY VARIOUS OFFICES, IGF-164-26-05-319 | E7: Office Supplies | F7: CARAGA | G7: AGUSAN DEL NORTE | H7: 386406.47 | I7: 46184 | J7: 0.33333333 | K7: =IF(I13="","",I13-TODAY()) -> -11 | L7: =IF(I13="","",IF(I13-TODAY()<=3,"High",IF(I13-TODAY()<=7,"Medium","Low"))) -> High | N7: Submitting | O7: For Checking by maam Astrid | R7: Pending | S7: =IF(H13="","",IFERROR(IF(H13>5000000,30,IF(H13>=1000000,20,10))+IF(I13-TODAY()>14,30,IF(I13-TODAY()>=7,20,10))+IF(R13="Won",40,IF(R13="Lost",10,20)),"")) -> 40 | T7: =IF(OR(H13="",I13=""),"",IF(AND(H13>5000000,I13-TODAY()>10),"🚨 FLAG","—")) -> — | U7: =IF(S13="","",IF(S13>=70,"✅ Highly Recommended",IF(S13>=50,"🔶 Consider","❌ Low Priority"))) -> 🔶 Consider
A8: 46180 | B8: 12994917 | C8: CARAGA REGIONAL HOSPITAL | D8: SUPPLY AND DELIVERY OF GREYSCALE PAPER A4 SIZE FOR CT SCAN OR XRAY | E8: Office Supplies | F8: CARAGA | G8: SURIGAO DEL NORTE | H8: 2400000 | I8: 46183 | J8: 0.41666667 | K8: =IF(I14="","",I14-TODAY()) -> -11 | L8: =IF(I14="","",IF(I14-TODAY()<=3,"High",IF(I14-TODAY()<=7,"Medium","Low"))) -> High | N8: Under Evaluation | O8: Under Evaluation | R8: Pending | S8: =IF(H14="","",IFERROR(IF(H14>5000000,30,IF(H14>=1000000,20,10))+IF(I14-TODAY()>14,30,IF(I14-TODAY()>=7,20,10))+IF(R14="Won",40,IF(R14="Lost",10,20)),"")) -> 40 | T8: =IF(OR(H14="",I14=""),"",IF(AND(H14>5000000,I14-TODAY()>10),"🚨 FLAG","—")) -> — | U8: =IF(S14="","",IF(S14>=70,"✅ Highly Recommended",IF(S14>=50,"🔶 Consider","❌ Low Priority"))) -> ❌ Low Priority
A9: 46179 | B9: 13029937 | C9: DEPARTMENT OF SOCIAL WELFARE AND DEVELOPMENT -CARAGA | D9: PURCHASE OF OFFICE SUPPLIES FOR JULY AND AUGUST FOR 4Ps USE | E9: Office Supplies | F9: CARAGA | G9: AGUSAN DEL NORTE | H9: 920450 | I9: 46181 | J9: 0.29166667 | K9: =IF(I4="","",I4-TODAY()) -> -10 | L9: =IF(I4="","",IF(I4-TODAY()<=3,"High",IF(I4-TODAY()<=7,"Medium","Low"))) -> High | M9: DAVEN | N9: Submitted | O9: Submitted by daven | P9: 46181 | R9: Pending | S9: =IF(H4="","",IFERROR(IF(H4>5000000,30,IF(H4>=1000000,20,10))+IF(I4-TODAY()>14,30,IF(I4-TODAY()>=7,20,10))+IF(R4="Won",40,IF(R4="Lost",10,20)),"")) -> 40 | T9: =IF(OR(H4="",I4=""),"",IF(AND(H4>5000000,I4-TODAY()>10),"🚨 FLAG","—")) -> — | U9: =IF(S4="","",IF(S4>=70,"✅ Highly Recommended",IF(S4>=50,"🔶 Consider","❌ Low Priority"))) -> ❌ Low Priority
A10: 46179 | B10: 13025115 | C10: DEPARTMENT OF SOCIAL WELFARE AND DEVELOPMENT -CARAGA | D10: SUBSIDIES EXPENSE: HFG RESIDENT'S SCHOOL SUPPLIES, CY 2026 | E10: Office Supplies | F10: CARAGA | G10: AGUSAN DEL NORTE | H10: 209927 | I10: 46181 | J10: 0.33333333 | K10: =IF(I5="","",I5-TODAY()) -> -12 | L10: =IF(I5="","",IF(I5-TODAY()<=3,"High",IF(I5-TODAY()<=7,"Medium","Low"))) -> High | M10: DAVEN | N10: Submitted | O10: Submitted by daven | P10: 46181 | R10: Pending | S10: =IF(H5="","",IFERROR(IF(H5>5000000,30,IF(H5>=1000000,20,10))+IF(I5-TODAY()>14,30,IF(I5-TODAY()>=7,20,10))+IF(R5="Won",40,IF(R5="Lost",10,20)),"")) -> 40 | T10: =IF(OR(H5="",I5=""),"",IF(AND(H5>5000000,I5-TODAY()>10),"🚨 FLAG","—")) -> — | U10: =IF(S5="","",IF(S5>=70,"✅ Highly Recommended",IF(S5>=50,"🔶 Consider","❌ Low Priority"))) -> ❌ Low Priority
A11: 46179 | B11: 13035898 | C11: DEPARTMENT OF HEALTH - CARAGA | D11: TOKEN AND AWARDS | E11: Tokens and Awards | F11: CARAGA | G11: AGUSAN DEL NORTE | H11: 330240 | I11: 46182 | J11: 0.625 | K11: =IF(I6="","",I6-TODAY()) -> -12 | L11: =IF(I6="","",IF(I6-TODAY()<=3,"High",IF(I6-TODAY()<=7,"Medium","Low"))) -> High | M11: Ann | N11: Submitted | O11: Submitted by daven | P11: 46181 | R11: Pending | S11: =IF(H6="","",IFERROR(IF(H6>5000000,30,IF(H6>=1000000,20,10))+IF(I6-TODAY()>14,30,IF(I6-TODAY()>=7,20,10))+IF(R6="Won",40,IF(R6="Lost",10,20)),"")) -> 40 | T11: =IF(OR(H6="",I6=""),"",IF(AND(H6>5000000,I6-TODAY()>10),"🚨 FLAG","—")) -> — | U11: =IF(S6="","",IF(S6>=70,"✅ Highly Recommended",IF(S6>=50,"🔶 Consider","❌ Low Priority"))) -> ❌ Low Priority
A12: 46179 | B12: 13036461 | C12: DEPARTMENT OF SOCIAL WELFARE AND DEVELOPMENT -CARAGA | D12: FOR PERSONNEL OFFICE USE | E12: IT Equipment | F12: CARAGA | G12: AGUSAN DEL NORTE | H12: 252995 | I12: 46182 | J12: 0.375 | K12: =IF(I7="","",I7-TODAY()) -> -9 | L12: Low | N12: Cancelled | O12: Cancelled by sir omar | R12: Cancelled | S12: =IF(H7="","",IFERROR(IF(H7>5000000,30,IF(H7>=1000000,20,10))+IF(I7-TODAY()>14,30,IF(I7-TODAY()>=7,20,10))+IF(R7="Won",40,IF(R7="Lost",10,20)),"")) -> 40 | T12: =IF(OR(H7="",I7=""),"",IF(AND(H7>5000000,I7-TODAY()>10),"🚨 FLAG","—")) -> — | U12: =IF(S7="","",IF(S7>=70,"✅ Highly Recommended",IF(S7>=50,"🔶 Consider","❌ Low Priority"))) -> ❌ Low Priority
A13: 46179 | B13: 13036211 | C13: DEPARTMENT OF AGRICULTURE - CARAGA | D13: POCUREMENT OF FARM TOOLS | E13: General Merchandise | F13: CARAGA | G13: AGUSAN DEL NORTE | H13: 501104 | I13: 46182 | J13: 0.041666667 | K13: =IF(I8="","",I8-TODAY()) -> -10 | L13: Low | N13: Cancelled | O13: Cancelled by sir omar | R13: Cancelled | S13: =IF(H8="","",IFERROR(IF(H8>5000000,30,IF(H8>=1000000,20,10))+IF(I8-TODAY()>14,30,IF(I8-TODAY()>=7,20,10))+IF(R8="Won",40,IF(R8="Lost",10,20)),"")) -> 50 | T13: =IF(OR(H8="",I8=""),"",IF(AND(H8>5000000,I8-TODAY()>10),"🚨 FLAG","—")) -> — | U13: =IF(S8="","",IF(S8>=70,"✅ Highly Recommended",IF(S8>=50,"🔶 Consider","❌ Low Priority"))) -> ❌ Low Priority
A14: 46179 | B14: 13037476 | C14: DEPARTMENT OF SOCIAL WELFARE AND DEVELOPMENT -CARAGA | D14: PURCHASE OF DESKTOP/LAPTOP/PRINTERS FRR HRMDD/HRPPMS USAGE | E14: IT Equipment | F14: CARAGA | G14: AGUSAN DEL NORTE | H14: 349993 | I14: 46182 | J14: 0.375 | K14: =IF(I9="","",I9-TODAY()) -> -12 | L14: Low | N14: Cancelled | O14: Cancelled by sir omar | R14: Cancelled | S14: =IF(H9="","",IFERROR(IF(H9>5000000,30,IF(H9>=1000000,20,10))+IF(I9-TODAY()>14,30,IF(I9-TODAY()>=7,20,10))+IF(R9="Won",40,IF(R9="Lost",10,20)),"")) -> 40 | T14: =IF(OR(H9="",I9=""),"",IF(AND(H9>5000000,I9-TODAY()>10),"🚨 FLAG","—")) -> — | U14: =IF(S9="","",IF(S9>=70,"✅ Highly Recommended",IF(S9>=50,"🔶 Consider","❌ Low Priority"))) -> ❌ Low Priority
A15: 46176 | B15: 13030274 | C15: DEPARTMENT OF SOCIAL WELFARE AND DEVELOPMENT -CARAGA | D15: PURCHASE OF OFFICE SUPPLIES FOR JULY AND AUGUST FOR 4Ps USE (INK CARTRIDGE) | E15: General Merchandise | F15: CARAGA | G15: AGUSAN DEL NORTE | H15: 571100 | I15: 46181 | J15: 0.29166667 | K15: =IF(I15="","",I15-TODAY()) -> -12 | L15: =IF(I15="","",IF(I15-TODAY()<=3,"High",IF(I15-TODAY()<=7,"Medium","Low"))) -> High | N15: Submitted | O15: Submitted by daven | P15: 46181 | R15: Pending | S15: =IF(H15="","",IFERROR(IF(H15>5000000,30,IF(H15>=1000000,20,10))+IF(I15-TODAY()>14,30,IF(I15-TODAY()>=7,20,10))+IF(R15="Won",40,IF(R15="Lost",10,20)),"")) -> 40 | T15: =IF(OR(H15="",I15=""),"",IF(AND(H15>5000000,I15-TODAY()>10),"🚨 FLAG","—")) -> — | U15: =IF(S15="","",IF(S15>=70,"✅ Highly Recommended",IF(S15>=50,"🔶 Consider","❌ Low Priority"))) -> ❌ Low Priority
A16: 46182 | B16: 13007679 | C16: DEPARTMENT OF EDUCATION - DIVISION OF SURIGAO DEL NORTE | D16: INVITATION TO BID FOR PROCUREMENT OF E-NUTRIBUN SQUASH VARIANT WITH 150 ML KALAMANSI JUICE, E-NUTRIBUN CARROT VARIANT WITH 150 ML KAMOTE JUICE, AND NUTRIBUNNETS WITH FILLING, WITH CERTIFICATION FROM D | E16: Food Stuff | F16: CARAGA | G16: SURIGAO DEL NORTE | H16: 3486560 | I16: 46184 | J16: 0.375 | K16: =IF(I16="","",I16-TODAY()) -> -9 | L16: =IF(I16="","",IF(I16-TODAY()<=3,"High",IF(I16-TODAY()<=7,"Medium","Low"))) -> High | N16: Cancelled | O16: FOR REVIEW | R16: Cancelled | S16: =IF(H16="","",IFERROR(IF(H16>5000000,30,IF(H16>=1000000,20,10))+IF(I16-TODAY()>14,30,IF(I16-TODAY()>=7,20,10))+IF(R16="Won",40,IF(R16="Lost",10,20)),"")) -> 50 | T16: =IF(OR(H16="",I16=""),"",IF(AND(H16>5000000,I16-TODAY()>10),"🚨 FLAG","—")) -> — | U16: =IF(S16="","",IF(S16>=70,"✅ Highly Recommended",IF(S16>=50,"🔶 Consider","❌ Low Priority"))) -> 🔶 Consider
A17: 46182 | B17: 13036941 | C17: DEPARTMENT OF AGRICULTURE - CARAGA | D17: Procurement of Animal Feeds (3 Lots) | E17: Animal Feeds | F17: CARAGA | G17: AGUSAN DEL NORTE | H17: 9866160 | I17: 46202 | J17: 0.375 | K17: =IF(I17="","",I17-TODAY()) -> 9 | L17: =IF(I17="","",IF(I17-TODAY()<=3,"High",IF(I17-TODAY()<=7,"Medium","Low"))) -> Low | N17: For Canvas | O17: FOR PRICING BY ZAR | R17: Pending | S17: =IF(H17="","",IFERROR(IF(H17>5000000,30,IF(H17>=1000000,20,10))+IF(I17-TODAY()>14,30,IF(I17-TODAY()>=7,20,10))+IF(R17="Won",40,IF(R17="Lost",10,20)),"")) -> 70 | T17: =IF(OR(H17="",I17=""),"",IF(AND(H17>5000000,I17-TODAY()>10),"🚨 FLAG","—")) -> — | U17: =IF(S17="","",IF(S17>=70,"✅ Highly Recommended",IF(S17>=50,"🔶 Consider","❌ Low Priority"))) -> ✅ Highly Recommended | V17: ..\..\..\..\..\..\..\..\..\Agencies\June 09, 2026\DA - CARAGA\Bidding Document.pdf
A18: 46184 | B18: 13047472 | C18: DEPARTMENT OF HEALTH - CARAGA | D18: TOKEN AND AWARDS | E18: Hygiene Kits | F18: CARAGA | G18: AGUSAN DEL NORTE | H18: 1500000 | I18: 46188 | J18: 0.625 | K18: =IF(I18="","",I18-TODAY()) -> -5 | L18: =IF(I18="","",IF(I18-TODAY()<=3,"High",IF(I18-TODAY()<=7,"Medium","Low"))) -> High | N18: For Canvas | O18: For canvass by Ann | R18: Pending | S18: =IF(H18="","",IFERROR(IF(H18>5000000,30,IF(H18>=1000000,20,10))+IF(I18-TODAY()>14,30,IF(I18-TODAY()>=7,20,10))+IF(R18="Won",40,IF(R18="Lost",10,20)),"")) -> 50 | T18: =IF(OR(H18="",I18=""),"",IF(AND(H18>5000000,I18-TODAY()>10),"🚨 FLAG","—")) -> — | U18: =IF(S18="","",IF(S18>=70,"✅ Highly Recommended",IF(S18>=50,"🔶 Consider","❌ Low Priority"))) -> 🔶 Consider | V18: E:\za\Agencies\June 11, 2026\DOH - Caraga\TOKEN AND AWARDS.pdf
A19: 46184 | B19: 13048712 | C19: DEPARTMENT OF PUBLIC WORKS AND HIGHWAYS - BUTUAN CITY DEO | D19: RFQ - 1 unit Desktop Computer (Application Use) and 6 unit Desktop Computer (Administrative Use) | E19: IT Equipment | F19: CARAGA | G19: AGUSAN DEL NORTE | H19: 1277131 | I19: 46188 | J19: 0.58333333 | K19: =IF(I19="","",I19-TODAY()) -> -5 | L19: =IF(I19="","",IF(I19-TODAY()<=3,"High",IF(I19-TODAY()<=7,"Medium","Low"))) -> High | N19: Pending | O19: For canvass by Zar | R19: Pending | S19: =IF(H19="","",IFERROR(IF(H19>5000000,30,IF(H19>=1000000,20,10))+IF(I19-TODAY()>14,30,IF(I19-TODAY()>=7,20,10))+IF(R19="Won",40,IF(R19="Lost",10,20)),"")) -> 50 | T19: =IF(OR(H19="",I19=""),"",IF(AND(H19>5000000,I19-TODAY()>10),"🚨 FLAG","—")) -> — | U19: =IF(S19="","",IF(S19>=70,"✅ Highly Recommended",IF(S19>=50,"🔶 Consider","❌ Low Priority"))) -> 🔶 Consider | V19: E:\za\Agencies\June 11, 2026\DPWH - Caraga\SPECS FOR PR NO. 2026-06-0105 DATED 06-02-2026.pdf
A20: 46184 | B20: 13042838 | C20: DEPARTMENT OF SCIENCE AND TECHNOLOGY - CARAGA (CSU-AMPAYON, BUTUAN CITY) | D20: Supply & delivery of 5-units Laptop with Complete Accessories | E20: IT Equipment | F20: CARAGA | G20: AGUSAN DEL NORTE | H20: 247500 | I20: 46189 | J20: 0.5 | K20: =IF(I20="","",I20-TODAY()) -> -4 | L20: =IF(I20="","",IF(I20-TODAY()<=3,"High",IF(I20-TODAY()<=7,"Medium","Low"))) -> High | N20: For Canvas | O20: For canvass by Zar | R20: Pending | S20: =IF(H20="","",IFERROR(IF(H20>5000000,30,IF(H20>=1000000,20,10))+IF(I20-TODAY()>14,30,IF(I20-TODAY()>=7,20,10))+IF(R20="Won",40,IF(R20="Lost",10,20)),"")) -> 40 | T20: =IF(OR(H20="",I20=""),"",IF(AND(H20>5000000,I20-TODAY()>10),"🚨 FLAG","—")) -> — | U20: =IF(S20="","",IF(S20>=70,"✅ Highly Recommended",IF(S20>=50,"🔶 Consider","❌ Low Priority"))) -> ❌ Low Priority | V20: E:\za\Agencies\June 11, 2026\DST - Caraga\Request for Quotation-LAPTOP.pdf
A21: 46184 | B21: 13051917 | C21: DEPARTMENT OF SOCIAL WELFARE AND DEVELOPMENT - CARAGA | D21: Procurement of Printers and Document Scanners for 4Ps use. | E21: IT Equipment | F21: CARAGA | G21: AGUSAN DEL NORTE | H21: 253000 | I21: 46190 | J21: 0.29166667 | K21: =IF(I21="","",I21-TODAY()) -> -3 | L21: =IF(I21="","",IF(I21-TODAY()<=3,"High",IF(I21-TODAY()<=7,"Medium","Low"))) -> High | N21: For Request Docs | O21: Requesting Documents | R21: Pending | S21: =IF(H21="","",IFERROR(IF(H21>5000000,30,IF(H21>=1000000,20,10))+IF(I21-TODAY()>14,30,IF(I21-TODAY()>=7,20,10))+IF(R21="Won",40,IF(R21="Lost",10,20)),"")) -> 40 | T21: =IF(OR(H21="",I21=""),"",IF(AND(H21>5000000,I21-TODAY()>10),"🚨 FLAG","—")) -> — | U21: =IF(S21="","",IF(S21>=70,"✅ Highly Recommended",IF(S21>=50,"🔶 Consider","❌ Low Priority"))) -> ❌ Low Priority | V21: REQUESTING A DOCUMENT TO DSWD
A22: 46184 | B22: 13045199 | C22: DEPARTMENT OF SOCIAL WELFARE AND DEVELOPMENT - CARAGA | D22: Subsidies Expense: HFG Residents' Apparel and Lines School Supplies Use CY 2026 | E22: General Merchandise | F22: CARAGA | G22: AGUSAN DEL NORTE | H22: 324200 | I22: 46188 | J22: 0.33333333 | K22: =IF(I22="","",I22-TODAY()) -> -5 | L22: =IF(I22="","",IF(I22-TODAY()<=3,"High",IF(I22-TODAY()<=7,"Medium","Low"))) -> High | N22: Submitting | O22: Submitting by daven | P22: 46188 | R22: Pending | S22: =IF(H22="","",IFERROR(IF(H22>5000000,30,IF(H22>=1000000,20,10))+IF(I22-TODAY()>14,30,IF(I22-TODAY()>=7,20,10))+IF(R22="Won",40,IF(R22="Lost",10,20)),"")) -> 40 | T22: =IF(OR(H22="",I22=""),"",IF(AND(H22>5000000,I22-TODAY()>10),"🚨 FLAG","—")) -> — | U22: =IF(S22="","",IF(S22>=70,"✅ Highly Recommended",IF(S22>=50,"🔶 Consider","❌ Low Priority"))) -> ❌ Low Priority | V22: E:\za\Agencies\June 11, 2026\DSWD - Caraga\Request for Quotation.pdf
A23: 46179 | B23: 13042045 | C23: DEPARTMENT OF SOCIAL WELFARE AND DEVELOPMENT - CARAGA | D23: SUPPLY AND DELIVERY OF VARIOUS FOOD ITEMS FOR SUPPLEMENTARY FEEDING PROGRAM IMPLEMENTATION FOR C.Y. 2026 (16th CYCLE)–ALTERNATIVE MEALS FOR DSWD FO CARAGA UNDER NP-TWO FAILED BIDDINGS-2ND POSTING | E23: Food Stuff | F23: CARAGA | G23: AGUSAN DEL NORTE | H23: 67713600 | I23: 46189 | J23: 0.375 | K23: =IF(I23="","",I23-TODAY()) -> -4 | L23: =IF(I23="","",IF(I23-TODAY()<=3,"High",IF(I23-TODAY()<=7,"Medium","Low"))) -> High | N23: Cancelled | O23: Cancelled by sir omar & ma'am Astrid | R23: Cancelled | S23: =IF(H23="","",IFERROR(IF(H23>5000000,30,IF(H23>=1000000,20,10))+IF(I23-TODAY()>14,30,IF(I23-TODAY()>=7,20,10))+IF(R23="Won",40,IF(R23="Lost",10,20)),"")) -> 60 | T23: =IF(OR(H23="",I23=""),"",IF(AND(H23>5000000,I23-TODAY()>10),"🚨 FLAG","—")) -> — | U23: =IF(S23="","",IF(S23>=70,"✅ Highly Recommended",IF(S23>=50,"🔶 Consider","❌ Low Priority"))) -> 🔶 Consider | V23: C:\Users\admin\Desktop\BHM-PhilGeps\Agencies\June 11, 2026\DSWD_1 - Caraga\NP- TWO FAILED BIDDING - NEGOTIATION DOCUMENT.pdf
A24: 46184 | B24: 13050778 | C24: NORTH EASTERN MINDANAO STATE UNIVERSITY | D24: Supply and Delivery of Information Technology (ICT Equipment) for DHM Faculty and Staff usage of NEMSU Tandag Campus. | E24: IT Equipment | F24: CARAGA | G24: Surigao Del Sur | H24: 230000 | I24: 46188 | J24: 0.41666667 | K24: =IF(I24="","",I24-TODAY()) -> -5 | L24: =IF(I24="","",IF(I24-TODAY()<=3,"High",IF(I24-TODAY()<=7,"Medium","Low"))) -> High | N24: For Canvas | O24: For canvass by Zar | R24: Pending | S24: =IF(H24="","",IFERROR(IF(H24>5000000,30,IF(H24>=1000000,20,10))+IF(I24-TODAY()>14,30,IF(I24-TODAY()>=7,20,10))+IF(R24="Won",40,IF(R24="Lost",10,20)),"")) -> 40 | T24: =IF(OR(H24="",I24=""),"",IF(AND(H24>5000000,I24-TODAY()>10),"🚨 FLAG","—")) -> — | U24: =IF(S24="","",IF(S24>=70,"✅ Highly Recommended",IF(S24>=50,"🔶 Consider","❌ Low Priority"))) -> ❌ Low Priority | V24: C:\Users\admin\Desktop\BHM-PhilGeps\Agencies\June 11, 2026\NEMSU Tandag Campus\RFQ.pdf
A25: 46184 | B25: 13048298 | C25: NORTH EASTERN MINDANAO STATE UNIVERSITY | D25: Supply and Delivery of ICT Equipment & Supplies for ICT Computer and Network Supply and Maintenance use of NEMSU Tandag Campus. | E25: IT Equipment | F25: CARAGA | G25: Surigao Del Sur | H25: 1580332.4 | I25: 46188 | J25: 0.41666667 | K25: =IF(I25="","",I25-TODAY()) -> -5 | L25: =IF(I25="","",IF(I25-TODAY()<=3,"High",IF(I25-TODAY()<=7,"Medium","Low"))) -> High | N25: For Canvas | O25: For canvass by Zar | R25: Pending | S25: =IF(H25="","",IFERROR(IF(H25>5000000,30,IF(H25>=1000000,20,10))+IF(I25-TODAY()>14,30,IF(I25-TODAY()>=7,20,10))+IF(R25="Won",40,IF(R25="Lost",10,20)),"")) -> 50 | T25: =IF(OR(H25="",I25=""),"",IF(AND(H25>5000000,I25-TODAY()>10),"🚨 FLAG","—")) -> — | U25: =IF(S25="","",IF(S25>=70,"✅ Highly Recommended",IF(S25>=50,"🔶 Consider","❌ Low Priority"))) -> 🔶 Consider | V25: C:\Users\admin\Desktop\BHM-PhilGeps\Agencies\June 11, 2026\NEMSU Tandag Campus - 1\RFQ.pdf
A26: 46187 | B26: 13031492 | C26: DEPARTMENT OF SOCIAL WELFARE AND DEVELOPMENT - CARAGA | D26: PROCUREMENT OF VARIOUS FOOD ITEMS FOR SUPPLEMENTARY FEEDING PROGRAM IMPLEMENTATION FOR C.Y. 2026 (16th CYCLE) – ALTERNATIVE MEALS FOR DSWD FIELD OFFICE CARAGA – SIARGAO ISLAND | E26: Food Stuff | F26: CARAGA | G26: AGUSAN DEL NORTE | H26: 3906000 | I26: 46196 | J26: 0.5 | K26: =IF(I26="","",I26-TODAY()) -> 3 | L26: =IF(I26="","",IF(I26-TODAY()<=3,"High",IF(I26-TODAY()<=7,"Medium","Low"))) -> High | N26: For Review | O26: FOR REVIEW BY SIR OMAR | R26: Pending | S26: =IF(H26="","",IFERROR(IF(H26>5000000,30,IF(H26>=1000000,20,10))+IF(I26-TODAY()>14,30,IF(I26-TODAY()>=7,20,10))+IF(R26="Won",40,IF(R26="Lost",10,20)),"")) -> 50 | T26: =IF(OR(H26="",I26=""),"",IF(AND(H26>5000000,I26-TODAY()>10),"🚨 FLAG","—")) -> — | U26: =IF(S26="","",IF(S26>=70,"✅ Highly Recommended",IF(S26>=50,"🔶 Consider","❌ Low Priority"))) -> 🔶 Consider | V26: ..\..\..\..\..\..\..\..\..\Agencies\June 14, 2026\DSWD - CARAGA\BIDDING DOCUMENTS.pdf
A27: 46187 | B27: 36729 | C27: PATIN-AY NATIONAL HIGH SCHOOL - Agusan Del Sur | D27: Procurement of Office Supplies and Materials in the Conduct of PPST-Based and PPSSH-Based PD Program: Training on the Strengthened Senior High School Curriculum (DepEd-Division Office) | E27: Office Supplies | F27: CARAGA | G27: AGUSAN DEL SUR | H27: 267965 | I27: 46190 | J27: 0.375 | K27: =IF(I27="","",I27-TODAY()) -> -3 | L27: =IF(I27="","",IF(I27-TODAY()<=3,"High",IF(I27-TODAY()<=7,"Medium","Low"))) -> High | N27: For Review | O27: FOR REVIEW BY ROTCHE | R27: Pending | S27: =IF(H27="","",IFERROR(IF(H27>5000000,30,IF(H27>=1000000,20,10))+IF(I27-TODAY()>14,30,IF(I27-TODAY()>=7,20,10))+IF(R27="Won",40,IF(R27="Lost",10,20)),"")) -> 40 | T27: =IF(OR(H27="",I27=""),"",IF(AND(H27>5000000,I27-TODAY()>10),"🚨 FLAG","—")) -> — | U27: =IF(S27="","",IF(S27>=70,"✅ Highly Recommended",IF(S27>=50,"🔶 Consider","❌ Low Priority"))) -> ❌ Low Priority | V27: ..\..\..\..\..\..\..\..\..\Agencies\June 14, 2026\DEPED - CARAGA\1781328153_2026_06_0245_Supplies_Jalalon.pdf
A28: 46187 | B28: 13042259 | C28: DEPARTMENT OF SOCIAL WELFARE AND DEVELOPMENT - CARAGA | D28: SUPPLY AND DELIVERY OF VARIOUS FOOD ITEMS FOR SFP IMPLEMENTATION FOR C.Y. 2026 (16th CYCLE)-HOTMEALS FOR BACUAG, CLAVER, GIGAQUIT AND PLACER SDN UNDER NP-TWO FAILED BIDDING-2ND POSTING | E28: Food Stuff | F28: CARAGA | G28: AGUSAN DEL NORTE | H28: 4590000 | I28: 46189 | J28: 0.375 | K28: =IF(I28="","",I28-TODAY()) -> -4 | L28: =IF(I28="","",IF(I28-TODAY()<=3,"High",IF(I28-TODAY()<=7,"Medium","Low"))) -> High | N28: Under Evaluation | O28: FOR EVALUATION | R28: Pending | S28: =IF(H28="","",IFERROR(IF(H28>5000000,30,IF(H28>=1000000,20,10))+IF(I28-TODAY()>14,30,IF(I28-TODAY()>=7,20,10))+IF(R28="Won",40,IF(R28="Lost",10,20)),"")) -> 50 | T28: =IF(OR(H28="",I28=""),"",IF(AND(H28>5000000,I28-TODAY()>10),"🚨 FLAG","—")) -> — | U28: =IF(S28="","",IF(S28>=70,"✅ Highly Recommended",IF(S28>=50,"🔶 Consider","❌ Low Priority"))) -> 🔶 Consider | V28: ..\..\..\..\..\..\..\..\..\Agencies\June 14, 2026\DSWD_BACUAG- CARAGA\NP- TWO FAILED BIDDING - NEGOTIATION DOCUMENT.pdf
A29: 46190 | B29: 13061414 | C29: CARAGA STATE UNIVERSITY | D29: RFQ - PROVISION OF OFFICE AND OTHER SUPPLIES AND MATERIALS FOR THE VARIOUS CSU ADMINISTRATIVE OFFICE OPERATIONS. , RAF-101-26-06-355 | E29: Office Supplies | F29: CARAGA | G29: AGUSAN DEL NORTE | H29: 238587.3 | I29: 46195 | J29: 0.33333333 | K29: =IF(I29="","",I29-TODAY()) -> 2 | L29: =IF(I29="","",IF(I29-TODAY()<=3,"High",IF(I29-TODAY()<=7,"Medium","Low"))) -> High | N29: For Review | O29: FOR REVIEW BY SIR OMAR | R29: Pending | S29: =IF(H29="","",IFERROR(IF(H29>5000000,30,IF(H29>=1000000,20,10))+IF(I29-TODAY()>14,30,IF(I29-TODAY()>=7,20,10))+IF(R29="Won",40,IF(R29="Lost",10,20)),"")) -> 40 | T29: =IF(OR(H29="",I29=""),"",IF(AND(H29>5000000,I29-TODAY()>10),"🚨 FLAG","—")) -> — | U29: =IF(S29="","",IF(S29>=70,"✅ Highly Recommended",IF(S29>=50,"🔶 Consider","❌ Low Priority"))) -> ❌ Low Priority | V29: ..\..\..\..\..\..\..\..\..\Agencies\JUNE 17, 2026\CSU - CARAGA\Canvass Form.pdf
A30: 46191 | B30: 13046873 | C30: NORTH CABADBARAN CENTRAL ELEMENTARY SCHOOL - CABADBARAN CITY | D30: Grocery Items | E30: Food Stuff | F30: CARAGA | G30: AGUSAN DEL NORTE | H30: 412634 | I30: 46195 | J30: 0.041666667 | K30: =IF(I30="","",I30-TODAY()) -> 2 | L30: =IF(I30="","",IF(I30-TODAY()<=3,"High",IF(I30-TODAY()<=7,"Medium","Low"))) -> High | N30: Submitting | O30: Submitting by daven | R30: Pending | S30: =IF(H30="","",IFERROR(IF(H30>5000000,30,IF(H30>=1000000,20,10))+IF(I30-TODAY()>14,30,IF(I30-TODAY()>=7,20,10))+IF(R30="Won",40,IF(R30="Lost",10,20)),"")) -> 40 | T30: =IF(OR(H30="",I30=""),"",IF(AND(H30>5000000,I30-TODAY()>10),"🚨 FLAG","—")) -> — | U30: =IF(S30="","",IF(S30>=70,"✅ Highly Recommended",IF(S30>=50,"🔶 Consider","❌ Low Priority"))) -> ❌ Low Priority | V30: ..\..\..\..\..\..\..\..\..\Agencies\June 18, 2026\Cabadbaran Elem\Grocery Items.pdf
A31: 46191 | B31: 13046956 | C31: NORTH CABADBARAN CENTRAL ELEMENTARY SCHOOL - CABADBARAN CITY | D31: Grocery Items | E31: Food Stuff | F31: CARAGA | G31: AGUSAN DEL NORTE | H31: 487550 | I31: 46195 | J31: 0.041666667 | K31: =IF(I31="","",I31-TODAY()) -> 2 | L31: =IF(I31="","",IF(I31-TODAY()<=3,"High",IF(I31-TODAY()<=7,"Medium","Low"))) -> High | N31: Submitting | O31: Submitting by daven | R31: Pending | S31: =IF(H31="","",IFERROR(IF(H31>5000000,30,IF(H31>=1000000,20,10))+IF(I31-TODAY()>14,30,IF(I31-TODAY()>=7,20,10))+IF(R31="Won",40,IF(R31="Lost",10,20)),"")) -> 40 | T31: =IF(OR(H31="",I31=""),"",IF(AND(H31>5000000,I31-TODAY()>10),"🚨 FLAG","—")) -> — | U31: =IF(S31="","",IF(S31>=70,"✅ Highly Recommended",IF(S31>=50,"🔶 Consider","❌ Low Priority"))) -> ❌ Low Priority | V31: C:\Users\admin\Desktop\BHM-PhilGeps\Agencies\June 18, 2026\DEPED - CBR_FISH\Grocery Items - fish.pdf
A32: 46191 | B32: 13046969 | C32: NORTH CABADBARAN CENTRAL ELEMENTARY SCHOOL - CABADBARAN CITY | D32: Grocery Items - Fish | E32: Food Stuff | F32: CARAGA | G32: AGUSAN DEL NORTE | H32: 303000 | I32: 46195 | J32: 0.041666667 | K32: =IF(I32="","",I32-TODAY()) -> 2 | L32: =IF(I32="","",IF(I32-TODAY()<=3,"High",IF(I32-TODAY()<=7,"Medium","Low"))) -> High | N32: Submitting | O32: Submitting by daven | R32: Pending | S32: =IF(H32="","",IFERROR(IF(H32>5000000,30,IF(H32>=1000000,20,10))+IF(I32-TODAY()>14,30,IF(I32-TODAY()>=7,20,10))+IF(R32="Won",40,IF(R32="Lost",10,20)),"")) -> 40 | T32: =IF(OR(H32="",I32=""),"",IF(AND(H32>5000000,I32-TODAY()>10),"🚨 FLAG","—")) -> — | U32: =IF(S32="","",IF(S32>=70,"✅ Highly Recommended",IF(S32>=50,"🔶 Consider","❌ Low Priority"))) -> ❌ Low Priority | V32: C:\Users\admin\Desktop\BHM-PhilGeps\Agencies\June 18, 2026\DEPED - CBR_FISH\Grocery Items - fish.pdf
A33: 46193 | B33: 13062125 | C33: DEPARTMENT OF HEALTH - CARAGA | D33: Computer Consumables | E33: Inks | F33: CARAGA | G33: AGUSAN DEL NORTE | H33: 228600 | I33: 46195 | J33: 0.625 | K33: =IF(I33="","",I33-TODAY()) -> 2 | L33: =IF(I33="","",IF(I33-TODAY()<=3,"High",IF(I33-TODAY()<=7,"Medium","Low"))) -> High | N33: For Canvas | O33: For canvass by Ann | R33: Pending | S33: =IF(H33="","",IFERROR(IF(H33>5000000,30,IF(H33>=1000000,20,10))+IF(I33-TODAY()>14,30,IF(I33-TODAY()>=7,20,10))+IF(R33="Won",40,IF(R33="Lost",10,20)),"")) -> 40 | T33: =IF(OR(H33="",I33=""),"",IF(AND(H33>5000000,I33-TODAY()>10),"🚨 FLAG","—")) -> — | U33: =IF(S33="","",IF(S33>=70,"✅ Highly Recommended",IF(S33>=50,"🔶 Consider","❌ Low Priority"))) -> ❌ Low Priority | V33: C:\Users\admin\Desktop\PHILGEPS\13062125.pdf
A34: 46193 | B34: 13061994 | C34: DEPARTMENT OF HEALTH - CARAGA | D34: Office Supplies | E34: Office Supplies | F34: CARAGA | G34: AGUSAN DEL NORTE | H34: 453964.84 | I34: 46195 | J34: 0.625 | K34: =IF(I34="","",I34-TODAY()) -> 2 | L34: =IF(I34="","",IF(I34-TODAY()<=3,"High",IF(I34-TODAY()<=7,"Medium","Low"))) -> High | N34: For Checking | O34: For Checking by maam Astrid | R34: Pending | S34: =IF(H34="","",IFERROR(IF(H34>5000000,30,IF(H34>=1000000,20,10))+IF(I34-TODAY()>14,30,IF(I34-TODAY()>=7,20,10))+IF(R34="Won",40,IF(R34="Lost",10,20)),"")) -> 40 | T34: =IF(OR(H34="",I34=""),"",IF(AND(H34>5000000,I34-TODAY()>10),"🚨 FLAG","—")) -> — | U34: =IF(S34="","",IF(S34>=70,"✅ Highly Recommended",IF(S34>=50,"🔶 Consider","❌ Low Priority"))) -> ❌ Low Priority | V34: C:\Users\admin\Desktop\PHILGEPS\13061994.pdf
K35: =IF(I35="","",I35-TODAY()) | L35: =IF(I35="","",IF(I35-TODAY()<=3,"High",IF(I35-TODAY()<=7,"Medium","Low"))) | S35: =IF(H35="","",IFERROR(IF(H35>5000000,30,IF(H35>=1000000,20,10))+IF(I35-TODAY()>14,30,IF(I35-TODAY()>=7,20,10))+IF(R35="Won",40,IF(R35="Lost",10,20)),"")) | T35: =IF(OR(H35="",I35=""),"",IF(AND(H35>5000000,I35-TODAY()>10),"🚨 FLAG","—")) | U35: =IF(S35="","",IF(S35>=70,"✅ Highly Recommended",IF(S35>=50,"🔶 Consider","❌ Low Priority")))
K36: =IF(I36="","",I36-TODAY()) | L36: =IF(I36="","",IF(I36-TODAY()<=3,"High",IF(I36-TODAY()<=7,"Medium","Low"))) | S36: =IF(H36="","",IFERROR(IF(H36>5000000,30,IF(H36>=1000000,20,10))+IF(I36-TODAY()>14,30,IF(I36-TODAY()>=7,20,10))+IF(R36="Won",40,IF(R36="Lost",10,20)),"")) | T36: =IF(OR(H36="",I36=""),"",IF(AND(H36>5000000,I36-TODAY()>10),"🚨 FLAG","—")) | U36: =IF(S36="","",IF(S36>=70,"✅ Highly Recommended",IF(S36>=50,"🔶 Consider","❌ Low Priority")))
K37: =IF(I37="","",I37-TODAY()) | L37: =IF(I37="","",IF(I37-TODAY()<=3,"High",IF(I37-TODAY()<=7,"Medium","Low"))) | S37: =IF(H37="","",IFERROR(IF(H37>5000000,30,IF(H37>=1000000,20,10))+IF(I37-TODAY()>14,30,IF(I37-TODAY()>=7,20,10))+IF(R37="Won",40,IF(R37="Lost",10,20)),"")) | T37: =IF(OR(H37="",I37=""),"",IF(AND(H37>5000000,I37-TODAY()>10),"🚨 FLAG","—")) | U37: =IF(S37="","",IF(S37>=70,"✅ Highly Recommended",IF(S37>=50,"🔶 Consider","❌ Low Priority")))
K38: =IF(I38="","",I38-TODAY()) | L38: =IF(I38="","",IF(I38-TODAY()<=3,"High",IF(I38-TODAY()<=7,"Medium","Low"))) | S38: =IF(H38="","",IFERROR(IF(H38>5000000,30,IF(H38>=1000000,20,10))+IF(I38-TODAY()>14,30,IF(I38-TODAY()>=7,20,10))+IF(R38="Won",40,IF(R38="Lost",10,20)),"")) | T38: =IF(OR(H38="",I38=""),"",IF(AND(H38>5000000,I38-TODAY()>10),"🚨 FLAG","—")) | U38: =IF(S38="","",IF(S38>=70,"✅ Highly Recommended",IF(S38>=50,"🔶 Consider","❌ Low Priority")))
K39: =IF(I39="","",I39-TODAY()) | L39: =IF(I39="","",IF(I39-TODAY()<=3,"High",IF(I39-TODAY()<=7,"Medium","Low"))) | S39: =IF(H39="","",IFERROR(IF(H39>5000000,30,IF(H39>=1000000,20,10))+IF(I39-TODAY()>14,30,IF(I39-TODAY()>=7,20,10))+IF(R39="Won",40,IF(R39="Lost",10,20)),"")) | T39: =IF(OR(H39="",I39=""),"",IF(AND(H39>5000000,I39-TODAY()>10),"🚨 FLAG","—")) | U39: =IF(S39="","",IF(S39>=70,"✅ Highly Recommended",IF(S39>=50,"🔶 Consider","❌ Low Priority")))
K40: =IF(I40="","",I40-TODAY()) | L40: =IF(I40="","",IF(I40-TODAY()<=3,"High",IF(I40-TODAY()<=7,"Medium","Low"))) | S40: =IF(H40="","",IFERROR(IF(H40>5000000,30,IF(H40>=1000000,20,10))+IF(I40-TODAY()>14,30,IF(I40-TODAY()>=7,20,10))+IF(R40="Won",40,IF(R40="Lost",10,20)),"")) | T40: =IF(OR(H40="",I40=""),"",IF(AND(H40>5000000,I40-TODAY()>10),"🚨 FLAG","—")) | U40: =IF(S40="","",IF(S40>=70,"✅ Highly Recommended",IF(S40>=50,"🔶 Consider","❌ Low Priority")))
K41: =IF(I41="","",I41-TODAY()) | L41: =IF(I41="","",IF(I41-TODAY()<=3,"High",IF(I41-TODAY()<=7,"Medium","Low"))) | S41: =IF(H41="","",IFERROR(IF(H41>5000000,30,IF(H41>=1000000,20,10))+IF(I41-TODAY()>14,30,IF(I41-TODAY()>=7,20,10))+IF(R41="Won",40,IF(R41="Lost",10,20)),"")) | T41: =IF(OR(H41="",I41=""),"",IF(AND(H41>5000000,I41-TODAY()>10),"🚨 FLAG","—")) | U41: =IF(S41="","",IF(S41>=70,"✅ Highly Recommended",IF(S41>=50,"🔶 Consider","❌ Low Priority")))
K42: =IF(I42="","",I42-TODAY()) | L42: =IF(I42="","",IF(I42-TODAY()<=3,"High",IF(I42-TODAY()<=7,"Medium","Low"))) | S42: =IF(H42="","",IFERROR(IF(H42>5000000,30,IF(H42>=1000000,20,10))+IF(I42-TODAY()>14,30,IF(I42-TODAY()>=7,20,10))+IF(R42="Won",40,IF(R42="Lost",10,20)),"")) | T42: =IF(OR(H42="",I42=""),"",IF(AND(H42>5000000,I42-TODAY()>10),"🚨 FLAG","—")) | U42: =IF(S42="","",IF(S42>=70,"✅ Highly Recommended",IF(S42>=50,"🔶 Consider","❌ Low Priority")))
K43: =IF(I43="","",I43-TODAY()) | L43: =IF(I43="","",IF(I43-TODAY()<=3,"High",IF(I43-TODAY()<=7,"Medium","Low"))) | S43: =IF(H43="","",IFERROR(IF(H43>5000000,30,IF(H43>=1000000,20,10))+IF(I43-TODAY()>14,30,IF(I43-TODAY()>=7,20,10))+IF(R43="Won",40,IF(R43="Lost",10,20)),"")) | T43: =IF(OR(H43="",I43=""),"",IF(AND(H43>5000000,I43-TODAY()>10),"🚨 FLAG","—")) | U43: =IF(S43="","",IF(S43>=70,"✅ Highly Recommended",IF(S43>=50,"🔶 Consider","❌ Low Priority")))
K44: =IF(I44="","",I44-TODAY()) | L44: =IF(I44="","",IF(I44-TODAY()<=3,"High",IF(I44-TODAY()<=7,"Medium","Low"))) | S44: =IF(H44="","",IFERROR(IF(H44>5000000,30,IF(H44>=1000000,20,10))+IF(I44-TODAY()>14,30,IF(I44-TODAY()>=7,20,10))+IF(R44="Won",40,IF(R44="Lost",10,20)),"")) | T44: =IF(OR(H44="",I44=""),"",IF(AND(H44>5000000,I44-TODAY()>10),"🚨 FLAG","—")) | U44: =IF(S44="","",IF(S44>=70,"✅ Highly Recommended",IF(S44>=50,"🔶 Consider","❌ Low Priority")))
K45: =IF(I45="","",I45-TODAY()) | L45: =IF(I45="","",IF(I45-TODAY()<=3,"High",IF(I45-TODAY()<=7,"Medium","Low"))) | S45: =IF(H45="","",IFERROR(IF(H45>5000000,30,IF(H45>=1000000,20,10))+IF(I45-TODAY()>14,30,IF(I45-TODAY()>=7,20,10))+IF(R45="Won",40,IF(R45="Lost",10,20)),"")) | T45: =IF(OR(H45="",I45=""),"",IF(AND(H45>5000000,I45-TODAY()>10),"🚨 FLAG","—")) | U45: =IF(S45="","",IF(S45>=70,"✅ Highly Recommended",IF(S45>=50,"🔶 Consider","❌ Low Priority")))
K46: =IF(I46="","",I46-TODAY()) | L46: =IF(I46="","",IF(I46-TODAY()<=3,"High",IF(I46-TODAY()<=7,"Medium","Low"))) | S46: =IF(H46="","",IFERROR(IF(H46>5000000,30,IF(H46>=1000000,20,10))+IF(I46-TODAY()>14,30,IF(I46-TODAY()>=7,20,10))+IF(R46="Won",40,IF(R46="Lost",10,20)),"")) | T46: =IF(OR(H46="",I46=""),"",IF(AND(H46>5000000,I46-TODAY()>10),"🚨 FLAG","—")) | U46: =IF(S46="","",IF(S46>=70,"✅ Highly Recommended",IF(S46>=50,"🔶 Consider","❌ Low Priority")))
... K200: =IF(I200="","",I200-TODAY()) | L200: =IF(I200="","",IF(I200-TODAY()<=3,"High",IF(I200-TODAY()<=7,"Medium","Low"))) | S200: =IF(H200="","",IFERROR(IF(H200>5000000,30,IF(H200>=1000000,20,10))+IF(I200-TODAY()>14,30,IF(I200-TODAY()>=7,20,10))+IF(R200="Won",40,IF(R200="Lost",10,20)),"")) | T200: =IF(OR(H200="",I200=""),"",IF(AND(H200>5000000,I200-TODAY()>10),"🚨 FLAG","—")) | U200: =IF(S200="","",IF(S200>=70,"✅ Highly Recommended",IF(S200>=50,"🔶 Consider","❌ Low Priority")))

Sheet Search & Filter
A1: 🔍 SEARCH & FILTER — PhilGEPS Bid Monitoring
A2: ℹ️ Select filters below using the dropdowns. The results table and summary cards update automatically based on your selection.
B3: STATUS FILTER | C3: PRIORITY FILTER | D3: REGION FILTER | E3: CATEGORY FILTER | F3: RESULT FILTER
B4: All | C4: All | D4: All | E4: Other | F4: All
A6: 📊 FILTERED RESULTS SUMMARY
A7: 🔍 | C7: 💰 | E7: 🔥 | G7: 📤 | I7: 🏆
A8: MATCHING BIDS | C8: TOTAL ABC VALUE | E8: ACTIVE / URGENT | G8: SUBMITTED | I8: AWARDED / WON
A9: =IFERROR(COUNTIFS('Bid Monitoring'!B3:B200,"<>",'Bid Monitoring'!N3:N200,IF(B4="All","*",B4),'Bid Monitoring'!L3:L200,IF(C4="All","<>""",C4),'Bid Monitoring'!F3:F200,IF(D4="All","*",D4),'Bid Monitoring'!E3:E200,IF(E4="All","*",E4),'Bid Monitoring'!R3:R200,IF(F4="All","*",F4)),0) -> 0 | C9: =IFERROR(SUMPRODUCT(('Bid Monitoring'!B3:B200<>"")*(IF(B4="All",1,'Bid Monitoring'!N3:N200=B4))*(IF(C4="All",1,'Bid Monitoring'!L3:L200=C4))*(IF(D4="All",1,'Bid Monitoring'!F3:F200=D4))*(IF(E4="All",1,'Bid Monitoring'!E3:E200=E4))*(IF(F4="All",1,'Bid Monitoring'!R3:R200=F4))*'Bid Monitoring'!H3:H200),0) -> 0 | E9: =IFERROR(COUNTIFS('Bid Monitoring'!B3:B200,"<>",'Bid Monitoring'!N3:N200,IF(B4="All","*",B4),'Bid Monitoring'!L3:L200,IF(C4="All","<>""",C4),'Bid Monitoring'!F3:F200,IF(D4="All","*",D4),'Bid Monitoring'!E3:E200,IF(E4="All","*",E4),'Bid Monitoring'!R3:R200,IF(F4="All","*",F4),'Bid Monitoring'!L3:L200,"High"),0) -> 0 | G9: =IFERROR(COUNTIFS('Bid Monitoring'!B3:B200,"<>",'Bid Monitoring'!N3:N200,IF(B4="All","*",B4),'Bid Monitoring'!L3:L200,IF(C4="All","<>""",C4),'Bid Monitoring'!F3:F200,IF(D4="All","*",D4),'Bid Monitoring'!E3:E200,IF(E4="All","*",E4),'Bid Monitoring'!R3:R200,IF(F4="All","*",F4),'Bid Monitoring'!N3:N200,"Submitted"),0) -> 0 | I9: =IFERROR(COUNTIFS('Bid Monitoring'!B3:B200,"<>",'Bid Monitoring'!N3:N200,IF(B4="All","*",B4),'Bid Monitoring'!L3:L200,IF(C4="All","<>""",C4),'Bid Monitoring'!F3:F200,IF(D4="All","*",D4),'Bid Monitoring'!E3:E200,IF(E4="All","*",E4),'Bid Monitoring'!R3:R200,IF(F4="All","*",F4),'Bid Monitoring'!N3:N200,"Awarded"),0) -> 0
A11: 📋 FILTERED BID LIST (All matching rows shown below)
A12: Ref # | B12: Project Title | C12: Procuring Entity | D12: Category | E12: Region | F12: ABC (₱) | G12: Closing Date | H12: Days Left | I12: Status | J12: Priority
A13: =IF(AND('Bid Monitoring'!B3<>"",IF(B4="All",TRUE(),'Bid Monitoring'!N3=B4),IF(C4="All",TRUE(),'Bid Monitoring'!L3=C4),IF(D4="All",TRUE(),'Bid Monitoring'!F3=D4),IF(E4="All",TRUE(),'Bid Monitoring'!E3=E4),IF(F4="All",TRUE(),'Bid Monitoring'!R3=F4)),'Bid Monitoring'!B3,"") | B13: =IF(AND('Bid Monitoring'!B3<>"",IF(B4="All",TRUE(),'Bid Monitoring'!N3=B4),IF(C4="All",TRUE(),'Bid Monitoring'!L3=C4),IF(D4="All",TRUE(),'Bid Monitoring'!F3=D4),IF(E4="All",TRUE(),'Bid Monitoring'!E3=E4),IF(F4="All",TRUE(),'Bid Monitoring'!R3=F4)),'Bid Monitoring'!D3,"") | C13: =IF(AND('Bid Monitoring'!B3<>"",IF(B4="All",TRUE(),'Bid Monitoring'!N3=B4),IF(C4="All",TRUE(),'Bid Monitoring'!L3=C4),IF(D4="All",TRUE(),'Bid Monitoring'!F3=D4),IF(E4="All",TRUE(),'Bid Monitoring'!E3=E4),IF(F4="All",TRUE(),'Bid Monitoring'!R3=F4)),'Bid Monitoring'!C3,"") | D13: =IF(AND('Bid Monitoring'!B3<>"",IF(B4="All",TRUE(),'Bid Monitoring'!N3=B4),IF(C4="All",TRUE(),'Bid Monitoring'!L3=C4),IF(D4="All",TRUE(),'Bid Monitoring'!F3=D4),IF(E4="All",TRUE(),'Bid Monitoring'!E3=E4),IF(F4="All",TRUE(),'Bid Monitoring'!R3=F4)),'Bid Monitoring'!E3,"") | E13: =IF(AND('Bid Monitoring'!B3<>"",IF(B4="All",TRUE(),'Bid Monitoring'!N3=B4),IF(C4="All",TRUE(),'Bid Monitoring'!L3=C4),IF(D4="All",TRUE(),'Bid Monitoring'!F3=D4),IF(E4="All",TRUE(),'Bid Monitoring'!E3=E4),IF(F4="All",TRUE(),'Bid Monitoring'!R3=F4)),'Bid Monitoring'!F3,"") | F13: =IF(AND('Bid Monitoring'!B3<>"",IF(B4="All",TRUE(),'Bid Monitoring'!N3=B4),IF(C4="All",TRUE(),'Bid Monitoring'!L3=C4),IF(D4="All",TRUE(),'Bid Monitoring'!F3=D4),IF(E4="All",TRUE(),'Bid Monitoring'!E3=E4),IF(F4="All",TRUE(),'Bid Monitoring'!R3=F4)),'Bid Monitoring'!H3,"") | G13: =IF(AND('Bid Monitoring'!B3<>"",IF(B4="All",TRUE(),'Bid Monitoring'!N3=B4),IF(C4="All",TRUE(),'Bid Monitoring'!L3=C4),IF(D4="All",TRUE(),'Bid Monitoring'!F3=D4),IF(E4="All",TRUE(),'Bid Monitoring'!E3=E4),IF(F4="All",TRUE(),'Bid Monitoring'!R3=F4)),'Bid Monitoring'!I3,"") | H13: =IF(AND('Bid Monitoring'!B3<>"",IF(B4="All",TRUE(),'Bid Monitoring'!N3=B4),IF(C4="All",TRUE(),'Bid Monitoring'!L3=C4),IF(D4="All",TRUE(),'Bid Monitoring'!F3=D4),IF(E4="All",TRUE(),'Bid Monitoring'!E3=E4),IF(F4="All",TRUE(),'Bid Monitoring'!R3=F4)),'Bid Monitoring'!K3,"") | I13: =IF(AND('Bid Monitoring'!B3<>"",IF(B4="All",TRUE(),'Bid Monitoring'!N3=B4),IF(C4="All",TRUE(),'Bid Monitoring'!L3=C4),IF(D4="All",TRUE(),'Bid Monitoring'!F3=D4),IF(E4="All",TRUE(),'Bid Monitoring'!E3=E4),IF(F4="All",TRUE(),'Bid Monitoring'!R3=F4)),'Bid Monitoring'!N3,"") | J13: =IF(AND('Bid Monitoring'!B3<>"",IF(B4="All",TRUE(),'Bid Monitoring'!N3=B4),IF(C4="All",TRUE(),'Bid Monitoring'!L3=C4),IF(D4="All",TRUE(),'Bid Monitoring'!F3=D4),IF(E4="All",TRUE(),'Bid Monitoring'!E3=E4),IF(F4="All",TRUE(),'Bid Monitoring'!R3=F4)),'Bid Monitoring'!L3,"")
A14: =IF(AND('Bid Monitoring'!B4<>"",IF(B4="All",TRUE(),'Bid Monitoring'!N4=B4),IF(C4="All",TRUE(),'Bid Monitoring'!L4=C4),IF(D4="All",TRUE(),'Bid Monitoring'!F4=D4),IF(E4="All",TRUE(),'Bid Monitoring'!E4=E4),IF(F4="All",TRUE(),'Bid Monitoring'!R4=F4)),'Bid Monitoring'!B4,"") | B14: =IF(AND('Bid Monitoring'!B4<>"",IF(B4="All",TRUE(),'Bid Monitoring'!N4=B4),IF(C4="All",TRUE(),'Bid Monitoring'!L4=C4),IF(D4="All",TRUE(),'Bid Monitoring'!F4=D4),IF(E4="All",TRUE(),'Bid Monitoring'!E4=E4),IF(F4="All",TRUE(),'Bid Monitoring'!R4=F4)),'Bid Monitoring'!D4,"") | C14: =IF(AND('Bid Monitoring'!B4<>"",IF(B4="All",TRUE(),'Bid Monitoring'!N4=B4),IF(C4="All",TRUE(),'Bid Monitoring'!L4=C4),IF(D4="All",TRUE(),'Bid Monitoring'!F4=D4),IF(E4="All",TRUE(),'Bid Monitoring'!E4=E4),IF(F4="All",TRUE(),'Bid Monitoring'!R4=F4)),'Bid Monitoring'!C4,"") | D14: =IF(AND('Bid Monitoring'!B4<>"",IF(B4="All",TRUE(),'Bid Monitoring'!N4=B4),IF(C4="All",TRUE(),'Bid Monitoring'!L4=C4),IF(D4="All",TRUE(),'Bid Monitoring'!F4=D4),IF(E4="All",TRUE(),'Bid Monitoring'!E4=E4),IF(F4="All",TRUE(),'Bid Monitoring'!R4=F4)),'Bid Monitoring'!E4,"") | E14: =IF(AND('Bid Monitoring'!B4<>"",IF(B4="All",TRUE(),'Bid Monitoring'!N4=B4),IF(C4="All",TRUE(),'Bid Monitoring'!L4=C4),IF(D4="All",TRUE(),'Bid Monitoring'!F4=D4),IF(E4="All",TRUE(),'Bid Monitoring'!E4=E4),IF(F4="All",TRUE(),'Bid Monitoring'!R4=F4)),'Bid Monitoring'!F4,"") | F14: =IF(AND('Bid Monitoring'!B4<>"",IF(B4="All",TRUE(),'Bid Monitoring'!N4=B4),IF(C4="All",TRUE(),'Bid Monitoring'!L4=C4),IF(D4="All",TRUE(),'Bid Monitoring'!F4=D4),IF(E4="All",TRUE(),'Bid Monitoring'!E4=E4),IF(F4="All",TRUE(),'Bid Monitoring'!R4=F4)),'Bid Monitoring'!H4,"") | G14: =IF(AND('Bid Monitoring'!B4<>"",IF(B4="All",TRUE(),'Bid Monitoring'!N4=B4),IF(C4="All",TRUE(),'Bid Monitoring'!L4=C4),IF(D4="All",TRUE(),'Bid Monitoring'!F4=D4),IF(E4="All",TRUE(),'Bid Monitoring'!E4=E4),IF(F4="All",TRUE(),'Bid Monitoring'!R4=F4)),'Bid Monitoring'!I4,"") | H14: =IF(AND('Bid Monitoring'!B4<>"",IF(B4="All",TRUE(),'Bid Monitoring'!N4=B4),IF(C4="All",TRUE(),'Bid Monitoring'!L4=C4),IF(D4="All",TRUE(),'Bid Monitoring'!F4=D4),IF(E4="All",TRUE(),'Bid Monitoring'!E4=E4),IF(F4="All",TRUE(),'Bid Monitoring'!R4=F4)),'Bid Monitoring'!K4,"") | I14: =IF(AND('Bid Monitoring'!B4<>"",IF(B4="All",TRUE(),'Bid Monitoring'!N4=B4),IF(C4="All",TRUE(),'Bid Monitoring'!L4=C4),IF(D4="All",TRUE(),'Bid Monitoring'!F4=D4),IF(E4="All",TRUE(),'Bid Monitoring'!E4=E4),IF(F4="All",TRUE(),'Bid Monitoring'!R4=F4)),'Bid Monitoring'!N4,"") | J14: =IF(AND('Bid Monitoring'!B4<>"",IF(B4="All",TRUE(),'Bid Monitoring'!N4=B4),IF(C4="All",TRUE(),'Bid Monitoring'!L4=C4),IF(D4="All",TRUE(),'Bid Monitoring'!F4=D4),IF(E4="All",TRUE(),'Bid Monitoring'!E4=E4),IF(F4="All",TRUE(),'Bid Monitoring'!R4=F4)),'Bid Monitoring'!L4,"")
A15: =IF(AND('Bid Monitoring'!B5<>"",IF(B4="All",TRUE(),'Bid Monitoring'!N5=B4),IF(C4="All",TRUE(),'Bid Monitoring'!L5=C4),IF(D4="All",TRUE(),'Bid Monitoring'!F5=D4),IF(E4="All",TRUE(),'Bid Monitoring'!E5=E4),IF(F4="All",TRUE(),'Bid Monitoring'!R5=F4)),'Bid Monitoring'!B5,"") | B15: =IF(AND('Bid Monitoring'!B5<>"",IF(B4="All",TRUE(),'Bid Monitoring'!N5=B4),IF(C4="All",TRUE(),'Bid Monitoring'!L5=C4),IF(D4="All",TRUE(),'Bid Monitoring'!F5=D4),IF(E4="All",TRUE(),'Bid Monitoring'!E5=E4),IF(F4="All",TRUE(),'Bid Monitoring'!R5=F4)),'Bid Monitoring'!D5,"") | C15: =IF(AND('Bid Monitoring'!B5<>"",IF(B4="All",TRUE(),'Bid Monitoring'!N5=B4),IF(C4="All",TRUE(),'Bid Monitoring'!L5=C4),IF(D4="All",TRUE(),'Bid Monitoring'!F5=D4),IF(E4="All",TRUE(),'Bid Monitoring'!E5=E4),IF(F4="All",TRUE(),'Bid Monitoring'!R5=F4)),'Bid Monitoring'!C5,"") | D15: =IF(AND('Bid Monitoring'!B5<>"",IF(B4="All",TRUE(),'Bid Monitoring'!N5=B4),IF(C4="All",TRUE(),'Bid Monitoring'!L5=C4),IF(D4="All",TRUE(),'Bid Monitoring'!F5=D4),IF(E4="All",TRUE(),'Bid Monitoring'!E5=E4),IF(F4="All",TRUE(),'Bid Monitoring'!R5=F4)),'Bid Monitoring'!E5,"") | E15: =IF(AND('Bid Monitoring'!B5<>"",IF(B4="All",TRUE(),'Bid Monitoring'!N5=B4),IF(C4="All",TRUE(),'Bid Monitoring'!L5=C4),IF(D4="All",TRUE(),'Bid Monitoring'!F5=D4),IF(E4="All",TRUE(),'Bid Monitoring'!E5=E4),IF(F4="All",TRUE(),'Bid Monitoring'!R5=F4)),'Bid Monitoring'!F5,"") | F15: =IF(AND('Bid Monitoring'!B5<>"",IF(B4="All",TRUE(),'Bid Monitoring'!N5=B4),IF(C4="All",TRUE(),'Bid Monitoring'!L5=C4),IF(D4="All",TRUE(),'Bid Monitoring'!F5=D4),IF(E4="All",TRUE(),'Bid Monitoring'!E5=E4),IF(F4="All",TRUE(),'Bid Monitoring'!R5=F4)),'Bid Monitoring'!H5,"") | G15: =IF(AND('Bid Monitoring'!B5<>"",IF(B4="All",TRUE(),'Bid Monitoring'!N5=B4),IF(C4="All",TRUE(),'Bid Monitoring'!L5=C4),IF(D4="All",TRUE(),'Bid Monitoring'!F5=D4),IF(E4="All",TRUE(),'Bid Monitoring'!E5=E4),IF(F4="All",TRUE(),'Bid Monitoring'!R5=F4)),'Bid Monitoring'!I5,"") | H15: =IF(AND('Bid Monitoring'!B5<>"",IF(B4="All",TRUE(),'Bid Monitoring'!N5=B4),IF(C4="All",TRUE(),'Bid Monitoring'!L5=C4),IF(D4="All",TRUE(),'Bid Monitoring'!F5=D4),IF(E4="All",TRUE(),'Bid Monitoring'!E5=E4),IF(F4="All",TRUE(),'Bid Monitoring'!R5=F4)),'Bid Monitoring'!K5,"") | I15: =IF(AND('Bid Monitoring'!B5<>"",IF(B4="All",TRUE(),'Bid Monitoring'!N5=B4),IF(C4="All",TRUE(),'Bid Monitoring'!L5=C4),IF(D4="All",TRUE(),'Bid Monitoring'!F5=D4),IF(E4="All",TRUE(),'Bid Monitoring'!E5=E4),IF(F4="All",TRUE(),'Bid Monitoring'!R5=F4)),'Bid Monitoring'!N5,"") | J15: =IF(AND('Bid Monitoring'!B5<>"",IF(B4="All",TRUE(),'Bid Monitoring'!N5=B4),IF(C4="All",TRUE(),'Bid Monitoring'!L5=C4),IF(D4="All",TRUE(),'Bid Monitoring'!F5=D4),IF(E4="All",TRUE(),'Bid Monitoring'!E5=E4),IF(F4="All",TRUE(),'Bid Monitoring'!R5=F4)),'Bid Monitoring'!L5,"")
A16: =IF(AND('Bid Monitoring'!B6<>"",IF(B4="All",TRUE(),'Bid Monitoring'!N6=B4),IF(C4="All",TRUE(),'Bid Monitoring'!L6=C4),IF(D4="All",TRUE(),'Bid Monitoring'!F6=D4),IF(E4="All",TRUE(),'Bid Monitoring'!E6=E4),IF(F4="All",TRUE(),'Bid Monitoring'!R6=F4)),'Bid Monitoring'!B6,"") | B16: =IF(AND('Bid Monitoring'!B6<>"",IF(B4="All",TRUE(),'Bid Monitoring'!N6=B4),IF(C4="All",TRUE(),'Bid Monitoring'!L6=C4),IF(D4="All",TRUE(),'Bid Monitoring'!F6=D4),IF(E4="All",TRUE(),'Bid Monitoring'!E6=E4),IF(F4="All",TRUE(),'Bid Monitoring'!R6=F4)),'Bid Monitoring'!D6,"") | C16: =IF(AND('Bid Monitoring'!B6<>"",IF(B4="All",TRUE(),'Bid Monitoring'!N6=B4),IF(C4="All",TRUE(),'Bid Monitoring'!L6=C4),IF(D4="All",TRUE(),'Bid Monitoring'!F6=D4),IF(E4="All",TRUE(),'Bid Monitoring'!E6=E4),IF(F4="All",TRUE(),'Bid Monitoring'!R6=F4)),'Bid Monitoring'!C6,"") | D16: =IF(AND('Bid Monitoring'!B6<>"",IF(B4="All",TRUE(),'Bid Monitoring'!N6=B4),IF(C4="All",TRUE(),'Bid Monitoring'!L6=C4),IF(D4="All",TRUE(),'Bid Monitoring'!F6=D4),IF(E4="All",TRUE(),'Bid Monitoring'!E6=E4),IF(F4="All",TRUE(),'Bid Monitoring'!R6=F4)),'Bid Monitoring'!E6,"") | E16: =IF(AND('Bid Monitoring'!B6<>"",IF(B4="All",TRUE(),'Bid Monitoring'!N6=B4),IF(C4="All",TRUE(),'Bid Monitoring'!L6=C4),IF(D4="All",TRUE(),'Bid Monitoring'!F6=D4),IF(E4="All",TRUE(),'Bid Monitoring'!E6=E4),IF(F4="All",TRUE(),'Bid Monitoring'!R6=F4)),'Bid Monitoring'!F6,"") | F16: =IF(AND('Bid Monitoring'!B6<>"",IF(B4="All",TRUE(),'Bid Monitoring'!N6=B4),IF(C4="All",TRUE(),'Bid Monitoring'!L6=C4),IF(D4="All",TRUE(),'Bid Monitoring'!F6=D4),IF(E4="All",TRUE(),'Bid Monitoring'!E6=E4),IF(F4="All",TRUE(),'Bid Monitoring'!R6=F4)),'Bid Monitoring'!H6,"") | G16: =IF(AND('Bid Monitoring'!B6<>"",IF(B4="All",TRUE(),'Bid Monitoring'!N6=B4),IF(C4="All",TRUE(),'Bid Monitoring'!L6=C4),IF(D4="All",TRUE(),'Bid Monitoring'!F6=D4),IF(E4="All",TRUE(),'Bid Monitoring'!E6=E4),IF(F4="All",TRUE(),'Bid Monitoring'!R6=F4)),'Bid Monitoring'!I6,"") | H16: =IF(AND('Bid Monitoring'!B6<>"",IF(B4="All",TRUE(),'Bid Monitoring'!N6=B4),IF(C4="All",TRUE(),'Bid Monitoring'!L6=C4),IF(D4="All",TRUE(),'Bid Monitoring'!F6=D4),IF(E4="All",TRUE(),'Bid Monitoring'!E6=E4),IF(F4="All",TRUE(),'Bid Monitoring'!R6=F4)),'Bid Monitoring'!K6,"") | I16: =IF(AND('Bid Monitoring'!B6<>"",IF(B4="All",TRUE(),'Bid Monitoring'!N6=B4),IF(C4="All",TRUE(),'Bid Monitoring'!L6=C4),IF(D4="All",TRUE(),'Bid Monitoring'!F6=D4),IF(E4="All",TRUE(),'Bid Monitoring'!E6=E4),IF(F4="All",TRUE(),'Bid Monitoring'!R6=F4)),'Bid Monitoring'!N6,"") | J16: =IF(AND('Bid Monitoring'!B6<>"",IF(B4="All",TRUE(),'Bid Monitoring'!N6=B4),IF(C4="All",TRUE(),'Bid Monitoring'!L6=C4),IF(D4="All",TRUE(),'Bid Monitoring'!F6=D4),IF(E4="All",TRUE(),'Bid Monitoring'!E6=E4),IF(F4="All",TRUE(),'Bid Monitoring'!R6=F4)),'Bid Monitoring'!L6,"")
A17: =IF(AND('Bid Monitoring'!B7<>"",IF(B4="All",TRUE(),'Bid Monitoring'!N7=B4),IF(C4="All",TRUE(),'Bid Monitoring'!L7=C4),IF(D4="All",TRUE(),'Bid Monitoring'!F7=D4),IF(E4="All",TRUE(),'Bid Monitoring'!E7=E4),IF(F4="All",TRUE(),'Bid Monitoring'!R7=F4)),'Bid Monitoring'!B7,"") | B17: =IF(AND('Bid Monitoring'!B7<>"",IF(B4="All",TRUE(),'Bid Monitoring'!N7=B4),IF(C4="All",TRUE(),'Bid Monitoring'!L7=C4),IF(D4="All",TRUE(),'Bid Monitoring'!F7=D4),IF(E4="All",TRUE(),'Bid Monitoring'!E7=E4),IF(F4="All",TRUE(),'Bid Monitoring'!R7=F4)),'Bid Monitoring'!D7,"") | C17: =IF(AND('Bid Monitoring'!B7<>"",IF(B4="All",TRUE(),'Bid Monitoring'!N7=B4),IF(C4="All",TRUE(),'Bid Monitoring'!L7=C4),IF(D4="All",TRUE(),'Bid Monitoring'!F7=D4),IF(E4="All",TRUE(),'Bid Monitoring'!E7=E4),IF(F4="All",TRUE(),'Bid Monitoring'!R7=F4)),'Bid Monitoring'!C7,"") | D17: =IF(AND('Bid Monitoring'!B7<>"",IF(B4="All",TRUE(),'Bid Monitoring'!N7=B4),IF(C4="All",TRUE(),'Bid Monitoring'!L7=C4),IF(D4="All",TRUE(),'Bid Monitoring'!F7=D4),IF(E4="All",TRUE(),'Bid Monitoring'!E7=E4),IF(F4="All",TRUE(),'Bid Monitoring'!R7=F4)),'Bid Monitoring'!E7,"") | E17: =IF(AND('Bid Monitoring'!B7<>"",IF(B4="All",TRUE(),'Bid Monitoring'!N7=B4),IF(C4="All",TRUE(),'Bid Monitoring'!L7=C4),IF(D4="All",TRUE(),'Bid Monitoring'!F7=D4),IF(E4="All",TRUE(),'Bid Monitoring'!E7=E4),IF(F4="All",TRUE(),'Bid Monitoring'!R7=F4)),'Bid Monitoring'!F7,"") | F17: =IF(AND('Bid Monitoring'!B7<>"",IF(B4="All",TRUE(),'Bid Monitoring'!N7=B4),IF(C4="All",TRUE(),'Bid Monitoring'!L7=C4),IF(D4="All",TRUE(),'Bid Monitoring'!F7=D4),IF(E4="All",TRUE(),'Bid Monitoring'!E7=E4),IF(F4="All",TRUE(),'Bid Monitoring'!R7=F4)),'Bid Monitoring'!H7,"") | G17: =IF(AND('Bid Monitoring'!B7<>"",IF(B4="All",TRUE(),'Bid Monitoring'!N7=B4),IF(C4="All",TRUE(),'Bid Monitoring'!L7=C4),IF(D4="All",TRUE(),'Bid Monitoring'!F7=D4),IF(E4="All",TRUE(),'Bid Monitoring'!E7=E4),IF(F4="All",TRUE(),'Bid Monitoring'!R7=F4)),'Bid Monitoring'!I7,"") | H17: =IF(AND('Bid Monitoring'!B7<>"",IF(B4="All",TRUE(),'Bid Monitoring'!N7=B4),IF(C4="All",TRUE(),'Bid Monitoring'!L7=C4),IF(D4="All",TRUE(),'Bid Monitoring'!F7=D4),IF(E4="All",TRUE(),'Bid Monitoring'!E7=E4),IF(F4="All",TRUE(),'Bid Monitoring'!R7=F4)),'Bid Monitoring'!K7,"") | I17: =IF(AND('Bid Monitoring'!B7<>"",IF(B4="All",TRUE(),'Bid Monitoring'!N7=B4),IF(C4="All",TRUE(),'Bid Monitoring'!L7=C4),IF(D4="All",TRUE(),'Bid Monitoring'!F7=D4),IF(E4="All",TRUE(),'Bid Monitoring'!E7=E4),IF(F4="All",TRUE(),'Bid Monitoring'!R7=F4)),'Bid Monitoring'!N7,"") | J17: =IF(AND('Bid Monitoring'!B7<>"",IF(B4="All",TRUE(),'Bid Monitoring'!N7=B4),IF(C4="All",TRUE(),'Bid Monitoring'!L7=C4),IF(D4="All",TRUE(),'Bid Monitoring'!F7=D4),IF(E4="All",TRUE(),'Bid Monitoring'!E7=E4),IF(F4="All",TRUE(),'Bid Monitoring'!R7=F4)),'Bid Monitoring'!L7,"")
A18: =IF(AND('Bid Monitoring'!B8<>"",IF(B4="All",TRUE(),'Bid Monitoring'!N8=B4),IF(C4="All",TRUE(),'Bid Monitoring'!L8=C4),IF(D4="All",TRUE(),'Bid Monitoring'!F8=D4),IF(E4="All",TRUE(),'Bid Monitoring'!E8=E4),IF(F4="All",TRUE(),'Bid Monitoring'!R8=F4)),'Bid Monitoring'!B8,"") | B18: =IF(AND('Bid Monitoring'!B8<>"",IF(B4="All",TRUE(),'Bid Monitoring'!N8=B4),IF(C4="All",TRUE(),'Bid Monitoring'!L8=C4),IF(D4="All",TRUE(),'Bid Monitoring'!F8=D4),IF(E4="All",TRUE(),'Bid Monitoring'!E8=E4),IF(F4="All",TRUE(),'Bid Monitoring'!R8=F4)),'Bid Monitoring'!D8,"") | C18: =IF(AND('Bid Monitoring'!B8<>"",IF(B4="All",TRUE(),'Bid Monitoring'!N8=B4),IF(C4="All",TRUE(),'Bid Monitoring'!L8=C4),IF(D4="All",TRUE(),'Bid Monitoring'!F8=D4),IF(E4="All",TRUE(),'Bid Monitoring'!E8=E4),IF(F4="All",TRUE(),'Bid Monitoring'!R8=F4)),'Bid Monitoring'!C8,"") | D18: =IF(AND('Bid Monitoring'!B8<>"",IF(B4="All",TRUE(),'Bid Monitoring'!N8=B4),IF(C4="All",TRUE(),'Bid Monitoring'!L8=C4),IF(D4="All",TRUE(),'Bid Monitoring'!F8=D4),IF(E4="All",TRUE(),'Bid Monitoring'!E8=E4),IF(F4="All",TRUE(),'Bid Monitoring'!R8=F4)),'Bid Monitoring'!E8,"") | E18: =IF(AND('Bid Monitoring'!B8<>"",IF(B4="All",TRUE(),'Bid Monitoring'!N8=B4),IF(C4="All",TRUE(),'Bid Monitoring'!L8=C4),IF(D4="All",TRUE(),'Bid Monitoring'!F8=D4),IF(E4="All",TRUE(),'Bid Monitoring'!E8=E4),IF(F4="All",TRUE(),'Bid Monitoring'!R8=F4)),'Bid Monitoring'!F8,"") | F18: =IF(AND('Bid Monitoring'!B8<>"",IF(B4="All",TRUE(),'Bid Monitoring'!N8=B4),IF(C4="All",TRUE(),'Bid Monitoring'!L8=C4),IF(D4="All",TRUE(),'Bid Monitoring'!F8=D4),IF(E4="All",TRUE(),'Bid Monitoring'!E8=E4),IF(F4="All",TRUE(),'Bid Monitoring'!R8=F4)),'Bid Monitoring'!H8,"") | G18: =IF(AND('Bid Monitoring'!B8<>"",IF(B4="All",TRUE(),'Bid Monitoring'!N8=B4),IF(C4="All",TRUE(),'Bid Monitoring'!L8=C4),IF(D4="All",TRUE(),'Bid Monitoring'!F8=D4),IF(E4="All",TRUE(),'Bid Monitoring'!E8=E4),IF(F4="All",TRUE(),'Bid Monitoring'!R8=F4)),'Bid Monitoring'!I8,"") | H18: =IF(AND('Bid Monitoring'!B8<>"",IF(B4="All",TRUE(),'Bid Monitoring'!N8=B4),IF(C4="All",TRUE(),'Bid Monitoring'!L8=C4),IF(D4="All",TRUE(),'Bid Monitoring'!F8=D4),IF(E4="All",TRUE(),'Bid Monitoring'!E8=E4),IF(F4="All",TRUE(),'Bid Monitoring'!R8=F4)),'Bid Monitoring'!K8,"") | I18: =IF(AND('Bid Monitoring'!B8<>"",IF(B4="All",TRUE(),'Bid Monitoring'!N8=B4),IF(C4="All",TRUE(),'Bid Monitoring'!L8=C4),IF(D4="All",TRUE(),'Bid Monitoring'!F8=D4),IF(E4="All",TRUE(),'Bid Monitoring'!E8=E4),IF(F4="All",TRUE(),'Bid Monitoring'!R8=F4)),'Bid Monitoring'!N8,"") | J18: =IF(AND('Bid Monitoring'!B8<>"",IF(B4="All",TRUE(),'Bid Monitoring'!N8=B4),IF(C4="All",TRUE(),'Bid Monitoring'!L8=C4),IF(D4="All",TRUE(),'Bid Monitoring'!F8=D4),IF(E4="All",TRUE(),'Bid Monitoring'!E8=E4),IF(F4="All",TRUE(),'Bid Monitoring'!R8=F4)),'Bid Monitoring'!L8,"")
A19: =IF(AND('Bid Monitoring'!B9<>"",IF(B4="All",TRUE(),'Bid Monitoring'!N9=B4),IF(C4="All",TRUE(),'Bid Monitoring'!L9=C4),IF(D4="All",TRUE(),'Bid Monitoring'!F9=D4),IF(E4="All",TRUE(),'Bid Monitoring'!E9=E4),IF(F4="All",TRUE(),'Bid Monitoring'!R9=F4)),'Bid Monitoring'!B9,"") | B19: =IF(AND('Bid Monitoring'!B9<>"",IF(B4="All",TRUE(),'Bid Monitoring'!N9=B4),IF(C4="All",TRUE(),'Bid Monitoring'!L9=C4),IF(D4="All",TRUE(),'Bid Monitoring'!F9=D4),IF(E4="All",TRUE(),'Bid Monitoring'!E9=E4),IF(F4="All",TRUE(),'Bid Monitoring'!R9=F4)),'Bid Monitoring'!D9,"") | C19: =IF(AND('Bid Monitoring'!B9<>"",IF(B4="All",TRUE(),'Bid Monitoring'!N9=B4),IF(C4="All",TRUE(),'Bid Monitoring'!L9=C4),IF(D4="All",TRUE(),'Bid Monitoring'!F9=D4),IF(E4="All",TRUE(),'Bid Monitoring'!E9=E4),IF(F4="All",TRUE(),'Bid Monitoring'!R9=F4)),'Bid Monitoring'!C9,"") | D19: =IF(AND('Bid Monitoring'!B9<>"",IF(B4="All",TRUE(),'Bid Monitoring'!N9=B4),IF(C4="All",TRUE(),'Bid Monitoring'!L9=C4),IF(D4="All",TRUE(),'Bid Monitoring'!F9=D4),IF(E4="All",TRUE(),'Bid Monitoring'!E9=E4),IF(F4="All",TRUE(),'Bid Monitoring'!R9=F4)),'Bid Monitoring'!E9,"") | E19: =IF(AND('Bid Monitoring'!B9<>"",IF(B4="All",TRUE(),'Bid Monitoring'!N9=B4),IF(C4="All",TRUE(),'Bid Monitoring'!L9=C4),IF(D4="All",TRUE(),'Bid Monitoring'!F9=D4),IF(E4="All",TRUE(),'Bid Monitoring'!E9=E4),IF(F4="All",TRUE(),'Bid Monitoring'!R9=F4)),'Bid Monitoring'!F9,"") | F19: =IF(AND('Bid Monitoring'!B9<>"",IF(B4="All",TRUE(),'Bid Monitoring'!N9=B4),IF(C4="All",TRUE(),'Bid Monitoring'!L9=C4),IF(D4="All",TRUE(),'Bid Monitoring'!F9=D4),IF(E4="All",TRUE(),'Bid Monitoring'!E9=E4),IF(F4="All",TRUE(),'Bid Monitoring'!R9=F4)),'Bid Monitoring'!H9,"") | G19: =IF(AND('Bid Monitoring'!B9<>"",IF(B4="All",TRUE(),'Bid Monitoring'!N9=B4),IF(C4="All",TRUE(),'Bid Monitoring'!L9=C4),IF(D4="All",TRUE(),'Bid Monitoring'!F9=D4),IF(E4="All",TRUE(),'Bid Monitoring'!E9=E4),IF(F4="All",TRUE(),'Bid Monitoring'!R9=F4)),'Bid Monitoring'!I9,"") | H19: =IF(AND('Bid Monitoring'!B9<>"",IF(B4="All",TRUE(),'Bid Monitoring'!N9=B4),IF(C4="All",TRUE(),'Bid Monitoring'!L9=C4),IF(D4="All",TRUE(),'Bid Monitoring'!F9=D4),IF(E4="All",TRUE(),'Bid Monitoring'!E9=E4),IF(F4="All",TRUE(),'Bid Monitoring'!R9=F4)),'Bid Monitoring'!K9,"") | I19: =IF(AND('Bid Monitoring'!B9<>"",IF(B4="All",TRUE(),'Bid Monitoring'!N9=B4),IF(C4="All",TRUE(),'Bid Monitoring'!L9=C4),IF(D4="All",TRUE(),'Bid Monitoring'!F9=D4),IF(E4="All",TRUE(),'Bid Monitoring'!E9=E4),IF(F4="All",TRUE(),'Bid Monitoring'!R9=F4)),'Bid Monitoring'!N9,"") | J19: =IF(AND('Bid Monitoring'!B9<>"",IF(B4="All",TRUE(),'Bid Monitoring'!N9=B4),IF(C4="All",TRUE(),'Bid Monitoring'!L9=C4),IF(D4="All",TRUE(),'Bid Monitoring'!F9=D4),IF(E4="All",TRUE(),'Bid Monitoring'!E9=E4),IF(F4="All",TRUE(),'Bid Monitoring'!R9=F4)),'Bid Monitoring'!L9,"")
A20: =IF(AND('Bid Monitoring'!B10<>"",IF(B4="All",TRUE(),'Bid Monitoring'!N10=B4),IF(C4="All",TRUE(),'Bid Monitoring'!L10=C4),IF(D4="All",TRUE(),'Bid Monitoring'!F10=D4),IF(E4="All",TRUE(),'Bid Monitoring'!E10=E4),IF(F4="All",TRUE(),'Bid Monitoring'!R10=F4)),'Bid Monitoring'!B10,"") | B20: =IF(AND('Bid Monitoring'!B10<>"",IF(B4="All",TRUE(),'Bid Monitoring'!N10=B4),IF(C4="All",TRUE(),'Bid Monitoring'!L10=C4),IF(D4="All",TRUE(),'Bid Monitoring'!F10=D4),IF(E4="All",TRUE(),'Bid Monitoring'!E10=E4),IF(F4="All",TRUE(),'Bid Monitoring'!R10=F4)),'Bid Monitoring'!D10,"") | C20: =IF(AND('Bid Monitoring'!B10<>"",IF(B4="All",TRUE(),'Bid Monitoring'!N10=B4),IF(C4="All",TRUE(),'Bid Monitoring'!L10=C4),IF(D4="All",TRUE(),'Bid Monitoring'!F10=D4),IF(E4="All",TRUE(),'Bid Monitoring'!E10=E4),IF(F4="All",TRUE(),'Bid Monitoring'!R10=F4)),'Bid Monitoring'!C10,"") | D20: =IF(AND('Bid Monitoring'!B10<>"",IF(B4="All",TRUE(),'Bid Monitoring'!N10=B4),IF(C4="All",TRUE(),'Bid Monitoring'!L10=C4),IF(D4="All",TRUE(),'Bid Monitoring'!F10=D4),IF(E4="All",TRUE(),'Bid Monitoring'!E10=E4),IF(F4="All",TRUE(),'Bid Monitoring'!R10=F4)),'Bid Monitoring'!E10,"") | E20: =IF(AND('Bid Monitoring'!B10<>"",IF(B4="All",TRUE(),'Bid Monitoring'!N10=B4),IF(C4="All",TRUE(),'Bid Monitoring'!L10=C4),IF(D4="All",TRUE(),'Bid Monitoring'!F10=D4),IF(E4="All",TRUE(),'Bid Monitoring'!E10=E4),IF(F4="All",TRUE(),'Bid Monitoring'!R10=F4)),'Bid Monitoring'!F10,"") | F20: =IF(AND('Bid Monitoring'!B10<>"",IF(B4="All",TRUE(),'Bid Monitoring'!N10=B4),IF(C4="All",TRUE(),'Bid Monitoring'!L10=C4),IF(D4="All",TRUE(),'Bid Monitoring'!F10=D4),IF(E4="All",TRUE(),'Bid Monitoring'!E10=E4),IF(F4="All",TRUE(),'Bid Monitoring'!R10=F4)),'Bid Monitoring'!H10,"") | G20: =IF(AND('Bid Monitoring'!B10<>"",IF(B4="All",TRUE(),'Bid Monitoring'!N10=B4),IF(C4="All",TRUE(),'Bid Monitoring'!L10=C4),IF(D4="All",TRUE(),'Bid Monitoring'!F10=D4),IF(E4="All",TRUE(),'Bid Monitoring'!E10=E4),IF(F4="All",TRUE(),'Bid Monitoring'!R10=F4)),'Bid Monitoring'!I10,"") | H20: =IF(AND('Bid Monitoring'!B10<>"",IF(B4="All",TRUE(),'Bid Monitoring'!N10=B4),IF(C4="All",TRUE(),'Bid Monitoring'!L10=C4),IF(D4="All",TRUE(),'Bid Monitoring'!F10=D4),IF(E4="All",TRUE(),'Bid Monitoring'!E10=E4),IF(F4="All",TRUE(),'Bid Monitoring'!R10=F4)),'Bid Monitoring'!K10,"") | I20: =IF(AND('Bid Monitoring'!B10<>"",IF(B4="All",TRUE(),'Bid Monitoring'!N10=B4),IF(C4="All",TRUE(),'Bid Monitoring'!L10=C4),IF(D4="All",TRUE(),'Bid Monitoring'!F10=D4),IF(E4="All",TRUE(),'Bid Monitoring'!E10=E4),IF(F4="All",TRUE(),'Bid Monitoring'!R10=F4)),'Bid Monitoring'!N10,"") | J20: =IF(AND('Bid Monitoring'!B10<>"",IF(B4="All",TRUE(),'Bid Monitoring'!N10=B4),IF(C4="All",TRUE(),'Bid Monitoring'!L10=C4),IF(D4="All",TRUE(),'Bid Monitoring'!F10=D4),IF(E4="All",TRUE(),'Bid Monitoring'!E10=E4),IF(F4="All",TRUE(),'Bid Monitoring'!R10=F4)),'Bid Monitoring'!L10,"")
A21: =IF(AND('Bid Monitoring'!B11<>"",IF(B4="All",TRUE(),'Bid Monitoring'!N11=B4),IF(C4="All",TRUE(),'Bid Monitoring'!L11=C4),IF(D4="All",TRUE(),'Bid Monitoring'!F11=D4),IF(E4="All",TRUE(),'Bid Monitoring'!E11=E4),IF(F4="All",TRUE(),'Bid Monitoring'!R11=F4)),'Bid Monitoring'!B11,"") | B21: =IF(AND('Bid Monitoring'!B11<>"",IF(B4="All",TRUE(),'Bid Monitoring'!N11=B4),IF(C4="All",TRUE(),'Bid Monitoring'!L11=C4),IF(D4="All",TRUE(),'Bid Monitoring'!F11=D4),IF(E4="All",TRUE(),'Bid Monitoring'!E11=E4),IF(F4="All",TRUE(),'Bid Monitoring'!R11=F4)),'Bid Monitoring'!D11,"") | C21: =IF(AND('Bid Monitoring'!B11<>"",IF(B4="All",TRUE(),'Bid Monitoring'!N11=B4),IF(C4="All",TRUE(),'Bid Monitoring'!L11=C4),IF(D4="All",TRUE(),'Bid Monitoring'!F11=D4),IF(E4="All",TRUE(),'Bid Monitoring'!E11=E4),IF(F4="All",TRUE(),'Bid Monitoring'!R11=F4)),'Bid Monitoring'!C11,"") | D21: =IF(AND('Bid Monitoring'!B11<>"",IF(B4="All",TRUE(),'Bid Monitoring'!N11=B4),IF(C4="All",TRUE(),'Bid Monitoring'!L11=C4),IF(D4="All",TRUE(),'Bid Monitoring'!F11=D4),IF(E4="All",TRUE(),'Bid Monitoring'!E11=E4),IF(F4="All",TRUE(),'Bid Monitoring'!R11=F4)),'Bid Monitoring'!E11,"") | E21: =IF(AND('Bid Monitoring'!B11<>"",IF(B4="All",TRUE(),'Bid Monitoring'!N11=B4),IF(C4="All",TRUE(),'Bid Monitoring'!L11=C4),IF(D4="All",TRUE(),'Bid Monitoring'!F11=D4),IF(E4="All",TRUE(),'Bid Monitoring'!E11=E4),IF(F4="All",TRUE(),'Bid Monitoring'!R11=F4)),'Bid Monitoring'!F11,"") | F21: =IF(AND('Bid Monitoring'!B11<>"",IF(B4="All",TRUE(),'Bid Monitoring'!N11=B4),IF(C4="All",TRUE(),'Bid Monitoring'!L11=C4),IF(D4="All",TRUE(),'Bid Monitoring'!F11=D4),IF(E4="All",TRUE(),'Bid Monitoring'!E11=E4),IF(F4="All",TRUE(),'Bid Monitoring'!R11=F4)),'Bid Monitoring'!H11,"") | G21: =IF(AND('Bid Monitoring'!B11<>"",IF(B4="All",TRUE(),'Bid Monitoring'!N11=B4),IF(C4="All",TRUE(),'Bid Monitoring'!L11=C4),IF(D4="All",TRUE(),'Bid Monitoring'!F11=D4),IF(E4="All",TRUE(),'Bid Monitoring'!E11=E4),IF(F4="All",TRUE(),'Bid Monitoring'!R11=F4)),'Bid Monitoring'!I11,"") | H21: =IF(AND('Bid Monitoring'!B11<>"",IF(B4="All",TRUE(),'Bid Monitoring'!N11=B4),IF(C4="All",TRUE(),'Bid Monitoring'!L11=C4),IF(D4="All",TRUE(),'Bid Monitoring'!F11=D4),IF(E4="All",TRUE(),'Bid Monitoring'!E11=E4),IF(F4="All",TRUE(),'Bid Monitoring'!R11=F4)),'Bid Monitoring'!K11,"") | I21: =IF(AND('Bid Monitoring'!B11<>"",IF(B4="All",TRUE(),'Bid Monitoring'!N11=B4),IF(C4="All",TRUE(),'Bid Monitoring'!L11=C4),IF(D4="All",TRUE(),'Bid Monitoring'!F11=D4),IF(E4="All",TRUE(),'Bid Monitoring'!E11=E4),IF(F4="All",TRUE(),'Bid Monitoring'!R11=F4)),'Bid Monitoring'!N11,"") | J21: =IF(AND('Bid Monitoring'!B11<>"",IF(B4="All",TRUE(),'Bid Monitoring'!N11=B4),IF(C4="All",TRUE(),'Bid Monitoring'!L11=C4),IF(D4="All",TRUE(),'Bid Monitoring'!F11=D4),IF(E4="All",TRUE(),'Bid Monitoring'!E11=E4),IF(F4="All",TRUE(),'Bid Monitoring'!R11=F4)),'Bid Monitoring'!L11,"")
A22: =IF(AND('Bid Monitoring'!B12<>"",IF(B4="All",TRUE(),'Bid Monitoring'!N12=B4),IF(C4="All",TRUE(),'Bid Monitoring'!L12=C4),IF(D4="All",TRUE(),'Bid Monitoring'!F12=D4),IF(E4="All",TRUE(),'Bid Monitoring'!E12=E4),IF(F4="All",TRUE(),'Bid Monitoring'!R12=F4)),'Bid Monitoring'!B12,"") | B22: =IF(AND('Bid Monitoring'!B12<>"",IF(B4="All",TRUE(),'Bid Monitoring'!N12=B4),IF(C4="All",TRUE(),'Bid Monitoring'!L12=C4),IF(D4="All",TRUE(),'Bid Monitoring'!F12=D4),IF(E4="All",TRUE(),'Bid Monitoring'!E12=E4),IF(F4="All",TRUE(),'Bid Monitoring'!R12=F4)),'Bid Monitoring'!D12,"") | C22: =IF(AND('Bid Monitoring'!B12<>"",IF(B4="All",TRUE(),'Bid Monitoring'!N12=B4),IF(C4="All",TRUE(),'Bid Monitoring'!L12=C4),IF(D4="All",TRUE(),'Bid Monitoring'!F12=D4),IF(E4="All",TRUE(),'Bid Monitoring'!E12=E4),IF(F4="All",TRUE(),'Bid Monitoring'!R12=F4)),'Bid Monitoring'!C12,"") | D22: =IF(AND('Bid Monitoring'!B12<>"",IF(B4="All",TRUE(),'Bid Monitoring'!N12=B4),IF(C4="All",TRUE(),'Bid Monitoring'!L12=C4),IF(D4="All",TRUE(),'Bid Monitoring'!F12=D4),IF(E4="All",TRUE(),'Bid Monitoring'!E12=E4),IF(F4="All",TRUE(),'Bid Monitoring'!R12=F4)),'Bid Monitoring'!E12,"") | E22: =IF(AND('Bid Monitoring'!B12<>"",IF(B4="All",TRUE(),'Bid Monitoring'!N12=B4),IF(C4="All",TRUE(),'Bid Monitoring'!L12=C4),IF(D4="All",TRUE(),'Bid Monitoring'!F12=D4),IF(E4="All",TRUE(),'Bid Monitoring'!E12=E4),IF(F4="All",TRUE(),'Bid Monitoring'!R12=F4)),'Bid Monitoring'!F12,"") | F22: =IF(AND('Bid Monitoring'!B12<>"",IF(B4="All",TRUE(),'Bid Monitoring'!N12=B4),IF(C4="All",TRUE(),'Bid Monitoring'!L12=C4),IF(D4="All",TRUE(),'Bid Monitoring'!F12=D4),IF(E4="All",TRUE(),'Bid Monitoring'!E12=E4),IF(F4="All",TRUE(),'Bid Monitoring'!R12=F4)),'Bid Monitoring'!H12,"") | G22: =IF(AND('Bid Monitoring'!B12<>"",IF(B4="All",TRUE(),'Bid Monitoring'!N12=B4),IF(C4="All",TRUE(),'Bid Monitoring'!L12=C4),IF(D4="All",TRUE(),'Bid Monitoring'!F12=D4),IF(E4="All",TRUE(),'Bid Monitoring'!E12=E4),IF(F4="All",TRUE(),'Bid Monitoring'!R12=F4)),'Bid Monitoring'!I12,"") | H22: =IF(AND('Bid Monitoring'!B12<>"",IF(B4="All",TRUE(),'Bid Monitoring'!N12=B4),IF(C4="All",TRUE(),'Bid Monitoring'!L12=C4),IF(D4="All",TRUE(),'Bid Monitoring'!F12=D4),IF(E4="All",TRUE(),'Bid Monitoring'!E12=E4),IF(F4="All",TRUE(),'Bid Monitoring'!R12=F4)),'Bid Monitoring'!K12,"") | I22: =IF(AND('Bid Monitoring'!B12<>"",IF(B4="All",TRUE(),'Bid Monitoring'!N12=B4),IF(C4="All",TRUE(),'Bid Monitoring'!L12=C4),IF(D4="All",TRUE(),'Bid Monitoring'!F12=D4),IF(E4="All",TRUE(),'Bid Monitoring'!E12=E4),IF(F4="All",TRUE(),'Bid Monitoring'!R12=F4)),'Bid Monitoring'!N12,"") | J22: =IF(AND('Bid Monitoring'!B12<>"",IF(B4="All",TRUE(),'Bid Monitoring'!N12=B4),IF(C4="All",TRUE(),'Bid Monitoring'!L12=C4),IF(D4="All",TRUE(),'Bid Monitoring'!F12=D4),IF(E4="All",TRUE(),'Bid Monitoring'!E12=E4),IF(F4="All",TRUE(),'Bid Monitoring'!R12=F4)),'Bid Monitoring'!L12,"")
A23: =IF(AND('Bid Monitoring'!B13<>"",IF(B4="All",TRUE(),'Bid Monitoring'!N13=B4),IF(C4="All",TRUE(),'Bid Monitoring'!L13=C4),IF(D4="All",TRUE(),'Bid Monitoring'!F13=D4),IF(E4="All",TRUE(),'Bid Monitoring'!E13=E4),IF(F4="All",TRUE(),'Bid Monitoring'!R13=F4)),'Bid Monitoring'!B13,"") | B23: =IF(AND('Bid Monitoring'!B13<>"",IF(B4="All",TRUE(),'Bid Monitoring'!N13=B4),IF(C4="All",TRUE(),'Bid Monitoring'!L13=C4),IF(D4="All",TRUE(),'Bid Monitoring'!F13=D4),IF(E4="All",TRUE(),'Bid Monitoring'!E13=E4),IF(F4="All",TRUE(),'Bid Monitoring'!R13=F4)),'Bid Monitoring'!D13,"") | C23: =IF(AND('Bid Monitoring'!B13<>"",IF(B4="All",TRUE(),'Bid Monitoring'!N13=B4),IF(C4="All",TRUE(),'Bid Monitoring'!L13=C4),IF(D4="All",TRUE(),'Bid Monitoring'!F13=D4),IF(E4="All",TRUE(),'Bid Monitoring'!E13=E4),IF(F4="All",TRUE(),'Bid Monitoring'!R13=F4)),'Bid Monitoring'!C13,"") | D23: =IF(AND('Bid Monitoring'!B13<>"",IF(B4="All",TRUE(),'Bid Monitoring'!N13=B4),IF(C4="All",TRUE(),'Bid Monitoring'!L13=C4),IF(D4="All",TRUE(),'Bid Monitoring'!F13=D4),IF(E4="All",TRUE(),'Bid Monitoring'!E13=E4),IF(F4="All",TRUE(),'Bid Monitoring'!R13=F4)),'Bid Monitoring'!E13,"") | E23: =IF(AND('Bid Monitoring'!B13<>"",IF(B4="All",TRUE(),'Bid Monitoring'!N13=B4),IF(C4="All",TRUE(),'Bid Monitoring'!L13=C4),IF(D4="All",TRUE(),'Bid Monitoring'!F13=D4),IF(E4="All",TRUE(),'Bid Monitoring'!E13=E4),IF(F4="All",TRUE(),'Bid Monitoring'!R13=F4)),'Bid Monitoring'!F13,"") | F23: =IF(AND('Bid Monitoring'!B13<>"",IF(B4="All",TRUE(),'Bid Monitoring'!N13=B4),IF(C4="All",TRUE(),'Bid Monitoring'!L13=C4),IF(D4="All",TRUE(),'Bid Monitoring'!F13=D4),IF(E4="All",TRUE(),'Bid Monitoring'!E13=E4),IF(F4="All",TRUE(),'Bid Monitoring'!R13=F4)),'Bid Monitoring'!H13,"") | G23: =IF(AND('Bid Monitoring'!B13<>"",IF(B4="All",TRUE(),'Bid Monitoring'!N13=B4),IF(C4="All",TRUE(),'Bid Monitoring'!L13=C4),IF(D4="All",TRUE(),'Bid Monitoring'!F13=D4),IF(E4="All",TRUE(),'Bid Monitoring'!E13=E4),IF(F4="All",TRUE(),'Bid Monitoring'!R13=F4)),'Bid Monitoring'!I13,"") | H23: =IF(AND('Bid Monitoring'!B13<>"",IF(B4="All",TRUE(),'Bid Monitoring'!N13=B4),IF(C4="All",TRUE(),'Bid Monitoring'!L13=C4),IF(D4="All",TRUE(),'Bid Monitoring'!F13=D4),IF(E4="All",TRUE(),'Bid Monitoring'!E13=E4),IF(F4="All",TRUE(),'Bid Monitoring'!R13=F4)),'Bid Monitoring'!K13,"") | I23: =IF(AND('Bid Monitoring'!B13<>"",IF(B4="All",TRUE(),'Bid Monitoring'!N13=B4),IF(C4="All",TRUE(),'Bid Monitoring'!L13=C4),IF(D4="All",TRUE(),'Bid Monitoring'!F13=D4),IF(E4="All",TRUE(),'Bid Monitoring'!E13=E4),IF(F4="All",TRUE(),'Bid Monitoring'!R13=F4)),'Bid Monitoring'!N13,"") | J23: =IF(AND('Bid Monitoring'!B13<>"",IF(B4="All",TRUE(),'Bid Monitoring'!N13=B4),IF(C4="All",TRUE(),'Bid Monitoring'!L13=C4),IF(D4="All",TRUE(),'Bid Monitoring'!F13=D4),IF(E4="All",TRUE(),'Bid Monitoring'!E13=E4),IF(F4="All",TRUE(),'Bid Monitoring'!R13=F4)),'Bid Monitoring'!L13,"")
A24: =IF(AND('Bid Monitoring'!B14<>"",IF(B4="All",TRUE(),'Bid Monitoring'!N14=B4),IF(C4="All",TRUE(),'Bid Monitoring'!L14=C4),IF(D4="All",TRUE(),'Bid Monitoring'!F14=D4),IF(E4="All",TRUE(),'Bid Monitoring'!E14=E4),IF(F4="All",TRUE(),'Bid Monitoring'!R14=F4)),'Bid Monitoring'!B14,"") | B24: =IF(AND('Bid Monitoring'!B14<>"",IF(B4="All",TRUE(),'Bid Monitoring'!N14=B4),IF(C4="All",TRUE(),'Bid Monitoring'!L14=C4),IF(D4="All",TRUE(),'Bid Monitoring'!F14=D4),IF(E4="All",TRUE(),'Bid Monitoring'!E14=E4),IF(F4="All",TRUE(),'Bid Monitoring'!R14=F4)),'Bid Monitoring'!D14,"") | C24: =IF(AND('Bid Monitoring'!B14<>"",IF(B4="All",TRUE(),'Bid Monitoring'!N14=B4),IF(C4="All",TRUE(),'Bid Monitoring'!L14=C4),IF(D4="All",TRUE(),'Bid Monitoring'!F14=D4),IF(E4="All",TRUE(),'Bid Monitoring'!E14=E4),IF(F4="All",TRUE(),'Bid Monitoring'!R14=F4)),'Bid Monitoring'!C14,"") | D24: =IF(AND('Bid Monitoring'!B14<>"",IF(B4="All",TRUE(),'Bid Monitoring'!N14=B4),IF(C4="All",TRUE(),'Bid Monitoring'!L14=C4),IF(D4="All",TRUE(),'Bid Monitoring'!F14=D4),IF(E4="All",TRUE(),'Bid Monitoring'!E14=E4),IF(F4="All",TRUE(),'Bid Monitoring'!R14=F4)),'Bid Monitoring'!E14,"") | E24: =IF(AND('Bid Monitoring'!B14<>"",IF(B4="All",TRUE(),'Bid Monitoring'!N14=B4),IF(C4="All",TRUE(),'Bid Monitoring'!L14=C4),IF(D4="All",TRUE(),'Bid Monitoring'!F14=D4),IF(E4="All",TRUE(),'Bid Monitoring'!E14=E4),IF(F4="All",TRUE(),'Bid Monitoring'!R14=F4)),'Bid Monitoring'!F14,"") | F24: =IF(AND('Bid Monitoring'!B14<>"",IF(B4="All",TRUE(),'Bid Monitoring'!N14=B4),IF(C4="All",TRUE(),'Bid Monitoring'!L14=C4),IF(D4="All",TRUE(),'Bid Monitoring'!F14=D4),IF(E4="All",TRUE(),'Bid Monitoring'!E14=E4),IF(F4="All",TRUE(),'Bid Monitoring'!R14=F4)),'Bid Monitoring'!H14,"") | G24: =IF(AND('Bid Monitoring'!B14<>"",IF(B4="All",TRUE(),'Bid Monitoring'!N14=B4),IF(C4="All",TRUE(),'Bid Monitoring'!L14=C4),IF(D4="All",TRUE(),'Bid Monitoring'!F14=D4),IF(E4="All",TRUE(),'Bid Monitoring'!E14=E4),IF(F4="All",TRUE(),'Bid Monitoring'!R14=F4)),'Bid Monitoring'!I14,"") | H24: =IF(AND('Bid Monitoring'!B14<>"",IF(B4="All",TRUE(),'Bid Monitoring'!N14=B4),IF(C4="All",TRUE(),'Bid Monitoring'!L14=C4),IF(D4="All",TRUE(),'Bid Monitoring'!F14=D4),IF(E4="All",TRUE(),'Bid Monitoring'!E14=E4),IF(F4="All",TRUE(),'Bid Monitoring'!R14=F4)),'Bid Monitoring'!K14,"") | I24: =IF(AND('Bid Monitoring'!B14<>"",IF(B4="All",TRUE(),'Bid Monitoring'!N14=B4),IF(C4="All",TRUE(),'Bid Monitoring'!L14=C4),IF(D4="All",TRUE(),'Bid Monitoring'!F14=D4),IF(E4="All",TRUE(),'Bid Monitoring'!E14=E4),IF(F4="All",TRUE(),'Bid Monitoring'!R14=F4)),'Bid Monitoring'!N14,"") | J24: =IF(AND('Bid Monitoring'!B14<>"",IF(B4="All",TRUE(),'Bid Monitoring'!N14=B4),IF(C4="All",TRUE(),'Bid Monitoring'!L14=C4),IF(D4="All",TRUE(),'Bid Monitoring'!F14=D4),IF(E4="All",TRUE(),'Bid Monitoring'!E14=E4),IF(F4="All",TRUE(),'Bid Monitoring'!R14=F4)),'Bid Monitoring'!L14,"")
A25: =IF(AND('Bid Monitoring'!B15<>"",IF(B4="All",TRUE(),'Bid Monitoring'!N15=B4),IF(C4="All",TRUE(),'Bid Monitoring'!L15=C4),IF(D4="All",TRUE(),'Bid Monitoring'!F15=D4),IF(E4="All",TRUE(),'Bid Monitoring'!E15=E4),IF(F4="All",TRUE(),'Bid Monitoring'!R15=F4)),'Bid Monitoring'!B15,"") | B25: =IF(AND('Bid Monitoring'!B15<>"",IF(B4="All",TRUE(),'Bid Monitoring'!N15=B4),IF(C4="All",TRUE(),'Bid Monitoring'!L15=C4),IF(D4="All",TRUE(),'Bid Monitoring'!F15=D4),IF(E4="All",TRUE(),'Bid Monitoring'!E15=E4),IF(F4="All",TRUE(),'Bid Monitoring'!R15=F4)),'Bid Monitoring'!D15,"") | C25: =IF(AND('Bid Monitoring'!B15<>"",IF(B4="All",TRUE(),'Bid Monitoring'!N15=B4),IF(C4="All",TRUE(),'Bid Monitoring'!L15=C4),IF(D4="All",TRUE(),'Bid Monitoring'!F15=D4),IF(E4="All",TRUE(),'Bid Monitoring'!E15=E4),IF(F4="All",TRUE(),'Bid Monitoring'!R15=F4)),'Bid Monitoring'!C15,"") | D25: =IF(AND('Bid Monitoring'!B15<>"",IF(B4="All",TRUE(),'Bid Monitoring'!N15=B4),IF(C4="All",TRUE(),'Bid Monitoring'!L15=C4),IF(D4="All",TRUE(),'Bid Monitoring'!F15=D4),IF(E4="All",TRUE(),'Bid Monitoring'!E15=E4),IF(F4="All",TRUE(),'Bid Monitoring'!R15=F4)),'Bid Monitoring'!E15,"") | E25: =IF(AND('Bid Monitoring'!B15<>"",IF(B4="All",TRUE(),'Bid Monitoring'!N15=B4),IF(C4="All",TRUE(),'Bid Monitoring'!L15=C4),IF(D4="All",TRUE(),'Bid Monitoring'!F15=D4),IF(E4="All",TRUE(),'Bid Monitoring'!E15=E4),IF(F4="All",TRUE(),'Bid Monitoring'!R15=F4)),'Bid Monitoring'!F15,"") | F25: =IF(AND('Bid Monitoring'!B15<>"",IF(B4="All",TRUE(),'Bid Monitoring'!N15=B4),IF(C4="All",TRUE(),'Bid Monitoring'!L15=C4),IF(D4="All",TRUE(),'Bid Monitoring'!F15=D4),IF(E4="All",TRUE(),'Bid Monitoring'!E15=E4),IF(F4="All",TRUE(),'Bid Monitoring'!R15=F4)),'Bid Monitoring'!H15,"") | G25: =IF(AND('Bid Monitoring'!B15<>"",IF(B4="All",TRUE(),'Bid Monitoring'!N15=B4),IF(C4="All",TRUE(),'Bid Monitoring'!L15=C4),IF(D4="All",TRUE(),'Bid Monitoring'!F15=D4),IF(E4="All",TRUE(),'Bid Monitoring'!E15=E4),IF(F4="All",TRUE(),'Bid Monitoring'!R15=F4)),'Bid Monitoring'!I15,"") | H25: =IF(AND('Bid Monitoring'!B15<>"",IF(B4="All",TRUE(),'Bid Monitoring'!N15=B4),IF(C4="All",TRUE(),'Bid Monitoring'!L15=C4),IF(D4="All",TRUE(),'Bid Monitoring'!F15=D4),IF(E4="All",TRUE(),'Bid Monitoring'!E15=E4),IF(F4="All",TRUE(),'Bid Monitoring'!R15=F4)),'Bid Monitoring'!K15,"") | I25: =IF(AND('Bid Monitoring'!B15<>"",IF(B4="All",TRUE(),'Bid Monitoring'!N15=B4),IF(C4="All",TRUE(),'Bid Monitoring'!L15=C4),IF(D4="All",TRUE(),'Bid Monitoring'!F15=D4),IF(E4="All",TRUE(),'Bid Monitoring'!E15=E4),IF(F4="All",TRUE(),'Bid Monitoring'!R15=F4)),'Bid Monitoring'!N15,"") | J25: =IF(AND('Bid Monitoring'!B15<>"",IF(B4="All",TRUE(),'Bid Monitoring'!N15=B4),IF(C4="All",TRUE(),'Bid Monitoring'!L15=C4),IF(D4="All",TRUE(),'Bid Monitoring'!F15=D4),IF(E4="All",TRUE(),'Bid Monitoring'!E15=E4),IF(F4="All",TRUE(),'Bid Monitoring'!R15=F4)),'Bid Monitoring'!L15,"")
A26: =IF(AND('Bid Monitoring'!B16<>"",IF(B4="All",TRUE(),'Bid Monitoring'!N16=B4),IF(C4="All",TRUE(),'Bid Monitoring'!L16=C4),IF(D4="All",TRUE(),'Bid Monitoring'!F16=D4),IF(E4="All",TRUE(),'Bid Monitoring'!E16=E4),IF(F4="All",TRUE(),'Bid Monitoring'!R16=F4)),'Bid Monitoring'!B16,"") | B26: =IF(AND('Bid Monitoring'!B16<>"",IF(B4="All",TRUE(),'Bid Monitoring'!N16=B4),IF(C4="All",TRUE(),'Bid Monitoring'!L16=C4),IF(D4="All",TRUE(),'Bid Monitoring'!F16=D4),IF(E4="All",TRUE(),'Bid Monitoring'!E16=E4),IF(F4="All",TRUE(),'Bid Monitoring'!R16=F4)),'Bid Monitoring'!D16,"") | C26: =IF(AND('Bid Monitoring'!B16<>"",IF(B4="All",TRUE(),'Bid Monitoring'!N16=B4),IF(C4="All",TRUE(),'Bid Monitoring'!L16=C4),IF(D4="All",TRUE(),'Bid Monitoring'!F16=D4),IF(E4="All",TRUE(),'Bid Monitoring'!E16=E4),IF(F4="All",TRUE(),'Bid Monitoring'!R16=F4)),'Bid Monitoring'!C16,"") | D26: =IF(AND('Bid Monitoring'!B16<>"",IF(B4="All",TRUE(),'Bid Monitoring'!N16=B4),IF(C4="All",TRUE(),'Bid Monitoring'!L16=C4),IF(D4="All",TRUE(),'Bid Monitoring'!F16=D4),IF(E4="All",TRUE(),'Bid Monitoring'!E16=E4),IF(F4="All",TRUE(),'Bid Monitoring'!R16=F4)),'Bid Monitoring'!E16,"") | E26: =IF(AND('Bid Monitoring'!B16<>"",IF(B4="All",TRUE(),'Bid Monitoring'!N16=B4),IF(C4="All",TRUE(),'Bid Monitoring'!L16=C4),IF(D4="All",TRUE(),'Bid Monitoring'!F16=D4),IF(E4="All",TRUE(),'Bid Monitoring'!E16=E4),IF(F4="All",TRUE(),'Bid Monitoring'!R16=F4)),'Bid Monitoring'!F16,"") | F26: =IF(AND('Bid Monitoring'!B16<>"",IF(B4="All",TRUE(),'Bid Monitoring'!N16=B4),IF(C4="All",TRUE(),'Bid Monitoring'!L16=C4),IF(D4="All",TRUE(),'Bid Monitoring'!F16=D4),IF(E4="All",TRUE(),'Bid Monitoring'!E16=E4),IF(F4="All",TRUE(),'Bid Monitoring'!R16=F4)),'Bid Monitoring'!H16,"") | G26: =IF(AND('Bid Monitoring'!B16<>"",IF(B4="All",TRUE(),'Bid Monitoring'!N16=B4),IF(C4="All",TRUE(),'Bid Monitoring'!L16=C4),IF(D4="All",TRUE(),'Bid Monitoring'!F16=D4),IF(E4="All",TRUE(),'Bid Monitoring'!E16=E4),IF(F4="All",TRUE(),'Bid Monitoring'!R16=F4)),'Bid Monitoring'!I16,"") | H26: =IF(AND('Bid Monitoring'!B16<>"",IF(B4="All",TRUE(),'Bid Monitoring'!N16=B4),IF(C4="All",TRUE(),'Bid Monitoring'!L16=C4),IF(D4="All",TRUE(),'Bid Monitoring'!F16=D4),IF(E4="All",TRUE(),'Bid Monitoring'!E16=E4),IF(F4="All",TRUE(),'Bid Monitoring'!R16=F4)),'Bid Monitoring'!K16,"") | I26: =IF(AND('Bid Monitoring'!B16<>"",IF(B4="All",TRUE(),'Bid Monitoring'!N16=B4),IF(C4="All",TRUE(),'Bid Monitoring'!L16=C4),IF(D4="All",TRUE(),'Bid Monitoring'!F16=D4),IF(E4="All",TRUE(),'Bid Monitoring'!E16=E4),IF(F4="All",TRUE(),'Bid Monitoring'!R16=F4)),'Bid Monitoring'!N16,"") | J26: =IF(AND('Bid Monitoring'!B16<>"",IF(B4="All",TRUE(),'Bid Monitoring'!N16=B4),IF(C4="All",TRUE(),'Bid Monitoring'!L16=C4),IF(D4="All",TRUE(),'Bid Monitoring'!F16=D4),IF(E4="All",TRUE(),'Bid Monitoring'!E16=E4),IF(F4="All",TRUE(),'Bid Monitoring'!R16=F4)),'Bid Monitoring'!L16,"")
A27: =IF(AND('Bid Monitoring'!B17<>"",IF(B4="All",TRUE(),'Bid Monitoring'!N17=B4),IF(C4="All",TRUE(),'Bid Monitoring'!L17=C4),IF(D4="All",TRUE(),'Bid Monitoring'!F17=D4),IF(E4="All",TRUE(),'Bid Monitoring'!E17=E4),IF(F4="All",TRUE(),'Bid Monitoring'!R17=F4)),'Bid Monitoring'!B17,"") | B27: =IF(AND('Bid Monitoring'!B17<>"",IF(B4="All",TRUE(),'Bid Monitoring'!N17=B4),IF(C4="All",TRUE(),'Bid Monitoring'!L17=C4),IF(D4="All",TRUE(),'Bid Monitoring'!F17=D4),IF(E4="All",TRUE(),'Bid Monitoring'!E17=E4),IF(F4="All",TRUE(),'Bid Monitoring'!R17=F4)),'Bid Monitoring'!D17,"") | C27: =IF(AND('Bid Monitoring'!B17<>"",IF(B4="All",TRUE(),'Bid Monitoring'!N17=B4),IF(C4="All",TRUE(),'Bid Monitoring'!L17=C4),IF(D4="All",TRUE(),'Bid Monitoring'!F17=D4),IF(E4="All",TRUE(),'Bid Monitoring'!E17=E4),IF(F4="All",TRUE(),'Bid Monitoring'!R17=F4)),'Bid Monitoring'!C17,"") | D27: =IF(AND('Bid Monitoring'!B17<>"",IF(B4="All",TRUE(),'Bid Monitoring'!N17=B4),IF(C4="All",TRUE(),'Bid Monitoring'!L17=C4),IF(D4="All",TRUE(),'Bid Monitoring'!F17=D4),IF(E4="All",TRUE(),'Bid Monitoring'!E17=E4),IF(F4="All",TRUE(),'Bid Monitoring'!R17=F4)),'Bid Monitoring'!E17,"") | E27: =IF(AND('Bid Monitoring'!B17<>"",IF(B4="All",TRUE(),'Bid Monitoring'!N17=B4),IF(C4="All",TRUE(),'Bid Monitoring'!L17=C4),IF(D4="All",TRUE(),'Bid Monitoring'!F17=D4),IF(E4="All",TRUE(),'Bid Monitoring'!E17=E4),IF(F4="All",TRUE(),'Bid Monitoring'!R17=F4)),'Bid Monitoring'!F17,"") | F27: =IF(AND('Bid Monitoring'!B17<>"",IF(B4="All",TRUE(),'Bid Monitoring'!N17=B4),IF(C4="All",TRUE(),'Bid Monitoring'!L17=C4),IF(D4="All",TRUE(),'Bid Monitoring'!F17=D4),IF(E4="All",TRUE(),'Bid Monitoring'!E17=E4),IF(F4="All",TRUE(),'Bid Monitoring'!R17=F4)),'Bid Monitoring'!H17,"") | G27: =IF(AND('Bid Monitoring'!B17<>"",IF(B4="All",TRUE(),'Bid Monitoring'!N17=B4),IF(C4="All",TRUE(),'Bid Monitoring'!L17=C4),IF(D4="All",TRUE(),'Bid Monitoring'!F17=D4),IF(E4="All",TRUE(),'Bid Monitoring'!E17=E4),IF(F4="All",TRUE(),'Bid Monitoring'!R17=F4)),'Bid Monitoring'!I17,"") | H27: =IF(AND('Bid Monitoring'!B17<>"",IF(B4="All",TRUE(),'Bid Monitoring'!N17=B4),IF(C4="All",TRUE(),'Bid Monitoring'!L17=C4),IF(D4="All",TRUE(),'Bid Monitoring'!F17=D4),IF(E4="All",TRUE(),'Bid Monitoring'!E17=E4),IF(F4="All",TRUE(),'Bid Monitoring'!R17=F4)),'Bid Monitoring'!K17,"") | I27: =IF(AND('Bid Monitoring'!B17<>"",IF(B4="All",TRUE(),'Bid Monitoring'!N17=B4),IF(C4="All",TRUE(),'Bid Monitoring'!L17=C4),IF(D4="All",TRUE(),'Bid Monitoring'!F17=D4),IF(E4="All",TRUE(),'Bid Monitoring'!E17=E4),IF(F4="All",TRUE(),'Bid Monitoring'!R17=F4)),'Bid Monitoring'!N17,"") | J27: =IF(AND('Bid Monitoring'!B17<>"",IF(B4="All",TRUE(),'Bid Monitoring'!N17=B4),IF(C4="All",TRUE(),'Bid Monitoring'!L17=C4),IF(D4="All",TRUE(),'Bid Monitoring'!F17=D4),IF(E4="All",TRUE(),'Bid Monitoring'!E17=E4),IF(F4="All",TRUE(),'Bid Monitoring'!R17=F4)),'Bid Monitoring'!L17,"")
A28: =IF(AND('Bid Monitoring'!B18<>"",IF(B4="All",TRUE(),'Bid Monitoring'!N18=B4),IF(C4="All",TRUE(),'Bid Monitoring'!L18=C4),IF(D4="All",TRUE(),'Bid Monitoring'!F18=D4),IF(E4="All",TRUE(),'Bid Monitoring'!E18=E4),IF(F4="All",TRUE(),'Bid Monitoring'!R18=F4)),'Bid Monitoring'!B18,"") | B28: =IF(AND('Bid Monitoring'!B18<>"",IF(B4="All",TRUE(),'Bid Monitoring'!N18=B4),IF(C4="All",TRUE(),'Bid Monitoring'!L18=C4),IF(D4="All",TRUE(),'Bid Monitoring'!F18=D4),IF(E4="All",TRUE(),'Bid Monitoring'!E18=E4),IF(F4="All",TRUE(),'Bid Monitoring'!R18=F4)),'Bid Monitoring'!D18,"") | C28: =IF(AND('Bid Monitoring'!B18<>"",IF(B4="All",TRUE(),'Bid Monitoring'!N18=B4),IF(C4="All",TRUE(),'Bid Monitoring'!L18=C4),IF(D4="All",TRUE(),'Bid Monitoring'!F18=D4),IF(E4="All",TRUE(),'Bid Monitoring'!E18=E4),IF(F4="All",TRUE(),'Bid Monitoring'!R18=F4)),'Bid Monitoring'!C18,"") | D28: =IF(AND('Bid Monitoring'!B18<>"",IF(B4="All",TRUE(),'Bid Monitoring'!N18=B4),IF(C4="All",TRUE(),'Bid Monitoring'!L18=C4),IF(D4="All",TRUE(),'Bid Monitoring'!F18=D4),IF(E4="All",TRUE(),'Bid Monitoring'!E18=E4),IF(F4="All",TRUE(),'Bid Monitoring'!R18=F4)),'Bid Monitoring'!E18,"") | E28: =IF(AND('Bid Monitoring'!B18<>"",IF(B4="All",TRUE(),'Bid Monitoring'!N18=B4),IF(C4="All",TRUE(),'Bid Monitoring'!L18=C4),IF(D4="All",TRUE(),'Bid Monitoring'!F18=D4),IF(E4="All",TRUE(),'Bid Monitoring'!E18=E4),IF(F4="All",TRUE(),'Bid Monitoring'!R18=F4)),'Bid Monitoring'!F18,"") | F28: =IF(AND('Bid Monitoring'!B18<>"",IF(B4="All",TRUE(),'Bid Monitoring'!N18=B4),IF(C4="All",TRUE(),'Bid Monitoring'!L18=C4),IF(D4="All",TRUE(),'Bid Monitoring'!F18=D4),IF(E4="All",TRUE(),'Bid Monitoring'!E18=E4),IF(F4="All",TRUE(),'Bid Monitoring'!R18=F4)),'Bid Monitoring'!H18,"") | G28: =IF(AND('Bid Monitoring'!B18<>"",IF(B4="All",TRUE(),'Bid Monitoring'!N18=B4),IF(C4="All",TRUE(),'Bid Monitoring'!L18=C4),IF(D4="All",TRUE(),'Bid Monitoring'!F18=D4),IF(E4="All",TRUE(),'Bid Monitoring'!E18=E4),IF(F4="All",TRUE(),'Bid Monitoring'!R18=F4)),'Bid Monitoring'!I18,"") | H28: =IF(AND('Bid Monitoring'!B18<>"",IF(B4="All",TRUE(),'Bid Monitoring'!N18=B4),IF(C4="All",TRUE(),'Bid Monitoring'!L18=C4),IF(D4="All",TRUE(),'Bid Monitoring'!F18=D4),IF(E4="All",TRUE(),'Bid Monitoring'!E18=E4),IF(F4="All",TRUE(),'Bid Monitoring'!R18=F4)),'Bid Monitoring'!K18,"") | I28: =IF(AND('Bid Monitoring'!B18<>"",IF(B4="All",TRUE(),'Bid Monitoring'!N18=B4),IF(C4="All",TRUE(),'Bid Monitoring'!L18=C4),IF(D4="All",TRUE(),'Bid Monitoring'!F18=D4),IF(E4="All",TRUE(),'Bid Monitoring'!E18=E4),IF(F4="All",TRUE(),'Bid Monitoring'!R18=F4)),'Bid Monitoring'!N18,"") | J28: =IF(AND('Bid Monitoring'!B18<>"",IF(B4="All",TRUE(),'Bid Monitoring'!N18=B4),IF(C4="All",TRUE(),'Bid Monitoring'!L18=C4),IF(D4="All",TRUE(),'Bid Monitoring'!F18=D4),IF(E4="All",TRUE(),'Bid Monitoring'!E18=E4),IF(F4="All",TRUE(),'Bid Monitoring'!R18=F4)),'Bid Monitoring'!L18,"")
A29: =IF(AND('Bid Monitoring'!B19<>"",IF(B4="All",TRUE(),'Bid Monitoring'!N19=B4),IF(C4="All",TRUE(),'Bid Monitoring'!L19=C4),IF(D4="All",TRUE(),'Bid Monitoring'!F19=D4),IF(E4="All",TRUE(),'Bid Monitoring'!E19=E4),IF(F4="All",TRUE(),'Bid Monitoring'!R19=F4)),'Bid Monitoring'!B19,"") | B29: =IF(AND('Bid Monitoring'!B19<>"",IF(B4="All",TRUE(),'Bid Monitoring'!N19=B4),IF(C4="All",TRUE(),'Bid Monitoring'!L19=C4),IF(D4="All",TRUE(),'Bid Monitoring'!F19=D4),IF(E4="All",TRUE(),'Bid Monitoring'!E19=E4),IF(F4="All",TRUE(),'Bid Monitoring'!R19=F4)),'Bid Monitoring'!D19,"") | C29: =IF(AND('Bid Monitoring'!B19<>"",IF(B4="All",TRUE(),'Bid Monitoring'!N19=B4),IF(C4="All",TRUE(),'Bid Monitoring'!L19=C4),IF(D4="All",TRUE(),'Bid Monitoring'!F19=D4),IF(E4="All",TRUE(),'Bid Monitoring'!E19=E4),IF(F4="All",TRUE(),'Bid Monitoring'!R19=F4)),'Bid Monitoring'!C19,"") | D29: =IF(AND('Bid Monitoring'!B19<>"",IF(B4="All",TRUE(),'Bid Monitoring'!N19=B4),IF(C4="All",TRUE(),'Bid Monitoring'!L19=C4),IF(D4="All",TRUE(),'Bid Monitoring'!F19=D4),IF(E4="All",TRUE(),'Bid Monitoring'!E19=E4),IF(F4="All",TRUE(),'Bid Monitoring'!R19=F4)),'Bid Monitoring'!E19,"") | E29: =IF(AND('Bid Monitoring'!B19<>"",IF(B4="All",TRUE(),'Bid Monitoring'!N19=B4),IF(C4="All",TRUE(),'Bid Monitoring'!L19=C4),IF(D4="All",TRUE(),'Bid Monitoring'!F19=D4),IF(E4="All",TRUE(),'Bid Monitoring'!E19=E4),IF(F4="All",TRUE(),'Bid Monitoring'!R19=F4)),'Bid Monitoring'!F19,"") | F29: =IF(AND('Bid Monitoring'!B19<>"",IF(B4="All",TRUE(),'Bid Monitoring'!N19=B4),IF(C4="All",TRUE(),'Bid Monitoring'!L19=C4),IF(D4="All",TRUE(),'Bid Monitoring'!F19=D4),IF(E4="All",TRUE(),'Bid Monitoring'!E19=E4),IF(F4="All",TRUE(),'Bid Monitoring'!R19=F4)),'Bid Monitoring'!H19,"") | G29: =IF(AND('Bid Monitoring'!B19<>"",IF(B4="All",TRUE(),'Bid Monitoring'!N19=B4),IF(C4="All",TRUE(),'Bid Monitoring'!L19=C4),IF(D4="All",TRUE(),'Bid Monitoring'!F19=D4),IF(E4="All",TRUE(),'Bid Monitoring'!E19=E4),IF(F4="All",TRUE(),'Bid Monitoring'!R19=F4)),'Bid Monitoring'!I19,"") | H29: =IF(AND('Bid Monitoring'!B19<>"",IF(B4="All",TRUE(),'Bid Monitoring'!N19=B4),IF(C4="All",TRUE(),'Bid Monitoring'!L19=C4),IF(D4="All",TRUE(),'Bid Monitoring'!F19=D4),IF(E4="All",TRUE(),'Bid Monitoring'!E19=E4),IF(F4="All",TRUE(),'Bid Monitoring'!R19=F4)),'Bid Monitoring'!K19,"") | I29: =IF(AND('Bid Monitoring'!B19<>"",IF(B4="All",TRUE(),'Bid Monitoring'!N19=B4),IF(C4="All",TRUE(),'Bid Monitoring'!L19=C4),IF(D4="All",TRUE(),'Bid Monitoring'!F19=D4),IF(E4="All",TRUE(),'Bid Monitoring'!E19=E4),IF(F4="All",TRUE(),'Bid Monitoring'!R19=F4)),'Bid Monitoring'!N19,"") | J29: =IF(AND('Bid Monitoring'!B19<>"",IF(B4="All",TRUE(),'Bid Monitoring'!N19=B4),IF(C4="All",TRUE(),'Bid Monitoring'!L19=C4),IF(D4="All",TRUE(),'Bid Monitoring'!F19=D4),IF(E4="All",TRUE(),'Bid Monitoring'!E19=E4),IF(F4="All",TRUE(),'Bid Monitoring'!R19=F4)),'Bid Monitoring'!L19,"")
A30: =IF(AND('Bid Monitoring'!B20<>"",IF(B4="All",TRUE(),'Bid Monitoring'!N20=B4),IF(C4="All",TRUE(),'Bid Monitoring'!L20=C4),IF(D4="All",TRUE(),'Bid Monitoring'!F20=D4),IF(E4="All",TRUE(),'Bid Monitoring'!E20=E4),IF(F4="All",TRUE(),'Bid Monitoring'!R20=F4)),'Bid Monitoring'!B20,"") | B30: =IF(AND('Bid Monitoring'!B20<>"",IF(B4="All",TRUE(),'Bid Monitoring'!N20=B4),IF(C4="All",TRUE(),'Bid Monitoring'!L20=C4),IF(D4="All",TRUE(),'Bid Monitoring'!F20=D4),IF(E4="All",TRUE(),'Bid Monitoring'!E20=E4),IF(F4="All",TRUE(),'Bid Monitoring'!R20=F4)),'Bid Monitoring'!D20,"") | C30: =IF(AND('Bid Monitoring'!B20<>"",IF(B4="All",TRUE(),'Bid Monitoring'!N20=B4),IF(C4="All",TRUE(),'Bid Monitoring'!L20=C4),IF(D4="All",TRUE(),'Bid Monitoring'!F20=D4),IF(E4="All",TRUE(),'Bid Monitoring'!E20=E4),IF(F4="All",TRUE(),'Bid Monitoring'!R20=F4)),'Bid Monitoring'!C20,"") | D30: =IF(AND('Bid Monitoring'!B20<>"",IF(B4="All",TRUE(),'Bid Monitoring'!N20=B4),IF(C4="All",TRUE(),'Bid Monitoring'!L20=C4),IF(D4="All",TRUE(),'Bid Monitoring'!F20=D4),IF(E4="All",TRUE(),'Bid Monitoring'!E20=E4),IF(F4="All",TRUE(),'Bid Monitoring'!R20=F4)),'Bid Monitoring'!E20,"") | E30: =IF(AND('Bid Monitoring'!B20<>"",IF(B4="All",TRUE(),'Bid Monitoring'!N20=B4),IF(C4="All",TRUE(),'Bid Monitoring'!L20=C4),IF(D4="All",TRUE(),'Bid Monitoring'!F20=D4),IF(E4="All",TRUE(),'Bid Monitoring'!E20=E4),IF(F4="All",TRUE(),'Bid Monitoring'!R20=F4)),'Bid Monitoring'!F20,"") | F30: =IF(AND('Bid Monitoring'!B20<>"",IF(B4="All",TRUE(),'Bid Monitoring'!N20=B4),IF(C4="All",TRUE(),'Bid Monitoring'!L20=C4),IF(D4="All",TRUE(),'Bid Monitoring'!F20=D4),IF(E4="All",TRUE(),'Bid Monitoring'!E20=E4),IF(F4="All",TRUE(),'Bid Monitoring'!R20=F4)),'Bid Monitoring'!H20,"") | G30: =IF(AND('Bid Monitoring'!B20<>"",IF(B4="All",TRUE(),'Bid Monitoring'!N20=B4),IF(C4="All",TRUE(),'Bid Monitoring'!L20=C4),IF(D4="All",TRUE(),'Bid Monitoring'!F20=D4),IF(E4="All",TRUE(),'Bid Monitoring'!E20=E4),IF(F4="All",TRUE(),'Bid Monitoring'!R20=F4)),'Bid Monitoring'!I20,"") | H30: =IF(AND('Bid Monitoring'!B20<>"",IF(B4="All",TRUE(),'Bid Monitoring'!N20=B4),IF(C4="All",TRUE(),'Bid Monitoring'!L20=C4),IF(D4="All",TRUE(),'Bid Monitoring'!F20=D4),IF(E4="All",TRUE(),'Bid Monitoring'!E20=E4),IF(F4="All",TRUE(),'Bid Monitoring'!R20=F4)),'Bid Monitoring'!K20,"") | I30: =IF(AND('Bid Monitoring'!B20<>"",IF(B4="All",TRUE(),'Bid Monitoring'!N20=B4),IF(C4="All",TRUE(),'Bid Monitoring'!L20=C4),IF(D4="All",TRUE(),'Bid Monitoring'!F20=D4),IF(E4="All",TRUE(),'Bid Monitoring'!E20=E4),IF(F4="All",TRUE(),'Bid Monitoring'!R20=F4)),'Bid Monitoring'!N20,"") | J30: =IF(AND('Bid Monitoring'!B20<>"",IF(B4="All",TRUE(),'Bid Monitoring'!N20=B4),IF(C4="All",TRUE(),'Bid Monitoring'!L20=C4),IF(D4="All",TRUE(),'Bid Monitoring'!F20=D4),IF(E4="All",TRUE(),'Bid Monitoring'!E20=E4),IF(F4="All",TRUE(),'Bid Monitoring'!R20=F4)),'Bid Monitoring'!L20,"")
A31: =IF(AND('Bid Monitoring'!B21<>"",IF(B4="All",TRUE(),'Bid Monitoring'!N21=B4),IF(C4="All",TRUE(),'Bid Monitoring'!L21=C4),IF(D4="All",TRUE(),'Bid Monitoring'!F21=D4),IF(E4="All",TRUE(),'Bid Monitoring'!E21=E4),IF(F4="All",TRUE(),'Bid Monitoring'!R21=F4)),'Bid Monitoring'!B21,"") | B31: =IF(AND('Bid Monitoring'!B21<>"",IF(B4="All",TRUE(),'Bid Monitoring'!N21=B4),IF(C4="All",TRUE(),'Bid Monitoring'!L21=C4),IF(D4="All",TRUE(),'Bid Monitoring'!F21=D4),IF(E4="All",TRUE(),'Bid Monitoring'!E21=E4),IF(F4="All",TRUE(),'Bid Monitoring'!R21=F4)),'Bid Monitoring'!D21,"") | C31: =IF(AND('Bid Monitoring'!B21<>"",IF(B4="All",TRUE(),'Bid Monitoring'!N21=B4),IF(C4="All",TRUE(),'Bid Monitoring'!L21=C4),IF(D4="All",TRUE(),'Bid Monitoring'!F21=D4),IF(E4="All",TRUE(),'Bid Monitoring'!E21=E4),IF(F4="All",TRUE(),'Bid Monitoring'!R21=F4)),'Bid Monitoring'!C21,"") | D31: =IF(AND('Bid Monitoring'!B21<>"",IF(B4="All",TRUE(),'Bid Monitoring'!N21=B4),IF(C4="All",TRUE(),'Bid Monitoring'!L21=C4),IF(D4="All",TRUE(),'Bid Monitoring'!F21=D4),IF(E4="All",TRUE(),'Bid Monitoring'!E21=E4),IF(F4="All",TRUE(),'Bid Monitoring'!R21=F4)),'Bid Monitoring'!E21,"") | E31: =IF(AND('Bid Monitoring'!B21<>"",IF(B4="All",TRUE(),'Bid Monitoring'!N21=B4),IF(C4="All",TRUE(),'Bid Monitoring'!L21=C4),IF(D4="All",TRUE(),'Bid Monitoring'!F21=D4),IF(E4="All",TRUE(),'Bid Monitoring'!E21=E4),IF(F4="All",TRUE(),'Bid Monitoring'!R21=F4)),'Bid Monitoring'!F21,"") | F31: =IF(AND('Bid Monitoring'!B21<>"",IF(B4="All",TRUE(),'Bid Monitoring'!N21=B4),IF(C4="All",TRUE(),'Bid Monitoring'!L21=C4),IF(D4="All",TRUE(),'Bid Monitoring'!F21=D4),IF(E4="All",TRUE(),'Bid Monitoring'!E21=E4),IF(F4="All",TRUE(),'Bid Monitoring'!R21=F4)),'Bid Monitoring'!H21,"") | G31: =IF(AND('Bid Monitoring'!B21<>"",IF(B4="All",TRUE(),'Bid Monitoring'!N21=B4),IF(C4="All",TRUE(),'Bid Monitoring'!L21=C4),IF(D4="All",TRUE(),'Bid Monitoring'!F21=D4),IF(E4="All",TRUE(),'Bid Monitoring'!E21=E4),IF(F4="All",TRUE(),'Bid Monitoring'!R21=F4)),'Bid Monitoring'!I21,"") | H31: =IF(AND('Bid Monitoring'!B21<>"",IF(B4="All",TRUE(),'Bid Monitoring'!N21=B4),IF(C4="All",TRUE(),'Bid Monitoring'!L21=C4),IF(D4="All",TRUE(),'Bid Monitoring'!F21=D4),IF(E4="All",TRUE(),'Bid Monitoring'!E21=E4),IF(F4="All",TRUE(),'Bid Monitoring'!R21=F4)),'Bid Monitoring'!K21,"") | I31: =IF(AND('Bid Monitoring'!B21<>"",IF(B4="All",TRUE(),'Bid Monitoring'!N21=B4),IF(C4="All",TRUE(),'Bid Monitoring'!L21=C4),IF(D4="All",TRUE(),'Bid Monitoring'!F21=D4),IF(E4="All",TRUE(),'Bid Monitoring'!E21=E4),IF(F4="All",TRUE(),'Bid Monitoring'!R21=F4)),'Bid Monitoring'!N21,"") | J31: =IF(AND('Bid Monitoring'!B21<>"",IF(B4="All",TRUE(),'Bid Monitoring'!N21=B4),IF(C4="All",TRUE(),'Bid Monitoring'!L21=C4),IF(D4="All",TRUE(),'Bid Monitoring'!F21=D4),IF(E4="All",TRUE(),'Bid Monitoring'!E21=E4),IF(F4="All",TRUE(),'Bid Monitoring'!R21=F4)),'Bid Monitoring'!L21,"")
A32: =IF(AND('Bid Monitoring'!B22<>"",IF(B4="All",TRUE(),'Bid Monitoring'!N22=B4),IF(C4="All",TRUE(),'Bid Monitoring'!L22=C4),IF(D4="All",TRUE(),'Bid Monitoring'!F22=D4),IF(E4="All",TRUE(),'Bid Monitoring'!E22=E4),IF(F4="All",TRUE(),'Bid Monitoring'!R22=F4)),'Bid Monitoring'!B22,"") | B32: =IF(AND('Bid Monitoring'!B22<>"",IF(B4="All",TRUE(),'Bid Monitoring'!N22=B4),IF(C4="All",TRUE(),'Bid Monitoring'!L22=C4),IF(D4="All",TRUE(),'Bid Monitoring'!F22=D4),IF(E4="All",TRUE(),'Bid Monitoring'!E22=E4),IF(F4="All",TRUE(),'Bid Monitoring'!R22=F4)),'Bid Monitoring'!D22,"") | C32: =IF(AND('Bid Monitoring'!B22<>"",IF(B4="All",TRUE(),'Bid Monitoring'!N22=B4),IF(C4="All",TRUE(),'Bid Monitoring'!L22=C4),IF(D4="All",TRUE(),'Bid Monitoring'!F22=D4),IF(E4="All",TRUE(),'Bid Monitoring'!E22=E4),IF(F4="All",TRUE(),'Bid Monitoring'!R22=F4)),'Bid Monitoring'!C22,"") | D32: =IF(AND('Bid Monitoring'!B22<>"",IF(B4="All",TRUE(),'Bid Monitoring'!N22=B4),IF(C4="All",TRUE(),'Bid Monitoring'!L22=C4),IF(D4="All",TRUE(),'Bid Monitoring'!F22=D4),IF(E4="All",TRUE(),'Bid Monitoring'!E22=E4),IF(F4="All",TRUE(),'Bid Monitoring'!R22=F4)),'Bid Monitoring'!E22,"") | E32: =IF(AND('Bid Monitoring'!B22<>"",IF(B4="All",TRUE(),'Bid Monitoring'!N22=B4),IF(C4="All",TRUE(),'Bid Monitoring'!L22=C4),IF(D4="All",TRUE(),'Bid Monitoring'!F22=D4),IF(E4="All",TRUE(),'Bid Monitoring'!E22=E4),IF(F4="All",TRUE(),'Bid Monitoring'!R22=F4)),'Bid Monitoring'!F22,"") | F32: =IF(AND('Bid Monitoring'!B22<>"",IF(B4="All",TRUE(),'Bid Monitoring'!N22=B4),IF(C4="All",TRUE(),'Bid Monitoring'!L22=C4),IF(D4="All",TRUE(),'Bid Monitoring'!F22=D4),IF(E4="All",TRUE(),'Bid Monitoring'!E22=E4),IF(F4="All",TRUE(),'Bid Monitoring'!R22=F4)),'Bid Monitoring'!H22,"") | G32: =IF(AND('Bid Monitoring'!B22<>"",IF(B4="All",TRUE(),'Bid Monitoring'!N22=B4),IF(C4="All",TRUE(),'Bid Monitoring'!L22=C4),IF(D4="All",TRUE(),'Bid Monitoring'!F22=D4),IF(E4="All",TRUE(),'Bid Monitoring'!E22=E4),IF(F4="All",TRUE(),'Bid Monitoring'!R22=F4)),'Bid Monitoring'!I22,"") | H32: =IF(AND('Bid Monitoring'!B22<>"",IF(B4="All",TRUE(),'Bid Monitoring'!N22=B4),IF(C4="All",TRUE(),'Bid Monitoring'!L22=C4),IF(D4="All",TRUE(),'Bid Monitoring'!F22=D4),IF(E4="All",TRUE(),'Bid Monitoring'!E22=E4),IF(F4="All",TRUE(),'Bid Monitoring'!R22=F4)),'Bid Monitoring'!K22,"") | I32: =IF(AND('Bid Monitoring'!B22<>"",IF(B4="All",TRUE(),'Bid Monitoring'!N22=B4),IF(C4="All",TRUE(),'Bid Monitoring'!L22=C4),IF(D4="All",TRUE(),'Bid Monitoring'!F22=D4),IF(E4="All",TRUE(),'Bid Monitoring'!E22=E4),IF(F4="All",TRUE(),'Bid Monitoring'!R22=F4)),'Bid Monitoring'!N22,"") | J32: =IF(AND('Bid Monitoring'!B22<>"",IF(B4="All",TRUE(),'Bid Monitoring'!N22=B4),IF(C4="All",TRUE(),'Bid Monitoring'!L22=C4),IF(D4="All",TRUE(),'Bid Monitoring'!F22=D4),IF(E4="All",TRUE(),'Bid Monitoring'!E22=E4),IF(F4="All",TRUE(),'Bid Monitoring'!R22=F4)),'Bid Monitoring'!L22,"")
A33: =IF(AND('Bid Monitoring'!B23<>"",IF(B4="All",TRUE(),'Bid Monitoring'!N23=B4),IF(C4="All",TRUE(),'Bid Monitoring'!L23=C4),IF(D4="All",TRUE(),'Bid Monitoring'!F23=D4),IF(E4="All",TRUE(),'Bid Monitoring'!E23=E4),IF(F4="All",TRUE(),'Bid Monitoring'!R23=F4)),'Bid Monitoring'!B23,"") | B33: =IF(AND('Bid Monitoring'!B23<>"",IF(B4="All",TRUE(),'Bid Monitoring'!N23=B4),IF(C4="All",TRUE(),'Bid Monitoring'!L23=C4),IF(D4="All",TRUE(),'Bid Monitoring'!F23=D4),IF(E4="All",TRUE(),'Bid Monitoring'!E23=E4),IF(F4="All",TRUE(),'Bid Monitoring'!R23=F4)),'Bid Monitoring'!D23,"") | C33: =IF(AND('Bid Monitoring'!B23<>"",IF(B4="All",TRUE(),'Bid Monitoring'!N23=B4),IF(C4="All",TRUE(),'Bid Monitoring'!L23=C4),IF(D4="All",TRUE(),'Bid Monitoring'!F23=D4),IF(E4="All",TRUE(),'Bid Monitoring'!E23=E4),IF(F4="All",TRUE(),'Bid Monitoring'!R23=F4)),'Bid Monitoring'!C23,"") | D33: =IF(AND('Bid Monitoring'!B23<>"",IF(B4="All",TRUE(),'Bid Monitoring'!N23=B4),IF(C4="All",TRUE(),'Bid Monitoring'!L23=C4),IF(D4="All",TRUE(),'Bid Monitoring'!F23=D4),IF(E4="All",TRUE(),'Bid Monitoring'!E23=E4),IF(F4="All",TRUE(),'Bid Monitoring'!R23=F4)),'Bid Monitoring'!E23,"") | E33: =IF(AND('Bid Monitoring'!B23<>"",IF(B4="All",TRUE(),'Bid Monitoring'!N23=B4),IF(C4="All",TRUE(),'Bid Monitoring'!L23=C4),IF(D4="All",TRUE(),'Bid Monitoring'!F23=D4),IF(E4="All",TRUE(),'Bid Monitoring'!E23=E4),IF(F4="All",TRUE(),'Bid Monitoring'!R23=F4)),'Bid Monitoring'!F23,"") | F33: =IF(AND('Bid Monitoring'!B23<>"",IF(B4="All",TRUE(),'Bid Monitoring'!N23=B4),IF(C4="All",TRUE(),'Bid Monitoring'!L23=C4),IF(D4="All",TRUE(),'Bid Monitoring'!F23=D4),IF(E4="All",TRUE(),'Bid Monitoring'!E23=E4),IF(F4="All",TRUE(),'Bid Monitoring'!R23=F4)),'Bid Monitoring'!H23,"") | G33: =IF(AND('Bid Monitoring'!B23<>"",IF(B4="All",TRUE(),'Bid Monitoring'!N23=B4),IF(C4="All",TRUE(),'Bid Monitoring'!L23=C4),IF(D4="All",TRUE(),'Bid Monitoring'!F23=D4),IF(E4="All",TRUE(),'Bid Monitoring'!E23=E4),IF(F4="All",TRUE(),'Bid Monitoring'!R23=F4)),'Bid Monitoring'!I23,"") | H33: =IF(AND('Bid Monitoring'!B23<>"",IF(B4="All",TRUE(),'Bid Monitoring'!N23=B4),IF(C4="All",TRUE(),'Bid Monitoring'!L23=C4),IF(D4="All",TRUE(),'Bid Monitoring'!F23=D4),IF(E4="All",TRUE(),'Bid Monitoring'!E23=E4),IF(F4="All",TRUE(),'Bid Monitoring'!R23=F4)),'Bid Monitoring'!K23,"") | I33: =IF(AND('Bid Monitoring'!B23<>"",IF(B4="All",TRUE(),'Bid Monitoring'!N23=B4),IF(C4="All",TRUE(),'Bid Monitoring'!L23=C4),IF(D4="All",TRUE(),'Bid Monitoring'!F23=D4),IF(E4="All",TRUE(),'Bid Monitoring'!E23=E4),IF(F4="All",TRUE(),'Bid Monitoring'!R23=F4)),'Bid Monitoring'!N23,"") | J33: =IF(AND('Bid Monitoring'!B23<>"",IF(B4="All",TRUE(),'Bid Monitoring'!N23=B4),IF(C4="All",TRUE(),'Bid Monitoring'!L23=C4),IF(D4="All",TRUE(),'Bid Monitoring'!F23=D4),IF(E4="All",TRUE(),'Bid Monitoring'!E23=E4),IF(F4="All",TRUE(),'Bid Monitoring'!R23=F4)),'Bid Monitoring'!L23,"")
A34: =IF(AND('Bid Monitoring'!B24<>"",IF(B4="All",TRUE(),'Bid Monitoring'!N24=B4),IF(C4="All",TRUE(),'Bid Monitoring'!L24=C4),IF(D4="All",TRUE(),'Bid Monitoring'!F24=D4),IF(E4="All",TRUE(),'Bid Monitoring'!E24=E4),IF(F4="All",TRUE(),'Bid Monitoring'!R24=F4)),'Bid Monitoring'!B24,"") | B34: =IF(AND('Bid Monitoring'!B24<>"",IF(B4="All",TRUE(),'Bid Monitoring'!N24=B4),IF(C4="All",TRUE(),'Bid Monitoring'!L24=C4),IF(D4="All",TRUE(),'Bid Monitoring'!F24=D4),IF(E4="All",TRUE(),'Bid Monitoring'!E24=E4),IF(F4="All",TRUE(),'Bid Monitoring'!R24=F4)),'Bid Monitoring'!D24,"") | C34: =IF(AND('Bid Monitoring'!B24<>"",IF(B4="All",TRUE(),'Bid Monitoring'!N24=B4),IF(C4="All",TRUE(),'Bid Monitoring'!L24=C4),IF(D4="All",TRUE(),'Bid Monitoring'!F24=D4),IF(E4="All",TRUE(),'Bid Monitoring'!E24=E4),IF(F4="All",TRUE(),'Bid Monitoring'!R24=F4)),'Bid Monitoring'!C24,"") | D34: =IF(AND('Bid Monitoring'!B24<>"",IF(B4="All",TRUE(),'Bid Monitoring'!N24=B4),IF(C4="All",TRUE(),'Bid Monitoring'!L24=C4),IF(D4="All",TRUE(),'Bid Monitoring'!F24=D4),IF(E4="All",TRUE(),'Bid Monitoring'!E24=E4),IF(F4="All",TRUE(),'Bid Monitoring'!R24=F4)),'Bid Monitoring'!E24,"") | E34: =IF(AND('Bid Monitoring'!B24<>"",IF(B4="All",TRUE(),'Bid Monitoring'!N24=B4),IF(C4="All",TRUE(),'Bid Monitoring'!L24=C4),IF(D4="All",TRUE(),'Bid Monitoring'!F24=D4),IF(E4="All",TRUE(),'Bid Monitoring'!E24=E4),IF(F4="All",TRUE(),'Bid Monitoring'!R24=F4)),'Bid Monitoring'!F24,"") | F34: =IF(AND('Bid Monitoring'!B24<>"",IF(B4="All",TRUE(),'Bid Monitoring'!N24=B4),IF(C4="All",TRUE(),'Bid Monitoring'!L24=C4),IF(D4="All",TRUE(),'Bid Monitoring'!F24=D4),IF(E4="All",TRUE(),'Bid Monitoring'!E24=E4),IF(F4="All",TRUE(),'Bid Monitoring'!R24=F4)),'Bid Monitoring'!H24,"") | G34: =IF(AND('Bid Monitoring'!B24<>"",IF(B4="All",TRUE(),'Bid Monitoring'!N24=B4),IF(C4="All",TRUE(),'Bid Monitoring'!L24=C4),IF(D4="All",TRUE(),'Bid Monitoring'!F24=D4),IF(E4="All",TRUE(),'Bid Monitoring'!E24=E4),IF(F4="All",TRUE(),'Bid Monitoring'!R24=F4)),'Bid Monitoring'!I24,"") | H34: =IF(AND('Bid Monitoring'!B24<>"",IF(B4="All",TRUE(),'Bid Monitoring'!N24=B4),IF(C4="All",TRUE(),'Bid Monitoring'!L24=C4),IF(D4="All",TRUE(),'Bid Monitoring'!F24=D4),IF(E4="All",TRUE(),'Bid Monitoring'!E24=E4),IF(F4="All",TRUE(),'Bid Monitoring'!R24=F4)),'Bid Monitoring'!K24,"") | I34: =IF(AND('Bid Monitoring'!B24<>"",IF(B4="All",TRUE(),'Bid Monitoring'!N24=B4),IF(C4="All",TRUE(),'Bid Monitoring'!L24=C4),IF(D4="All",TRUE(),'Bid Monitoring'!F24=D4),IF(E4="All",TRUE(),'Bid Monitoring'!E24=E4),IF(F4="All",TRUE(),'Bid Monitoring'!R24=F4)),'Bid Monitoring'!N24,"") | J34: =IF(AND('Bid Monitoring'!B24<>"",IF(B4="All",TRUE(),'Bid Monitoring'!N24=B4),IF(C4="All",TRUE(),'Bid Monitoring'!L24=C4),IF(D4="All",TRUE(),'Bid Monitoring'!F24=D4),IF(E4="All",TRUE(),'Bid Monitoring'!E24=E4),IF(F4="All",TRUE(),'Bid Monitoring'!R24=F4)),'Bid Monitoring'!L24,"")
A35: =IF(AND('Bid Monitoring'!B25<>"",IF(B4="All",TRUE(),'Bid Monitoring'!N25=B4),IF(C4="All",TRUE(),'Bid Monitoring'!L25=C4),IF(D4="All",TRUE(),'Bid Monitoring'!F25=D4),IF(E4="All",TRUE(),'Bid Monitoring'!E25=E4),IF(F4="All",TRUE(),'Bid Monitoring'!R25=F4)),'Bid Monitoring'!B25,"") | B35: =IF(AND('Bid Monitoring'!B25<>"",IF(B4="All",TRUE(),'Bid Monitoring'!N25=B4),IF(C4="All",TRUE(),'Bid Monitoring'!L25=C4),IF(D4="All",TRUE(),'Bid Monitoring'!F25=D4),IF(E4="All",TRUE(),'Bid Monitoring'!E25=E4),IF(F4="All",TRUE(),'Bid Monitoring'!R25=F4)),'Bid Monitoring'!D25,"") | C35: =IF(AND('Bid Monitoring'!B25<>"",IF(B4="All",TRUE(),'Bid Monitoring'!N25=B4),IF(C4="All",TRUE(),'Bid Monitoring'!L25=C4),IF(D4="All",TRUE(),'Bid Monitoring'!F25=D4),IF(E4="All",TRUE(),'Bid Monitoring'!E25=E4),IF(F4="All",TRUE(),'Bid Monitoring'!R25=F4)),'Bid Monitoring'!C25,"") | D35: =IF(AND('Bid Monitoring'!B25<>"",IF(B4="All",TRUE(),'Bid Monitoring'!N25=B4),IF(C4="All",TRUE(),'Bid Monitoring'!L25=C4),IF(D4="All",TRUE(),'Bid Monitoring'!F25=D4),IF(E4="All",TRUE(),'Bid Monitoring'!E25=E4),IF(F4="All",TRUE(),'Bid Monitoring'!R25=F4)),'Bid Monitoring'!E25,"") | E35: =IF(AND('Bid Monitoring'!B25<>"",IF(B4="All",TRUE(),'Bid Monitoring'!N25=B4),IF(C4="All",TRUE(),'Bid Monitoring'!L25=C4),IF(D4="All",TRUE(),'Bid Monitoring'!F25=D4),IF(E4="All",TRUE(),'Bid Monitoring'!E25=E4),IF(F4="All",TRUE(),'Bid Monitoring'!R25=F4)),'Bid Monitoring'!F25,"") | F35: =IF(AND('Bid Monitoring'!B25<>"",IF(B4="All",TRUE(),'Bid Monitoring'!N25=B4),IF(C4="All",TRUE(),'Bid Monitoring'!L25=C4),IF(D4="All",TRUE(),'Bid Monitoring'!F25=D4),IF(E4="All",TRUE(),'Bid Monitoring'!E25=E4),IF(F4="All",TRUE(),'Bid Monitoring'!R25=F4)),'Bid Monitoring'!H25,"") | G35: =IF(AND('Bid Monitoring'!B25<>"",IF(B4="All",TRUE(),'Bid Monitoring'!N25=B4),IF(C4="All",TRUE(),'Bid Monitoring'!L25=C4),IF(D4="All",TRUE(),'Bid Monitoring'!F25=D4),IF(E4="All",TRUE(),'Bid Monitoring'!E25=E4),IF(F4="All",TRUE(),'Bid Monitoring'!R25=F4)),'Bid Monitoring'!I25,"") | H35: =IF(AND('Bid Monitoring'!B25<>"",IF(B4="All",TRUE(),'Bid Monitoring'!N25=B4),IF(C4="All",TRUE(),'Bid Monitoring'!L25=C4),IF(D4="All",TRUE(),'Bid Monitoring'!F25=D4),IF(E4="All",TRUE(),'Bid Monitoring'!E25=E4),IF(F4="All",TRUE(),'Bid Monitoring'!R25=F4)),'Bid Monitoring'!K25,"") | I35: =IF(AND('Bid Monitoring'!B25<>"",IF(B4="All",TRUE(),'Bid Monitoring'!N25=B4),IF(C4="All",TRUE(),'Bid Monitoring'!L25=C4),IF(D4="All",TRUE(),'Bid Monitoring'!F25=D4),IF(E4="All",TRUE(),'Bid Monitoring'!E25=E4),IF(F4="All",TRUE(),'Bid Monitoring'!R25=F4)),'Bid Monitoring'!N25,"") | J35: =IF(AND('Bid Monitoring'!B25<>"",IF(B4="All",TRUE(),'Bid Monitoring'!N25=B4),IF(C4="All",TRUE(),'Bid Monitoring'!L25=C4),IF(D4="All",TRUE(),'Bid Monitoring'!F25=D4),IF(E4="All",TRUE(),'Bid Monitoring'!E25=E4),IF(F4="All",TRUE(),'Bid Monitoring'!R25=F4)),'Bid Monitoring'!L25,"")
A36: =IF(AND('Bid Monitoring'!B26<>"",IF(B4="All",TRUE(),'Bid Monitoring'!N26=B4),IF(C4="All",TRUE(),'Bid Monitoring'!L26=C4),IF(D4="All",TRUE(),'Bid Monitoring'!F26=D4),IF(E4="All",TRUE(),'Bid Monitoring'!E26=E4),IF(F4="All",TRUE(),'Bid Monitoring'!R26=F4)),'Bid Monitoring'!B26,"") | B36: =IF(AND('Bid Monitoring'!B26<>"",IF(B4="All",TRUE(),'Bid Monitoring'!N26=B4),IF(C4="All",TRUE(),'Bid Monitoring'!L26=C4),IF(D4="All",TRUE(),'Bid Monitoring'!F26=D4),IF(E4="All",TRUE(),'Bid Monitoring'!E26=E4),IF(F4="All",TRUE(),'Bid Monitoring'!R26=F4)),'Bid Monitoring'!D26,"") | C36: =IF(AND('Bid Monitoring'!B26<>"",IF(B4="All",TRUE(),'Bid Monitoring'!N26=B4),IF(C4="All",TRUE(),'Bid Monitoring'!L26=C4),IF(D4="All",TRUE(),'Bid Monitoring'!F26=D4),IF(E4="All",TRUE(),'Bid Monitoring'!E26=E4),IF(F4="All",TRUE(),'Bid Monitoring'!R26=F4)),'Bid Monitoring'!C26,"") | D36: =IF(AND('Bid Monitoring'!B26<>"",IF(B4="All",TRUE(),'Bid Monitoring'!N26=B4),IF(C4="All",TRUE(),'Bid Monitoring'!L26=C4),IF(D4="All",TRUE(),'Bid Monitoring'!F26=D4),IF(E4="All",TRUE(),'Bid Monitoring'!E26=E4),IF(F4="All",TRUE(),'Bid Monitoring'!R26=F4)),'Bid Monitoring'!E26,"") | E36: =IF(AND('Bid Monitoring'!B26<>"",IF(B4="All",TRUE(),'Bid Monitoring'!N26=B4),IF(C4="All",TRUE(),'Bid Monitoring'!L26=C4),IF(D4="All",TRUE(),'Bid Monitoring'!F26=D4),IF(E4="All",TRUE(),'Bid Monitoring'!E26=E4),IF(F4="All",TRUE(),'Bid Monitoring'!R26=F4)),'Bid Monitoring'!F26,"") | F36: =IF(AND('Bid Monitoring'!B26<>"",IF(B4="All",TRUE(),'Bid Monitoring'!N26=B4),IF(C4="All",TRUE(),'Bid Monitoring'!L26=C4),IF(D4="All",TRUE(),'Bid Monitoring'!F26=D4),IF(E4="All",TRUE(),'Bid Monitoring'!E26=E4),IF(F4="All",TRUE(),'Bid Monitoring'!R26=F4)),'Bid Monitoring'!H26,"") | G36: =IF(AND('Bid Monitoring'!B26<>"",IF(B4="All",TRUE(),'Bid Monitoring'!N26=B4),IF(C4="All",TRUE(),'Bid Monitoring'!L26=C4),IF(D4="All",TRUE(),'Bid Monitoring'!F26=D4),IF(E4="All",TRUE(),'Bid Monitoring'!E26=E4),IF(F4="All",TRUE(),'Bid Monitoring'!R26=F4)),'Bid Monitoring'!I26,"") | H36: =IF(AND('Bid Monitoring'!B26<>"",IF(B4="All",TRUE(),'Bid Monitoring'!N26=B4),IF(C4="All",TRUE(),'Bid Monitoring'!L26=C4),IF(D4="All",TRUE(),'Bid Monitoring'!F26=D4),IF(E4="All",TRUE(),'Bid Monitoring'!E26=E4),IF(F4="All",TRUE(),'Bid Monitoring'!R26=F4)),'Bid Monitoring'!K26,"") | I36: =IF(AND('Bid Monitoring'!B26<>"",IF(B4="All",TRUE(),'Bid Monitoring'!N26=B4),IF(C4="All",TRUE(),'Bid Monitoring'!L26=C4),IF(D4="All",TRUE(),'Bid Monitoring'!F26=D4),IF(E4="All",TRUE(),'Bid Monitoring'!E26=E4),IF(F4="All",TRUE(),'Bid Monitoring'!R26=F4)),'Bid Monitoring'!N26,"") | J36: =IF(AND('Bid Monitoring'!B26<>"",IF(B4="All",TRUE(),'Bid Monitoring'!N26=B4),IF(C4="All",TRUE(),'Bid Monitoring'!L26=C4),IF(D4="All",TRUE(),'Bid Monitoring'!F26=D4),IF(E4="All",TRUE(),'Bid Monitoring'!E26=E4),IF(F4="All",TRUE(),'Bid Monitoring'!R26=F4)),'Bid Monitoring'!L26,"")
A37: =IF(AND('Bid Monitoring'!B27<>"",IF(B4="All",TRUE(),'Bid Monitoring'!N27=B4),IF(C4="All",TRUE(),'Bid Monitoring'!L27=C4),IF(D4="All",TRUE(),'Bid Monitoring'!F27=D4),IF(E4="All",TRUE(),'Bid Monitoring'!E27=E4),IF(F4="All",TRUE(),'Bid Monitoring'!R27=F4)),'Bid Monitoring'!B27,"") | B37: =IF(AND('Bid Monitoring'!B27<>"",IF(B4="All",TRUE(),'Bid Monitoring'!N27=B4),IF(C4="All",TRUE(),'Bid Monitoring'!L27=C4),IF(D4="All",TRUE(),'Bid Monitoring'!F27=D4),IF(E4="All",TRUE(),'Bid Monitoring'!E27=E4),IF(F4="All",TRUE(),'Bid Monitoring'!R27=F4)),'Bid Monitoring'!D27,"") | C37: =IF(AND('Bid Monitoring'!B27<>"",IF(B4="All",TRUE(),'Bid Monitoring'!N27=B4),IF(C4="All",TRUE(),'Bid Monitoring'!L27=C4),IF(D4="All",TRUE(),'Bid Monitoring'!F27=D4),IF(E4="All",TRUE(),'Bid Monitoring'!E27=E4),IF(F4="All",TRUE(),'Bid Monitoring'!R27=F4)),'Bid Monitoring'!C27,"") | D37: =IF(AND('Bid Monitoring'!B27<>"",IF(B4="All",TRUE(),'Bid Monitoring'!N27=B4),IF(C4="All",TRUE(),'Bid Monitoring'!L27=C4),IF(D4="All",TRUE(),'Bid Monitoring'!F27=D4),IF(E4="All",TRUE(),'Bid Monitoring'!E27=E4),IF(F4="All",TRUE(),'Bid Monitoring'!R27=F4)),'Bid Monitoring'!E27,"") | E37: =IF(AND('Bid Monitoring'!B27<>"",IF(B4="All",TRUE(),'Bid Monitoring'!N27=B4),IF(C4="All",TRUE(),'Bid Monitoring'!L27=C4),IF(D4="All",TRUE(),'Bid Monitoring'!F27=D4),IF(E4="All",TRUE(),'Bid Monitoring'!E27=E4),IF(F4="All",TRUE(),'Bid Monitoring'!R27=F4)),'Bid Monitoring'!F27,"") | F37: =IF(AND('Bid Monitoring'!B27<>"",IF(B4="All",TRUE(),'Bid Monitoring'!N27=B4),IF(C4="All",TRUE(),'Bid Monitoring'!L27=C4),IF(D4="All",TRUE(),'Bid Monitoring'!F27=D4),IF(E4="All",TRUE(),'Bid Monitoring'!E27=E4),IF(F4="All",TRUE(),'Bid Monitoring'!R27=F4)),'Bid Monitoring'!H27,"") | G37: =IF(AND('Bid Monitoring'!B27<>"",IF(B4="All",TRUE(),'Bid Monitoring'!N27=B4),IF(C4="All",TRUE(),'Bid Monitoring'!L27=C4),IF(D4="All",TRUE(),'Bid Monitoring'!F27=D4),IF(E4="All",TRUE(),'Bid Monitoring'!E27=E4),IF(F4="All",TRUE(),'Bid Monitoring'!R27=F4)),'Bid Monitoring'!I27,"") | H37: =IF(AND('Bid Monitoring'!B27<>"",IF(B4="All",TRUE(),'Bid Monitoring'!N27=B4),IF(C4="All",TRUE(),'Bid Monitoring'!L27=C4),IF(D4="All",TRUE(),'Bid Monitoring'!F27=D4),IF(E4="All",TRUE(),'Bid Monitoring'!E27=E4),IF(F4="All",TRUE(),'Bid Monitoring'!R27=F4)),'Bid Monitoring'!K27,"") | I37: =IF(AND('Bid Monitoring'!B27<>"",IF(B4="All",TRUE(),'Bid Monitoring'!N27=B4),IF(C4="All",TRUE(),'Bid Monitoring'!L27=C4),IF(D4="All",TRUE(),'Bid Monitoring'!F27=D4),IF(E4="All",TRUE(),'Bid Monitoring'!E27=E4),IF(F4="All",TRUE(),'Bid Monitoring'!R27=F4)),'Bid Monitoring'!N27,"") | J37: =IF(AND('Bid Monitoring'!B27<>"",IF(B4="All",TRUE(),'Bid Monitoring'!N27=B4),IF(C4="All",TRUE(),'Bid Monitoring'!L27=C4),IF(D4="All",TRUE(),'Bid Monitoring'!F27=D4),IF(E4="All",TRUE(),'Bid Monitoring'!E27=E4),IF(F4="All",TRUE(),'Bid Monitoring'!R27=F4)),'Bid Monitoring'!L27,"")
A38: =IF(AND('Bid Monitoring'!B28<>"",IF(B4="All",TRUE(),'Bid Monitoring'!N28=B4),IF(C4="All",TRUE(),'Bid Monitoring'!L28=C4),IF(D4="All",TRUE(),'Bid Monitoring'!F28=D4),IF(E4="All",TRUE(),'Bid Monitoring'!E28=E4),IF(F4="All",TRUE(),'Bid Monitoring'!R28=F4)),'Bid Monitoring'!B28,"") | B38: =IF(AND('Bid Monitoring'!B28<>"",IF(B4="All",TRUE(),'Bid Monitoring'!N28=B4),IF(C4="All",TRUE(),'Bid Monitoring'!L28=C4),IF(D4="All",TRUE(),'Bid Monitoring'!F28=D4),IF(E4="All",TRUE(),'Bid Monitoring'!E28=E4),IF(F4="All",TRUE(),'Bid Monitoring'!R28=F4)),'Bid Monitoring'!D28,"") | C38: =IF(AND('Bid Monitoring'!B28<>"",IF(B4="All",TRUE(),'Bid Monitoring'!N28=B4),IF(C4="All",TRUE(),'Bid Monitoring'!L28=C4),IF(D4="All",TRUE(),'Bid Monitoring'!F28=D4),IF(E4="All",TRUE(),'Bid Monitoring'!E28=E4),IF(F4="All",TRUE(),'Bid Monitoring'!R28=F4)),'Bid Monitoring'!C28,"") | D38: =IF(AND('Bid Monitoring'!B28<>"",IF(B4="All",TRUE(),'Bid Monitoring'!N28=B4),IF(C4="All",TRUE(),'Bid Monitoring'!L28=C4),IF(D4="All",TRUE(),'Bid Monitoring'!F28=D4),IF(E4="All",TRUE(),'Bid Monitoring'!E28=E4),IF(F4="All",TRUE(),'Bid Monitoring'!R28=F4)),'Bid Monitoring'!E28,"") | E38: =IF(AND('Bid Monitoring'!B28<>"",IF(B4="All",TRUE(),'Bid Monitoring'!N28=B4),IF(C4="All",TRUE(),'Bid Monitoring'!L28=C4),IF(D4="All",TRUE(),'Bid Monitoring'!F28=D4),IF(E4="All",TRUE(),'Bid Monitoring'!E28=E4),IF(F4="All",TRUE(),'Bid Monitoring'!R28=F4)),'Bid Monitoring'!F28,"") | F38: =IF(AND('Bid Monitoring'!B28<>"",IF(B4="All",TRUE(),'Bid Monitoring'!N28=B4),IF(C4="All",TRUE(),'Bid Monitoring'!L28=C4),IF(D4="All",TRUE(),'Bid Monitoring'!F28=D4),IF(E4="All",TRUE(),'Bid Monitoring'!E28=E4),IF(F4="All",TRUE(),'Bid Monitoring'!R28=F4)),'Bid Monitoring'!H28,"") | G38: =IF(AND('Bid Monitoring'!B28<>"",IF(B4="All",TRUE(),'Bid Monitoring'!N28=B4),IF(C4="All",TRUE(),'Bid Monitoring'!L28=C4),IF(D4="All",TRUE(),'Bid Monitoring'!F28=D4),IF(E4="All",TRUE(),'Bid Monitoring'!E28=E4),IF(F4="All",TRUE(),'Bid Monitoring'!R28=F4)),'Bid Monitoring'!I28,"") | H38: =IF(AND('Bid Monitoring'!B28<>"",IF(B4="All",TRUE(),'Bid Monitoring'!N28=B4),IF(C4="All",TRUE(),'Bid Monitoring'!L28=C4),IF(D4="All",TRUE(),'Bid Monitoring'!F28=D4),IF(E4="All",TRUE(),'Bid Monitoring'!E28=E4),IF(F4="All",TRUE(),'Bid Monitoring'!R28=F4)),'Bid Monitoring'!K28,"") | I38: =IF(AND('Bid Monitoring'!B28<>"",IF(B4="All",TRUE(),'Bid Monitoring'!N28=B4),IF(C4="All",TRUE(),'Bid Monitoring'!L28=C4),IF(D4="All",TRUE(),'Bid Monitoring'!F28=D4),IF(E4="All",TRUE(),'Bid Monitoring'!E28=E4),IF(F4="All",TRUE(),'Bid Monitoring'!R28=F4)),'Bid Monitoring'!N28,"") | J38: =IF(AND('Bid Monitoring'!B28<>"",IF(B4="All",TRUE(),'Bid Monitoring'!N28=B4),IF(C4="All",TRUE(),'Bid Monitoring'!L28=C4),IF(D4="All",TRUE(),'Bid Monitoring'!F28=D4),IF(E4="All",TRUE(),'Bid Monitoring'!E28=E4),IF(F4="All",TRUE(),'Bid Monitoring'!R28=F4)),'Bid Monitoring'!L28,"")
A39: =IF(AND('Bid Monitoring'!B29<>"",IF(B4="All",TRUE(),'Bid Monitoring'!N29=B4),IF(C4="All",TRUE(),'Bid Monitoring'!L29=C4),IF(D4="All",TRUE(),'Bid Monitoring'!F29=D4),IF(E4="All",TRUE(),'Bid Monitoring'!E29=E4),IF(F4="All",TRUE(),'Bid Monitoring'!R29=F4)),'Bid Monitoring'!B29,"") | B39: =IF(AND('Bid Monitoring'!B29<>"",IF(B4="All",TRUE(),'Bid Monitoring'!N29=B4),IF(C4="All",TRUE(),'Bid Monitoring'!L29=C4),IF(D4="All",TRUE(),'Bid Monitoring'!F29=D4),IF(E4="All",TRUE(),'Bid Monitoring'!E29=E4),IF(F4="All",TRUE(),'Bid Monitoring'!R29=F4)),'Bid Monitoring'!D29,"") | C39: =IF(AND('Bid Monitoring'!B29<>"",IF(B4="All",TRUE(),'Bid Monitoring'!N29=B4),IF(C4="All",TRUE(),'Bid Monitoring'!L29=C4),IF(D4="All",TRUE(),'Bid Monitoring'!F29=D4),IF(E4="All",TRUE(),'Bid Monitoring'!E29=E4),IF(F4="All",TRUE(),'Bid Monitoring'!R29=F4)),'Bid Monitoring'!C29,"") | D39: =IF(AND('Bid Monitoring'!B29<>"",IF(B4="All",TRUE(),'Bid Monitoring'!N29=B4),IF(C4="All",TRUE(),'Bid Monitoring'!L29=C4),IF(D4="All",TRUE(),'Bid Monitoring'!F29=D4),IF(E4="All",TRUE(),'Bid Monitoring'!E29=E4),IF(F4="All",TRUE(),'Bid Monitoring'!R29=F4)),'Bid Monitoring'!E29,"") | E39: =IF(AND('Bid Monitoring'!B29<>"",IF(B4="All",TRUE(),'Bid Monitoring'!N29=B4),IF(C4="All",TRUE(),'Bid Monitoring'!L29=C4),IF(D4="All",TRUE(),'Bid Monitoring'!F29=D4),IF(E4="All",TRUE(),'Bid Monitoring'!E29=E4),IF(F4="All",TRUE(),'Bid Monitoring'!R29=F4)),'Bid Monitoring'!F29,"") | F39: =IF(AND('Bid Monitoring'!B29<>"",IF(B4="All",TRUE(),'Bid Monitoring'!N29=B4),IF(C4="All",TRUE(),'Bid Monitoring'!L29=C4),IF(D4="All",TRUE(),'Bid Monitoring'!F29=D4),IF(E4="All",TRUE(),'Bid Monitoring'!E29=E4),IF(F4="All",TRUE(),'Bid Monitoring'!R29=F4)),'Bid Monitoring'!H29,"") | G39: =IF(AND('Bid Monitoring'!B29<>"",IF(B4="All",TRUE(),'Bid Monitoring'!N29=B4),IF(C4="All",TRUE(),'Bid Monitoring'!L29=C4),IF(D4="All",TRUE(),'Bid Monitoring'!F29=D4),IF(E4="All",TRUE(),'Bid Monitoring'!E29=E4),IF(F4="All",TRUE(),'Bid Monitoring'!R29=F4)),'Bid Monitoring'!I29,"") | H39: =IF(AND('Bid Monitoring'!B29<>"",IF(B4="All",TRUE(),'Bid Monitoring'!N29=B4),IF(C4="All",TRUE(),'Bid Monitoring'!L29=C4),IF(D4="All",TRUE(),'Bid Monitoring'!F29=D4),IF(E4="All",TRUE(),'Bid Monitoring'!E29=E4),IF(F4="All",TRUE(),'Bid Monitoring'!R29=F4)),'Bid Monitoring'!K29,"") | I39: =IF(AND('Bid Monitoring'!B29<>"",IF(B4="All",TRUE(),'Bid Monitoring'!N29=B4),IF(C4="All",TRUE(),'Bid Monitoring'!L29=C4),IF(D4="All",TRUE(),'Bid Monitoring'!F29=D4),IF(E4="All",TRUE(),'Bid Monitoring'!E29=E4),IF(F4="All",TRUE(),'Bid Monitoring'!R29=F4)),'Bid Monitoring'!N29,"") | J39: =IF(AND('Bid Monitoring'!B29<>"",IF(B4="All",TRUE(),'Bid Monitoring'!N29=B4),IF(C4="All",TRUE(),'Bid Monitoring'!L29=C4),IF(D4="All",TRUE(),'Bid Monitoring'!F29=D4),IF(E4="All",TRUE(),'Bid Monitoring'!E29=E4),IF(F4="All",TRUE(),'Bid Monitoring'!R29=F4)),'Bid Monitoring'!L29,"")
A40: =IF(AND('Bid Monitoring'!B30<>"",IF(B4="All",TRUE(),'Bid Monitoring'!N30=B4),IF(C4="All",TRUE(),'Bid Monitoring'!L30=C4),IF(D4="All",TRUE(),'Bid Monitoring'!F30=D4),IF(E4="All",TRUE(),'Bid Monitoring'!E30=E4),IF(F4="All",TRUE(),'Bid Monitoring'!R30=F4)),'Bid Monitoring'!B30,"") | B40: =IF(AND('Bid Monitoring'!B30<>"",IF(B4="All",TRUE(),'Bid Monitoring'!N30=B4),IF(C4="All",TRUE(),'Bid Monitoring'!L30=C4),IF(D4="All",TRUE(),'Bid Monitoring'!F30=D4),IF(E4="All",TRUE(),'Bid Monitoring'!E30=E4),IF(F4="All",TRUE(),'Bid Monitoring'!R30=F4)),'Bid Monitoring'!D30,"") | C40: =IF(AND('Bid Monitoring'!B30<>"",IF(B4="All",TRUE(),'Bid Monitoring'!N30=B4),IF(C4="All",TRUE(),'Bid Monitoring'!L30=C4),IF(D4="All",TRUE(),'Bid Monitoring'!F30=D4),IF(E4="All",TRUE(),'Bid Monitoring'!E30=E4),IF(F4="All",TRUE(),'Bid Monitoring'!R30=F4)),'Bid Monitoring'!C30,"") | D40: =IF(AND('Bid Monitoring'!B30<>"",IF(B4="All",TRUE(),'Bid Monitoring'!N30=B4),IF(C4="All",TRUE(),'Bid Monitoring'!L30=C4),IF(D4="All",TRUE(),'Bid Monitoring'!F30=D4),IF(E4="All",TRUE(),'Bid Monitoring'!E30=E4),IF(F4="All",TRUE(),'Bid Monitoring'!R30=F4)),'Bid Monitoring'!E30,"") | E40: =IF(AND('Bid Monitoring'!B30<>"",IF(B4="All",TRUE(),'Bid Monitoring'!N30=B4),IF(C4="All",TRUE(),'Bid Monitoring'!L30=C4),IF(D4="All",TRUE(),'Bid Monitoring'!F30=D4),IF(E4="All",TRUE(),'Bid Monitoring'!E30=E4),IF(F4="All",TRUE(),'Bid Monitoring'!R30=F4)),'Bid Monitoring'!F30,"") | F40: =IF(AND('Bid Monitoring'!B30<>"",IF(B4="All",TRUE(),'Bid Monitoring'!N30=B4),IF(C4="All",TRUE(),'Bid Monitoring'!L30=C4),IF(D4="All",TRUE(),'Bid Monitoring'!F30=D4),IF(E4="All",TRUE(),'Bid Monitoring'!E30=E4),IF(F4="All",TRUE(),'Bid Monitoring'!R30=F4)),'Bid Monitoring'!H30,"") | G40: =IF(AND('Bid Monitoring'!B30<>"",IF(B4="All",TRUE(),'Bid Monitoring'!N30=B4),IF(C4="All",TRUE(),'Bid Monitoring'!L30=C4),IF(D4="All",TRUE(),'Bid Monitoring'!F30=D4),IF(E4="All",TRUE(),'Bid Monitoring'!E30=E4),IF(F4="All",TRUE(),'Bid Monitoring'!R30=F4)),'Bid Monitoring'!I30,"") | H40: =IF(AND('Bid Monitoring'!B30<>"",IF(B4="All",TRUE(),'Bid Monitoring'!N30=B4),IF(C4="All",TRUE(),'Bid Monitoring'!L30=C4),IF(D4="All",TRUE(),'Bid Monitoring'!F30=D4),IF(E4="All",TRUE(),'Bid Monitoring'!E30=E4),IF(F4="All",TRUE(),'Bid Monitoring'!R30=F4)),'Bid Monitoring'!K30,"") | I40: =IF(AND('Bid Monitoring'!B30<>"",IF(B4="All",TRUE(),'Bid Monitoring'!N30=B4),IF(C4="All",TRUE(),'Bid Monitoring'!L30=C4),IF(D4="All",TRUE(),'Bid Monitoring'!F30=D4),IF(E4="All",TRUE(),'Bid Monitoring'!E30=E4),IF(F4="All",TRUE(),'Bid Monitoring'!R30=F4)),'Bid Monitoring'!N30,"") | J40: =IF(AND('Bid Monitoring'!B30<>"",IF(B4="All",TRUE(),'Bid Monitoring'!N30=B4),IF(C4="All",TRUE(),'Bid Monitoring'!L30=C4),IF(D4="All",TRUE(),'Bid Monitoring'!F30=D4),IF(E4="All",TRUE(),'Bid Monitoring'!E30=E4),IF(F4="All",TRUE(),'Bid Monitoring'!R30=F4)),'Bid Monitoring'!L30,"")
A41: =IF(AND('Bid Monitoring'!B31<>"",IF(B4="All",TRUE(),'Bid Monitoring'!N31=B4),IF(C4="All",TRUE(),'Bid Monitoring'!L31=C4),IF(D4="All",TRUE(),'Bid Monitoring'!F31=D4),IF(E4="All",TRUE(),'Bid Monitoring'!E31=E4),IF(F4="All",TRUE(),'Bid Monitoring'!R31=F4)),'Bid Monitoring'!B31,"") | B41: =IF(AND('Bid Monitoring'!B31<>"",IF(B4="All",TRUE(),'Bid Monitoring'!N31=B4),IF(C4="All",TRUE(),'Bid Monitoring'!L31=C4),IF(D4="All",TRUE(),'Bid Monitoring'!F31=D4),IF(E4="All",TRUE(),'Bid Monitoring'!E31=E4),IF(F4="All",TRUE(),'Bid Monitoring'!R31=F4)),'Bid Monitoring'!D31,"") | C41: =IF(AND('Bid Monitoring'!B31<>"",IF(B4="All",TRUE(),'Bid Monitoring'!N31=B4),IF(C4="All",TRUE(),'Bid Monitoring'!L31=C4),IF(D4="All",TRUE(),'Bid Monitoring'!F31=D4),IF(E4="All",TRUE(),'Bid Monitoring'!E31=E4),IF(F4="All",TRUE(),'Bid Monitoring'!R31=F4)),'Bid Monitoring'!C31,"") | D41: =IF(AND('Bid Monitoring'!B31<>"",IF(B4="All",TRUE(),'Bid Monitoring'!N31=B4),IF(C4="All",TRUE(),'Bid Monitoring'!L31=C4),IF(D4="All",TRUE(),'Bid Monitoring'!F31=D4),IF(E4="All",TRUE(),'Bid Monitoring'!E31=E4),IF(F4="All",TRUE(),'Bid Monitoring'!R31=F4)),'Bid Monitoring'!E31,"") | E41: =IF(AND('Bid Monitoring'!B31<>"",IF(B4="All",TRUE(),'Bid Monitoring'!N31=B4),IF(C4="All",TRUE(),'Bid Monitoring'!L31=C4),IF(D4="All",TRUE(),'Bid Monitoring'!F31=D4),IF(E4="All",TRUE(),'Bid Monitoring'!E31=E4),IF(F4="All",TRUE(),'Bid Monitoring'!R31=F4)),'Bid Monitoring'!F31,"") | F41: =IF(AND('Bid Monitoring'!B31<>"",IF(B4="All",TRUE(),'Bid Monitoring'!N31=B4),IF(C4="All",TRUE(),'Bid Monitoring'!L31=C4),IF(D4="All",TRUE(),'Bid Monitoring'!F31=D4),IF(E4="All",TRUE(),'Bid Monitoring'!E31=E4),IF(F4="All",TRUE(),'Bid Monitoring'!R31=F4)),'Bid Monitoring'!H31,"") | G41: =IF(AND('Bid Monitoring'!B31<>"",IF(B4="All",TRUE(),'Bid Monitoring'!N31=B4),IF(C4="All",TRUE(),'Bid Monitoring'!L31=C4),IF(D4="All",TRUE(),'Bid Monitoring'!F31=D4),IF(E4="All",TRUE(),'Bid Monitoring'!E31=E4),IF(F4="All",TRUE(),'Bid Monitoring'!R31=F4)),'Bid Monitoring'!I31,"") | H41: =IF(AND('Bid Monitoring'!B31<>"",IF(B4="All",TRUE(),'Bid Monitoring'!N31=B4),IF(C4="All",TRUE(),'Bid Monitoring'!L31=C4),IF(D4="All",TRUE(),'Bid Monitoring'!F31=D4),IF(E4="All",TRUE(),'Bid Monitoring'!E31=E4),IF(F4="All",TRUE(),'Bid Monitoring'!R31=F4)),'Bid Monitoring'!K31,"") | I41: =IF(AND('Bid Monitoring'!B31<>"",IF(B4="All",TRUE(),'Bid Monitoring'!N31=B4),IF(C4="All",TRUE(),'Bid Monitoring'!L31=C4),IF(D4="All",TRUE(),'Bid Monitoring'!F31=D4),IF(E4="All",TRUE(),'Bid Monitoring'!E31=E4),IF(F4="All",TRUE(),'Bid Monitoring'!R31=F4)),'Bid Monitoring'!N31,"") | J41: =IF(AND('Bid Monitoring'!B31<>"",IF(B4="All",TRUE(),'Bid Monitoring'!N31=B4),IF(C4="All",TRUE(),'Bid Monitoring'!L31=C4),IF(D4="All",TRUE(),'Bid Monitoring'!F31=D4),IF(E4="All",TRUE(),'Bid Monitoring'!E31=E4),IF(F4="All",TRUE(),'Bid Monitoring'!R31=F4)),'Bid Monitoring'!L31,"")
A42: =IF(AND('Bid Monitoring'!B32<>"",IF(B4="All",TRUE(),'Bid Monitoring'!N32=B4),IF(C4="All",TRUE(),'Bid Monitoring'!L32=C4),IF(D4="All",TRUE(),'Bid Monitoring'!F32=D4),IF(E4="All",TRUE(),'Bid Monitoring'!E32=E4),IF(F4="All",TRUE(),'Bid Monitoring'!R32=F4)),'Bid Monitoring'!B32,"") | B42: =IF(AND('Bid Monitoring'!B32<>"",IF(B4="All",TRUE(),'Bid Monitoring'!N32=B4),IF(C4="All",TRUE(),'Bid Monitoring'!L32=C4),IF(D4="All",TRUE(),'Bid Monitoring'!F32=D4),IF(E4="All",TRUE(),'Bid Monitoring'!E32=E4),IF(F4="All",TRUE(),'Bid Monitoring'!R32=F4)),'Bid Monitoring'!D32,"") | C42: =IF(AND('Bid Monitoring'!B32<>"",IF(B4="All",TRUE(),'Bid Monitoring'!N32=B4),IF(C4="All",TRUE(),'Bid Monitoring'!L32=C4),IF(D4="All",TRUE(),'Bid Monitoring'!F32=D4),IF(E4="All",TRUE(),'Bid Monitoring'!E32=E4),IF(F4="All",TRUE(),'Bid Monitoring'!R32=F4)),'Bid Monitoring'!C32,"") | D42: =IF(AND('Bid Monitoring'!B32<>"",IF(B4="All",TRUE(),'Bid Monitoring'!N32=B4),IF(C4="All",TRUE(),'Bid Monitoring'!L32=C4),IF(D4="All",TRUE(),'Bid Monitoring'!F32=D4),IF(E4="All",TRUE(),'Bid Monitoring'!E32=E4),IF(F4="All",TRUE(),'Bid Monitoring'!R32=F4)),'Bid Monitoring'!E32,"") | E42: =IF(AND('Bid Monitoring'!B32<>"",IF(B4="All",TRUE(),'Bid Monitoring'!N32=B4),IF(C4="All",TRUE(),'Bid Monitoring'!L32=C4),IF(D4="All",TRUE(),'Bid Monitoring'!F32=D4),IF(E4="All",TRUE(),'Bid Monitoring'!E32=E4),IF(F4="All",TRUE(),'Bid Monitoring'!R32=F4)),'Bid Monitoring'!F32,"") | F42: =IF(AND('Bid Monitoring'!B32<>"",IF(B4="All",TRUE(),'Bid Monitoring'!N32=B4),IF(C4="All",TRUE(),'Bid Monitoring'!L32=C4),IF(D4="All",TRUE(),'Bid Monitoring'!F32=D4),IF(E4="All",TRUE(),'Bid Monitoring'!E32=E4),IF(F4="All",TRUE(),'Bid Monitoring'!R32=F4)),'Bid Monitoring'!H32,"") | G42: =IF(AND('Bid Monitoring'!B32<>"",IF(B4="All",TRUE(),'Bid Monitoring'!N32=B4),IF(C4="All",TRUE(),'Bid Monitoring'!L32=C4),IF(D4="All",TRUE(),'Bid Monitoring'!F32=D4),IF(E4="All",TRUE(),'Bid Monitoring'!E32=E4),IF(F4="All",TRUE(),'Bid Monitoring'!R32=F4)),'Bid Monitoring'!I32,"") | H42: =IF(AND('Bid Monitoring'!B32<>"",IF(B4="All",TRUE(),'Bid Monitoring'!N32=B4),IF(C4="All",TRUE(),'Bid Monitoring'!L32=C4),IF(D4="All",TRUE(),'Bid Monitoring'!F32=D4),IF(E4="All",TRUE(),'Bid Monitoring'!E32=E4),IF(F4="All",TRUE(),'Bid Monitoring'!R32=F4)),'Bid Monitoring'!K32,"") | I42: =IF(AND('Bid Monitoring'!B32<>"",IF(B4="All",TRUE(),'Bid Monitoring'!N32=B4),IF(C4="All",TRUE(),'Bid Monitoring'!L32=C4),IF(D4="All",TRUE(),'Bid Monitoring'!F32=D4),IF(E4="All",TRUE(),'Bid Monitoring'!E32=E4),IF(F4="All",TRUE(),'Bid Monitoring'!R32=F4)),'Bid Monitoring'!N32,"") | J42: =IF(AND('Bid Monitoring'!B32<>"",IF(B4="All",TRUE(),'Bid Monitoring'!N32=B4),IF(C4="All",TRUE(),'Bid Monitoring'!L32=C4),IF(D4="All",TRUE(),'Bid Monitoring'!F32=D4),IF(E4="All",TRUE(),'Bid Monitoring'!E32=E4),IF(F4="All",TRUE(),'Bid Monitoring'!R32=F4)),'Bid Monitoring'!L32,"")
A43: =IF(AND('Bid Monitoring'!B33<>"",IF(B4="All",TRUE(),'Bid Monitoring'!N33=B4),IF(C4="All",TRUE(),'Bid Monitoring'!L33=C4),IF(D4="All",TRUE(),'Bid Monitoring'!F33=D4),IF(E4="All",TRUE(),'Bid Monitoring'!E33=E4),IF(F4="All",TRUE(),'Bid Monitoring'!R33=F4)),'Bid Monitoring'!B33,"") | B43: =IF(AND('Bid Monitoring'!B33<>"",IF(B4="All",TRUE(),'Bid Monitoring'!N33=B4),IF(C4="All",TRUE(),'Bid Monitoring'!L33=C4),IF(D4="All",TRUE(),'Bid Monitoring'!F33=D4),IF(E4="All",TRUE(),'Bid Monitoring'!E33=E4),IF(F4="All",TRUE(),'Bid Monitoring'!R33=F4)),'Bid Monitoring'!D33,"") | C43: =IF(AND('Bid Monitoring'!B33<>"",IF(B4="All",TRUE(),'Bid Monitoring'!N33=B4),IF(C4="All",TRUE(),'Bid Monitoring'!L33=C4),IF(D4="All",TRUE(),'Bid Monitoring'!F33=D4),IF(E4="All",TRUE(),'Bid Monitoring'!E33=E4),IF(F4="All",TRUE(),'Bid Monitoring'!R33=F4)),'Bid Monitoring'!C33,"") | D43: =IF(AND('Bid Monitoring'!B33<>"",IF(B4="All",TRUE(),'Bid Monitoring'!N33=B4),IF(C4="All",TRUE(),'Bid Monitoring'!L33=C4),IF(D4="All",TRUE(),'Bid Monitoring'!F33=D4),IF(E4="All",TRUE(),'Bid Monitoring'!E33=E4),IF(F4="All",TRUE(),'Bid Monitoring'!R33=F4)),'Bid Monitoring'!E33,"") | E43: =IF(AND('Bid Monitoring'!B33<>"",IF(B4="All",TRUE(),'Bid Monitoring'!N33=B4),IF(C4="All",TRUE(),'Bid Monitoring'!L33=C4),IF(D4="All",TRUE(),'Bid Monitoring'!F33=D4),IF(E4="All",TRUE(),'Bid Monitoring'!E33=E4),IF(F4="All",TRUE(),'Bid Monitoring'!R33=F4)),'Bid Monitoring'!F33,"") | F43: =IF(AND('Bid Monitoring'!B33<>"",IF(B4="All",TRUE(),'Bid Monitoring'!N33=B4),IF(C4="All",TRUE(),'Bid Monitoring'!L33=C4),IF(D4="All",TRUE(),'Bid Monitoring'!F33=D4),IF(E4="All",TRUE(),'Bid Monitoring'!E33=E4),IF(F4="All",TRUE(),'Bid Monitoring'!R33=F4)),'Bid Monitoring'!H33,"") | G43: =IF(AND('Bid Monitoring'!B33<>"",IF(B4="All",TRUE(),'Bid Monitoring'!N33=B4),IF(C4="All",TRUE(),'Bid Monitoring'!L33=C4),IF(D4="All",TRUE(),'Bid Monitoring'!F33=D4),IF(E4="All",TRUE(),'Bid Monitoring'!E33=E4),IF(F4="All",TRUE(),'Bid Monitoring'!R33=F4)),'Bid Monitoring'!I33,"") | H43: =IF(AND('Bid Monitoring'!B33<>"",IF(B4="All",TRUE(),'Bid Monitoring'!N33=B4),IF(C4="All",TRUE(),'Bid Monitoring'!L33=C4),IF(D4="All",TRUE(),'Bid Monitoring'!F33=D4),IF(E4="All",TRUE(),'Bid Monitoring'!E33=E4),IF(F4="All",TRUE(),'Bid Monitoring'!R33=F4)),'Bid Monitoring'!K33,"") | I43: =IF(AND('Bid Monitoring'!B33<>"",IF(B4="All",TRUE(),'Bid Monitoring'!N33=B4),IF(C4="All",TRUE(),'Bid Monitoring'!L33=C4),IF(D4="All",TRUE(),'Bid Monitoring'!F33=D4),IF(E4="All",TRUE(),'Bid Monitoring'!E33=E4),IF(F4="All",TRUE(),'Bid Monitoring'!R33=F4)),'Bid Monitoring'!N33,"") | J43: =IF(AND('Bid Monitoring'!B33<>"",IF(B4="All",TRUE(),'Bid Monitoring'!N33=B4),IF(C4="All",TRUE(),'Bid Monitoring'!L33=C4),IF(D4="All",TRUE(),'Bid Monitoring'!F33=D4),IF(E4="All",TRUE(),'Bid Monitoring'!E33=E4),IF(F4="All",TRUE(),'Bid Monitoring'!R33=F4)),'Bid Monitoring'!L33,"")
A44: =IF(AND('Bid Monitoring'!B34<>"",IF(B4="All",TRUE(),'Bid Monitoring'!N34=B4),IF(C4="All",TRUE(),'Bid Monitoring'!L34=C4),IF(D4="All",TRUE(),'Bid Monitoring'!F34=D4),IF(E4="All",TRUE(),'Bid Monitoring'!E34=E4),IF(F4="All",TRUE(),'Bid Monitoring'!R34=F4)),'Bid Monitoring'!B34,"") | B44: =IF(AND('Bid Monitoring'!B34<>"",IF(B4="All",TRUE(),'Bid Monitoring'!N34=B4),IF(C4="All",TRUE(),'Bid Monitoring'!L34=C4),IF(D4="All",TRUE(),'Bid Monitoring'!F34=D4),IF(E4="All",TRUE(),'Bid Monitoring'!E34=E4),IF(F4="All",TRUE(),'Bid Monitoring'!R34=F4)),'Bid Monitoring'!D34,"") | C44: =IF(AND('Bid Monitoring'!B34<>"",IF(B4="All",TRUE(),'Bid Monitoring'!N34=B4),IF(C4="All",TRUE(),'Bid Monitoring'!L34=C4),IF(D4="All",TRUE(),'Bid Monitoring'!F34=D4),IF(E4="All",TRUE(),'Bid Monitoring'!E34=E4),IF(F4="All",TRUE(),'Bid Monitoring'!R34=F4)),'Bid Monitoring'!C34,"") | D44: =IF(AND('Bid Monitoring'!B34<>"",IF(B4="All",TRUE(),'Bid Monitoring'!N34=B4),IF(C4="All",TRUE(),'Bid Monitoring'!L34=C4),IF(D4="All",TRUE(),'Bid Monitoring'!F34=D4),IF(E4="All",TRUE(),'Bid Monitoring'!E34=E4),IF(F4="All",TRUE(),'Bid Monitoring'!R34=F4)),'Bid Monitoring'!E34,"") | E44: =IF(AND('Bid Monitoring'!B34<>"",IF(B4="All",TRUE(),'Bid Monitoring'!N34=B4),IF(C4="All",TRUE(),'Bid Monitoring'!L34=C4),IF(D4="All",TRUE(),'Bid Monitoring'!F34=D4),IF(E4="All",TRUE(),'Bid Monitoring'!E34=E4),IF(F4="All",TRUE(),'Bid Monitoring'!R34=F4)),'Bid Monitoring'!F34,"") | F44: =IF(AND('Bid Monitoring'!B34<>"",IF(B4="All",TRUE(),'Bid Monitoring'!N34=B4),IF(C4="All",TRUE(),'Bid Monitoring'!L34=C4),IF(D4="All",TRUE(),'Bid Monitoring'!F34=D4),IF(E4="All",TRUE(),'Bid Monitoring'!E34=E4),IF(F4="All",TRUE(),'Bid Monitoring'!R34=F4)),'Bid Monitoring'!H34,"") | G44: =IF(AND('Bid Monitoring'!B34<>"",IF(B4="All",TRUE(),'Bid Monitoring'!N34=B4),IF(C4="All",TRUE(),'Bid Monitoring'!L34=C4),IF(D4="All",TRUE(),'Bid Monitoring'!F34=D4),IF(E4="All",TRUE(),'Bid Monitoring'!E34=E4),IF(F4="All",TRUE(),'Bid Monitoring'!R34=F4)),'Bid Monitoring'!I34,"") | H44: =IF(AND('Bid Monitoring'!B34<>"",IF(B4="All",TRUE(),'Bid Monitoring'!N34=B4),IF(C4="All",TRUE(),'Bid Monitoring'!L34=C4),IF(D4="All",TRUE(),'Bid Monitoring'!F34=D4),IF(E4="All",TRUE(),'Bid Monitoring'!E34=E4),IF(F4="All",TRUE(),'Bid Monitoring'!R34=F4)),'Bid Monitoring'!K34,"") | I44: =IF(AND('Bid Monitoring'!B34<>"",IF(B4="All",TRUE(),'Bid Monitoring'!N34=B4),IF(C4="All",TRUE(),'Bid Monitoring'!L34=C4),IF(D4="All",TRUE(),'Bid Monitoring'!F34=D4),IF(E4="All",TRUE(),'Bid Monitoring'!E34=E4),IF(F4="All",TRUE(),'Bid Monitoring'!R34=F4)),'Bid Monitoring'!N34,"") | J44: =IF(AND('Bid Monitoring'!B34<>"",IF(B4="All",TRUE(),'Bid Monitoring'!N34=B4),IF(C4="All",TRUE(),'Bid Monitoring'!L34=C4),IF(D4="All",TRUE(),'Bid Monitoring'!F34=D4),IF(E4="All",TRUE(),'Bid Monitoring'!E34=E4),IF(F4="All",TRUE(),'Bid Monitoring'!R34=F4)),'Bid Monitoring'!L34,"")
A45: =IF(AND('Bid Monitoring'!B35<>"",IF(B4="All",TRUE(),'Bid Monitoring'!N35=B4),IF(C4="All",TRUE(),'Bid Monitoring'!L35=C4),IF(D4="All",TRUE(),'Bid Monitoring'!F35=D4),IF(E4="All",TRUE(),'Bid Monitoring'!E35=E4),IF(F4="All",TRUE(),'Bid Monitoring'!R35=F4)),'Bid Monitoring'!B35,"") | B45: =IF(AND('Bid Monitoring'!B35<>"",IF(B4="All",TRUE(),'Bid Monitoring'!N35=B4),IF(C4="All",TRUE(),'Bid Monitoring'!L35=C4),IF(D4="All",TRUE(),'Bid Monitoring'!F35=D4),IF(E4="All",TRUE(),'Bid Monitoring'!E35=E4),IF(F4="All",TRUE(),'Bid Monitoring'!R35=F4)),'Bid Monitoring'!D35,"") | C45: =IF(AND('Bid Monitoring'!B35<>"",IF(B4="All",TRUE(),'Bid Monitoring'!N35=B4),IF(C4="All",TRUE(),'Bid Monitoring'!L35=C4),IF(D4="All",TRUE(),'Bid Monitoring'!F35=D4),IF(E4="All",TRUE(),'Bid Monitoring'!E35=E4),IF(F4="All",TRUE(),'Bid Monitoring'!R35=F4)),'Bid Monitoring'!C35,"") | D45: =IF(AND('Bid Monitoring'!B35<>"",IF(B4="All",TRUE(),'Bid Monitoring'!N35=B4),IF(C4="All",TRUE(),'Bid Monitoring'!L35=C4),IF(D4="All",TRUE(),'Bid Monitoring'!F35=D4),IF(E4="All",TRUE(),'Bid Monitoring'!E35=E4),IF(F4="All",TRUE(),'Bid Monitoring'!R35=F4)),'Bid Monitoring'!E35,"") | E45: =IF(AND('Bid Monitoring'!B35<>"",IF(B4="All",TRUE(),'Bid Monitoring'!N35=B4),IF(C4="All",TRUE(),'Bid Monitoring'!L35=C4),IF(D4="All",TRUE(),'Bid Monitoring'!F35=D4),IF(E4="All",TRUE(),'Bid Monitoring'!E35=E4),IF(F4="All",TRUE(),'Bid Monitoring'!R35=F4)),'Bid Monitoring'!F35,"") | F45: =IF(AND('Bid Monitoring'!B35<>"",IF(B4="All",TRUE(),'Bid Monitoring'!N35=B4),IF(C4="All",TRUE(),'Bid Monitoring'!L35=C4),IF(D4="All",TRUE(),'Bid Monitoring'!F35=D4),IF(E4="All",TRUE(),'Bid Monitoring'!E35=E4),IF(F4="All",TRUE(),'Bid Monitoring'!R35=F4)),'Bid Monitoring'!H35,"") | G45: =IF(AND('Bid Monitoring'!B35<>"",IF(B4="All",TRUE(),'Bid Monitoring'!N35=B4),IF(C4="All",TRUE(),'Bid Monitoring'!L35=C4),IF(D4="All",TRUE(),'Bid Monitoring'!F35=D4),IF(E4="All",TRUE(),'Bid Monitoring'!E35=E4),IF(F4="All",TRUE(),'Bid Monitoring'!R35=F4)),'Bid Monitoring'!I35,"") | H45: =IF(AND('Bid Monitoring'!B35<>"",IF(B4="All",TRUE(),'Bid Monitoring'!N35=B4),IF(C4="All",TRUE(),'Bid Monitoring'!L35=C4),IF(D4="All",TRUE(),'Bid Monitoring'!F35=D4),IF(E4="All",TRUE(),'Bid Monitoring'!E35=E4),IF(F4="All",TRUE(),'Bid Monitoring'!R35=F4)),'Bid Monitoring'!K35,"") | I45: =IF(AND('Bid Monitoring'!B35<>"",IF(B4="All",TRUE(),'Bid Monitoring'!N35=B4),IF(C4="All",TRUE(),'Bid Monitoring'!L35=C4),IF(D4="All",TRUE(),'Bid Monitoring'!F35=D4),IF(E4="All",TRUE(),'Bid Monitoring'!E35=E4),IF(F4="All",TRUE(),'Bid Monitoring'!R35=F4)),'Bid Monitoring'!N35,"") | J45: =IF(AND('Bid Monitoring'!B35<>"",IF(B4="All",TRUE(),'Bid Monitoring'!N35=B4),IF(C4="All",TRUE(),'Bid Monitoring'!L35=C4),IF(D4="All",TRUE(),'Bid Monitoring'!F35=D4),IF(E4="All",TRUE(),'Bid Monitoring'!E35=E4),IF(F4="All",TRUE(),'Bid Monitoring'!R35=F4)),'Bid Monitoring'!L35,"")
A46: =IF(AND('Bid Monitoring'!B36<>"",IF(B4="All",TRUE(),'Bid Monitoring'!N36=B4),IF(C4="All",TRUE(),'Bid Monitoring'!L36=C4),IF(D4="All",TRUE(),'Bid Monitoring'!F36=D4),IF(E4="All",TRUE(),'Bid Monitoring'!E36=E4),IF(F4="All",TRUE(),'Bid Monitoring'!R36=F4)),'Bid Monitoring'!B36,"") | B46: =IF(AND('Bid Monitoring'!B36<>"",IF(B4="All",TRUE(),'Bid Monitoring'!N36=B4),IF(C4="All",TRUE(),'Bid Monitoring'!L36=C4),IF(D4="All",TRUE(),'Bid Monitoring'!F36=D4),IF(E4="All",TRUE(),'Bid Monitoring'!E36=E4),IF(F4="All",TRUE(),'Bid Monitoring'!R36=F4)),'Bid Monitoring'!D36,"") | C46: =IF(AND('Bid Monitoring'!B36<>"",IF(B4="All",TRUE(),'Bid Monitoring'!N36=B4),IF(C4="All",TRUE(),'Bid Monitoring'!L36=C4),IF(D4="All",TRUE(),'Bid Monitoring'!F36=D4),IF(E4="All",TRUE(),'Bid Monitoring'!E36=E4),IF(F4="All",TRUE(),'Bid Monitoring'!R36=F4)),'Bid Monitoring'!C36,"") | D46: =IF(AND('Bid Monitoring'!B36<>"",IF(B4="All",TRUE(),'Bid Monitoring'!N36=B4),IF(C4="All",TRUE(),'Bid Monitoring'!L36=C4),IF(D4="All",TRUE(),'Bid Monitoring'!F36=D4),IF(E4="All",TRUE(),'Bid Monitoring'!E36=E4),IF(F4="All",TRUE(),'Bid Monitoring'!R36=F4)),'Bid Monitoring'!E36,"") | E46: =IF(AND('Bid Monitoring'!B36<>"",IF(B4="All",TRUE(),'Bid Monitoring'!N36=B4),IF(C4="All",TRUE(),'Bid Monitoring'!L36=C4),IF(D4="All",TRUE(),'Bid Monitoring'!F36=D4),IF(E4="All",TRUE(),'Bid Monitoring'!E36=E4),IF(F4="All",TRUE(),'Bid Monitoring'!R36=F4)),'Bid Monitoring'!F36,"") | F46: =IF(AND('Bid Monitoring'!B36<>"",IF(B4="All",TRUE(),'Bid Monitoring'!N36=B4),IF(C4="All",TRUE(),'Bid Monitoring'!L36=C4),IF(D4="All",TRUE(),'Bid Monitoring'!F36=D4),IF(E4="All",TRUE(),'Bid Monitoring'!E36=E4),IF(F4="All",TRUE(),'Bid Monitoring'!R36=F4)),'Bid Monitoring'!H36,"") | G46: =IF(AND('Bid Monitoring'!B36<>"",IF(B4="All",TRUE(),'Bid Monitoring'!N36=B4),IF(C4="All",TRUE(),'Bid Monitoring'!L36=C4),IF(D4="All",TRUE(),'Bid Monitoring'!F36=D4),IF(E4="All",TRUE(),'Bid Monitoring'!E36=E4),IF(F4="All",TRUE(),'Bid Monitoring'!R36=F4)),'Bid Monitoring'!I36,"") | H46: =IF(AND('Bid Monitoring'!B36<>"",IF(B4="All",TRUE(),'Bid Monitoring'!N36=B4),IF(C4="All",TRUE(),'Bid Monitoring'!L36=C4),IF(D4="All",TRUE(),'Bid Monitoring'!F36=D4),IF(E4="All",TRUE(),'Bid Monitoring'!E36=E4),IF(F4="All",TRUE(),'Bid Monitoring'!R36=F4)),'Bid Monitoring'!K36,"") | I46: =IF(AND('Bid Monitoring'!B36<>"",IF(B4="All",TRUE(),'Bid Monitoring'!N36=B4),IF(C4="All",TRUE(),'Bid Monitoring'!L36=C4),IF(D4="All",TRUE(),'Bid Monitoring'!F36=D4),IF(E4="All",TRUE(),'Bid Monitoring'!E36=E4),IF(F4="All",TRUE(),'Bid Monitoring'!R36=F4)),'Bid Monitoring'!N36,"") | J46: =IF(AND('Bid Monitoring'!B36<>"",IF(B4="All",TRUE(),'Bid Monitoring'!N36=B4),IF(C4="All",TRUE(),'Bid Monitoring'!L36=C4),IF(D4="All",TRUE(),'Bid Monitoring'!F36=D4),IF(E4="All",TRUE(),'Bid Monitoring'!E36=E4),IF(F4="All",TRUE(),'Bid Monitoring'!R36=F4)),'Bid Monitoring'!L36,"")
A47: =IF(AND('Bid Monitoring'!B37<>"",IF(B4="All",TRUE(),'Bid Monitoring'!N37=B4),IF(C4="All",TRUE(),'Bid Monitoring'!L37=C4),IF(D4="All",TRUE(),'Bid Monitoring'!F37=D4),IF(E4="All",TRUE(),'Bid Monitoring'!E37=E4),IF(F4="All",TRUE(),'Bid Monitoring'!R37=F4)),'Bid Monitoring'!B37,"") | B47: =IF(AND('Bid Monitoring'!B37<>"",IF(B4="All",TRUE(),'Bid Monitoring'!N37=B4),IF(C4="All",TRUE(),'Bid Monitoring'!L37=C4),IF(D4="All",TRUE(),'Bid Monitoring'!F37=D4),IF(E4="All",TRUE(),'Bid Monitoring'!E37=E4),IF(F4="All",TRUE(),'Bid Monitoring'!R37=F4)),'Bid Monitoring'!D37,"") | C47: =IF(AND('Bid Monitoring'!B37<>"",IF(B4="All",TRUE(),'Bid Monitoring'!N37=B4),IF(C4="All",TRUE(),'Bid Monitoring'!L37=C4),IF(D4="All",TRUE(),'Bid Monitoring'!F37=D4),IF(E4="All",TRUE(),'Bid Monitoring'!E37=E4),IF(F4="All",TRUE(),'Bid Monitoring'!R37=F4)),'Bid Monitoring'!C37,"") | D47: =IF(AND('Bid Monitoring'!B37<>"",IF(B4="All",TRUE(),'Bid Monitoring'!N37=B4),IF(C4="All",TRUE(),'Bid Monitoring'!L37=C4),IF(D4="All",TRUE(),'Bid Monitoring'!F37=D4),IF(E4="All",TRUE(),'Bid Monitoring'!E37=E4),IF(F4="All",TRUE(),'Bid Monitoring'!R37=F4)),'Bid Monitoring'!E37,"") | E47: =IF(AND('Bid Monitoring'!B37<>"",IF(B4="All",TRUE(),'Bid Monitoring'!N37=B4),IF(C4="All",TRUE(),'Bid Monitoring'!L37=C4),IF(D4="All",TRUE(),'Bid Monitoring'!F37=D4),IF(E4="All",TRUE(),'Bid Monitoring'!E37=E4),IF(F4="All",TRUE(),'Bid Monitoring'!R37=F4)),'Bid Monitoring'!F37,"") | F47: =IF(AND('Bid Monitoring'!B37<>"",IF(B4="All",TRUE(),'Bid Monitoring'!N37=B4),IF(C4="All",TRUE(),'Bid Monitoring'!L37=C4),IF(D4="All",TRUE(),'Bid Monitoring'!F37=D4),IF(E4="All",TRUE(),'Bid Monitoring'!E37=E4),IF(F4="All",TRUE(),'Bid Monitoring'!R37=F4)),'Bid Monitoring'!H37,"") | G47: =IF(AND('Bid Monitoring'!B37<>"",IF(B4="All",TRUE(),'Bid Monitoring'!N37=B4),IF(C4="All",TRUE(),'Bid Monitoring'!L37=C4),IF(D4="All",TRUE(),'Bid Monitoring'!F37=D4),IF(E4="All",TRUE(),'Bid Monitoring'!E37=E4),IF(F4="All",TRUE(),'Bid Monitoring'!R37=F4)),'Bid Monitoring'!I37,"") | H47: =IF(AND('Bid Monitoring'!B37<>"",IF(B4="All",TRUE(),'Bid Monitoring'!N37=B4),IF(C4="All",TRUE(),'Bid Monitoring'!L37=C4),IF(D4="All",TRUE(),'Bid Monitoring'!F37=D4),IF(E4="All",TRUE(),'Bid Monitoring'!E37=E4),IF(F4="All",TRUE(),'Bid Monitoring'!R37=F4)),'Bid Monitoring'!K37,"") | I47: =IF(AND('Bid Monitoring'!B37<>"",IF(B4="All",TRUE(),'Bid Monitoring'!N37=B4),IF(C4="All",TRUE(),'Bid Monitoring'!L37=C4),IF(D4="All",TRUE(),'Bid Monitoring'!F37=D4),IF(E4="All",TRUE(),'Bid Monitoring'!E37=E4),IF(F4="All",TRUE(),'Bid Monitoring'!R37=F4)),'Bid Monitoring'!N37,"") | J47: =IF(AND('Bid Monitoring'!B37<>"",IF(B4="All",TRUE(),'Bid Monitoring'!N37=B4),IF(C4="All",TRUE(),'Bid Monitoring'!L37=C4),IF(D4="All",TRUE(),'Bid Monitoring'!F37=D4),IF(E4="All",TRUE(),'Bid Monitoring'!E37=E4),IF(F4="All",TRUE(),'Bid Monitoring'!R37=F4)),'Bid Monitoring'!L37,"")
A48: =IF(AND('Bid Monitoring'!B38<>"",IF(B4="All",TRUE(),'Bid Monitoring'!N38=B4),IF(C4="All",TRUE(),'Bid Monitoring'!L38=C4),IF(D4="All",TRUE(),'Bid Monitoring'!F38=D4),IF(E4="All",TRUE(),'Bid Monitoring'!E38=E4),IF(F4="All",TRUE(),'Bid Monitoring'!R38=F4)),'Bid Monitoring'!B38,"") | B48: =IF(AND('Bid Monitoring'!B38<>"",IF(B4="All",TRUE(),'Bid Monitoring'!N38=B4),IF(C4="All",TRUE(),'Bid Monitoring'!L38=C4),IF(D4="All",TRUE(),'Bid Monitoring'!F38=D4),IF(E4="All",TRUE(),'Bid Monitoring'!E38=E4),IF(F4="All",TRUE(),'Bid Monitoring'!R38=F4)),'Bid Monitoring'!D38,"") | C48: =IF(AND('Bid Monitoring'!B38<>"",IF(B4="All",TRUE(),'Bid Monitoring'!N38=B4),IF(C4="All",TRUE(),'Bid Monitoring'!L38=C4),IF(D4="All",TRUE(),'Bid Monitoring'!F38=D4),IF(E4="All",TRUE(),'Bid Monitoring'!E38=E4),IF(F4="All",TRUE(),'Bid Monitoring'!R38=F4)),'Bid Monitoring'!C38,"") | D48: =IF(AND('Bid Monitoring'!B38<>"",IF(B4="All",TRUE(),'Bid Monitoring'!N38=B4),IF(C4="All",TRUE(),'Bid Monitoring'!L38=C4),IF(D4="All",TRUE(),'Bid Monitoring'!F38=D4),IF(E4="All",TRUE(),'Bid Monitoring'!E38=E4),IF(F4="All",TRUE(),'Bid Monitoring'!R38=F4)),'Bid Monitoring'!E38,"") | E48: =IF(AND('Bid Monitoring'!B38<>"",IF(B4="All",TRUE(),'Bid Monitoring'!N38=B4),IF(C4="All",TRUE(),'Bid Monitoring'!L38=C4),IF(D4="All",TRUE(),'Bid Monitoring'!F38=D4),IF(E4="All",TRUE(),'Bid Monitoring'!E38=E4),IF(F4="All",TRUE(),'Bid Monitoring'!R38=F4)),'Bid Monitoring'!F38,"") | F48: =IF(AND('Bid Monitoring'!B38<>"",IF(B4="All",TRUE(),'Bid Monitoring'!N38=B4),IF(C4="All",TRUE(),'Bid Monitoring'!L38=C4),IF(D4="All",TRUE(),'Bid Monitoring'!F38=D4),IF(E4="All",TRUE(),'Bid Monitoring'!E38=E4),IF(F4="All",TRUE(),'Bid Monitoring'!R38=F4)),'Bid Monitoring'!H38,"") | G48: =IF(AND('Bid Monitoring'!B38<>"",IF(B4="All",TRUE(),'Bid Monitoring'!N38=B4),IF(C4="All",TRUE(),'Bid Monitoring'!L38=C4),IF(D4="All",TRUE(),'Bid Monitoring'!F38=D4),IF(E4="All",TRUE(),'Bid Monitoring'!E38=E4),IF(F4="All",TRUE(),'Bid Monitoring'!R38=F4)),'Bid Monitoring'!I38,"") | H48: =IF(AND('Bid Monitoring'!B38<>"",IF(B4="All",TRUE(),'Bid Monitoring'!N38=B4),IF(C4="All",TRUE(),'Bid Monitoring'!L38=C4),IF(D4="All",TRUE(),'Bid Monitoring'!F38=D4),IF(E4="All",TRUE(),'Bid Monitoring'!E38=E4),IF(F4="All",TRUE(),'Bid Monitoring'!R38=F4)),'Bid Monitoring'!K38,"") | I48: =IF(AND('Bid Monitoring'!B38<>"",IF(B4="All",TRUE(),'Bid Monitoring'!N38=B4),IF(C4="All",TRUE(),'Bid Monitoring'!L38=C4),IF(D4="All",TRUE(),'Bid Monitoring'!F38=D4),IF(E4="All",TRUE(),'Bid Monitoring'!E38=E4),IF(F4="All",TRUE(),'Bid Monitoring'!R38=F4)),'Bid Monitoring'!N38,"") | J48: =IF(AND('Bid Monitoring'!B38<>"",IF(B4="All",TRUE(),'Bid Monitoring'!N38=B4),IF(C4="All",TRUE(),'Bid Monitoring'!L38=C4),IF(D4="All",TRUE(),'Bid Monitoring'!F38=D4),IF(E4="All",TRUE(),'Bid Monitoring'!E38=E4),IF(F4="All",TRUE(),'Bid Monitoring'!R38=F4)),'Bid Monitoring'!L38,"")
A49: =IF(AND('Bid Monitoring'!B39<>"",IF(B4="All",TRUE(),'Bid Monitoring'!N39=B4),IF(C4="All",TRUE(),'Bid Monitoring'!L39=C4),IF(D4="All",TRUE(),'Bid Monitoring'!F39=D4),IF(E4="All",TRUE(),'Bid Monitoring'!E39=E4),IF(F4="All",TRUE(),'Bid Monitoring'!R39=F4)),'Bid Monitoring'!B39,"") | B49: =IF(AND('Bid Monitoring'!B39<>"",IF(B4="All",TRUE(),'Bid Monitoring'!N39=B4),IF(C4="All",TRUE(),'Bid Monitoring'!L39=C4),IF(D4="All",TRUE(),'Bid Monitoring'!F39=D4),IF(E4="All",TRUE(),'Bid Monitoring'!E39=E4),IF(F4="All",TRUE(),'Bid Monitoring'!R39=F4)),'Bid Monitoring'!D39,"") | C49: =IF(AND('Bid Monitoring'!B39<>"",IF(B4="All",TRUE(),'Bid Monitoring'!N39=B4),IF(C4="All",TRUE(),'Bid Monitoring'!L39=C4),IF(D4="All",TRUE(),'Bid Monitoring'!F39=D4),IF(E4="All",TRUE(),'Bid Monitoring'!E39=E4),IF(F4="All",TRUE(),'Bid Monitoring'!R39=F4)),'Bid Monitoring'!C39,"") | D49: =IF(AND('Bid Monitoring'!B39<>"",IF(B4="All",TRUE(),'Bid Monitoring'!N39=B4),IF(C4="All",TRUE(),'Bid Monitoring'!L39=C4),IF(D4="All",TRUE(),'Bid Monitoring'!F39=D4),IF(E4="All",TRUE(),'Bid Monitoring'!E39=E4),IF(F4="All",TRUE(),'Bid Monitoring'!R39=F4)),'Bid Monitoring'!E39,"") | E49: =IF(AND('Bid Monitoring'!B39<>"",IF(B4="All",TRUE(),'Bid Monitoring'!N39=B4),IF(C4="All",TRUE(),'Bid Monitoring'!L39=C4),IF(D4="All",TRUE(),'Bid Monitoring'!F39=D4),IF(E4="All",TRUE(),'Bid Monitoring'!E39=E4),IF(F4="All",TRUE(),'Bid Monitoring'!R39=F4)),'Bid Monitoring'!F39,"") | F49: =IF(AND('Bid Monitoring'!B39<>"",IF(B4="All",TRUE(),'Bid Monitoring'!N39=B4),IF(C4="All",TRUE(),'Bid Monitoring'!L39=C4),IF(D4="All",TRUE(),'Bid Monitoring'!F39=D4),IF(E4="All",TRUE(),'Bid Monitoring'!E39=E4),IF(F4="All",TRUE(),'Bid Monitoring'!R39=F4)),'Bid Monitoring'!H39,"") | G49: =IF(AND('Bid Monitoring'!B39<>"",IF(B4="All",TRUE(),'Bid Monitoring'!N39=B4),IF(C4="All",TRUE(),'Bid Monitoring'!L39=C4),IF(D4="All",TRUE(),'Bid Monitoring'!F39=D4),IF(E4="All",TRUE(),'Bid Monitoring'!E39=E4),IF(F4="All",TRUE(),'Bid Monitoring'!R39=F4)),'Bid Monitoring'!I39,"") | H49: =IF(AND('Bid Monitoring'!B39<>"",IF(B4="All",TRUE(),'Bid Monitoring'!N39=B4),IF(C4="All",TRUE(),'Bid Monitoring'!L39=C4),IF(D4="All",TRUE(),'Bid Monitoring'!F39=D4),IF(E4="All",TRUE(),'Bid Monitoring'!E39=E4),IF(F4="All",TRUE(),'Bid Monitoring'!R39=F4)),'Bid Monitoring'!K39,"") | I49: =IF(AND('Bid Monitoring'!B39<>"",IF(B4="All",TRUE(),'Bid Monitoring'!N39=B4),IF(C4="All",TRUE(),'Bid Monitoring'!L39=C4),IF(D4="All",TRUE(),'Bid Monitoring'!F39=D4),IF(E4="All",TRUE(),'Bid Monitoring'!E39=E4),IF(F4="All",TRUE(),'Bid Monitoring'!R39=F4)),'Bid Monitoring'!N39,"") | J49: =IF(AND('Bid Monitoring'!B39<>"",IF(B4="All",TRUE(),'Bid Monitoring'!N39=B4),IF(C4="All",TRUE(),'Bid Monitoring'!L39=C4),IF(D4="All",TRUE(),'Bid Monitoring'!F39=D4),IF(E4="All",TRUE(),'Bid Monitoring'!E39=E4),IF(F4="All",TRUE(),'Bid Monitoring'!R39=F4)),'Bid Monitoring'!L39,"")
A50: =IF(AND('Bid Monitoring'!B40<>"",IF(B4="All",TRUE(),'Bid Monitoring'!N40=B4),IF(C4="All",TRUE(),'Bid Monitoring'!L40=C4),IF(D4="All",TRUE(),'Bid Monitoring'!F40=D4),IF(E4="All",TRUE(),'Bid Monitoring'!E40=E4),IF(F4="All",TRUE(),'Bid Monitoring'!R40=F4)),'Bid Monitoring'!B40,"") | B50: =IF(AND('Bid Monitoring'!B40<>"",IF(B4="All",TRUE(),'Bid Monitoring'!N40=B4),IF(C4="All",TRUE(),'Bid Monitoring'!L40=C4),IF(D4="All",TRUE(),'Bid Monitoring'!F40=D4),IF(E4="All",TRUE(),'Bid Monitoring'!E40=E4),IF(F4="All",TRUE(),'Bid Monitoring'!R40=F4)),'Bid Monitoring'!D40,"") | C50: =IF(AND('Bid Monitoring'!B40<>"",IF(B4="All",TRUE(),'Bid Monitoring'!N40=B4),IF(C4="All",TRUE(),'Bid Monitoring'!L40=C4),IF(D4="All",TRUE(),'Bid Monitoring'!F40=D4),IF(E4="All",TRUE(),'Bid Monitoring'!E40=E4),IF(F4="All",TRUE(),'Bid Monitoring'!R40=F4)),'Bid Monitoring'!C40,"") | D50: =IF(AND('Bid Monitoring'!B40<>"",IF(B4="All",TRUE(),'Bid Monitoring'!N40=B4),IF(C4="All",TRUE(),'Bid Monitoring'!L40=C4),IF(D4="All",TRUE(),'Bid Monitoring'!F40=D4),IF(E4="All",TRUE(),'Bid Monitoring'!E40=E4),IF(F4="All",TRUE(),'Bid Monitoring'!R40=F4)),'Bid Monitoring'!E40,"") | E50: =IF(AND('Bid Monitoring'!B40<>"",IF(B4="All",TRUE(),'Bid Monitoring'!N40=B4),IF(C4="All",TRUE(),'Bid Monitoring'!L40=C4),IF(D4="All",TRUE(),'Bid Monitoring'!F40=D4),IF(E4="All",TRUE(),'Bid Monitoring'!E40=E4),IF(F4="All",TRUE(),'Bid Monitoring'!R40=F4)),'Bid Monitoring'!F40,"") | F50: =IF(AND('Bid Monitoring'!B40<>"",IF(B4="All",TRUE(),'Bid Monitoring'!N40=B4),IF(C4="All",TRUE(),'Bid Monitoring'!L40=C4),IF(D4="All",TRUE(),'Bid Monitoring'!F40=D4),IF(E4="All",TRUE(),'Bid Monitoring'!E40=E4),IF(F4="All",TRUE(),'Bid Monitoring'!R40=F4)),'Bid Monitoring'!H40,"") | G50: =IF(AND('Bid Monitoring'!B40<>"",IF(B4="All",TRUE(),'Bid Monitoring'!N40=B4),IF(C4="All",TRUE(),'Bid Monitoring'!L40=C4),IF(D4="All",TRUE(),'Bid Monitoring'!F40=D4),IF(E4="All",TRUE(),'Bid Monitoring'!E40=E4),IF(F4="All",TRUE(),'Bid Monitoring'!R40=F4)),'Bid Monitoring'!I40,"") | H50: =IF(AND('Bid Monitoring'!B40<>"",IF(B4="All",TRUE(),'Bid Monitoring'!N40=B4),IF(C4="All",TRUE(),'Bid Monitoring'!L40=C4),IF(D4="All",TRUE(),'Bid Monitoring'!F40=D4),IF(E4="All",TRUE(),'Bid Monitoring'!E40=E4),IF(F4="All",TRUE(),'Bid Monitoring'!R40=F4)),'Bid Monitoring'!K40,"") | I50: =IF(AND('Bid Monitoring'!B40<>"",IF(B4="All",TRUE(),'Bid Monitoring'!N40=B4),IF(C4="All",TRUE(),'Bid Monitoring'!L40=C4),IF(D4="All",TRUE(),'Bid Monitoring'!F40=D4),IF(E4="All",TRUE(),'Bid Monitoring'!E40=E4),IF(F4="All",TRUE(),'Bid Monitoring'!R40=F4)),'Bid Monitoring'!N40,"") | J50: =IF(AND('Bid Monitoring'!B40<>"",IF(B4="All",TRUE(),'Bid Monitoring'!N40=B4),IF(C4="All",TRUE(),'Bid Monitoring'!L40=C4),IF(D4="All",TRUE(),'Bid Monitoring'!F40=D4),IF(E4="All",TRUE(),'Bid Monitoring'!E40=E4),IF(F4="All",TRUE(),'Bid Monitoring'!R40=F4)),'Bid Monitoring'!L40,"")
A51: =IF(AND('Bid Monitoring'!B41<>"",IF(B4="All",TRUE(),'Bid Monitoring'!N41=B4),IF(C4="All",TRUE(),'Bid Monitoring'!L41=C4),IF(D4="All",TRUE(),'Bid Monitoring'!F41=D4),IF(E4="All",TRUE(),'Bid Monitoring'!E41=E4),IF(F4="All",TRUE(),'Bid Monitoring'!R41=F4)),'Bid Monitoring'!B41,"") | B51: =IF(AND('Bid Monitoring'!B41<>"",IF(B4="All",TRUE(),'Bid Monitoring'!N41=B4),IF(C4="All",TRUE(),'Bid Monitoring'!L41=C4),IF(D4="All",TRUE(),'Bid Monitoring'!F41=D4),IF(E4="All",TRUE(),'Bid Monitoring'!E41=E4),IF(F4="All",TRUE(),'Bid Monitoring'!R41=F4)),'Bid Monitoring'!D41,"") | C51: =IF(AND('Bid Monitoring'!B41<>"",IF(B4="All",TRUE(),'Bid Monitoring'!N41=B4),IF(C4="All",TRUE(),'Bid Monitoring'!L41=C4),IF(D4="All",TRUE(),'Bid Monitoring'!F41=D4),IF(E4="All",TRUE(),'Bid Monitoring'!E41=E4),IF(F4="All",TRUE(),'Bid Monitoring'!R41=F4)),'Bid Monitoring'!C41,"") | D51: =IF(AND('Bid Monitoring'!B41<>"",IF(B4="All",TRUE(),'Bid Monitoring'!N41=B4),IF(C4="All",TRUE(),'Bid Monitoring'!L41=C4),IF(D4="All",TRUE(),'Bid Monitoring'!F41=D4),IF(E4="All",TRUE(),'Bid Monitoring'!E41=E4),IF(F4="All",TRUE(),'Bid Monitoring'!R41=F4)),'Bid Monitoring'!E41,"") | E51: =IF(AND('Bid Monitoring'!B41<>"",IF(B4="All",TRUE(),'Bid Monitoring'!N41=B4),IF(C4="All",TRUE(),'Bid Monitoring'!L41=C4),IF(D4="All",TRUE(),'Bid Monitoring'!F41=D4),IF(E4="All",TRUE(),'Bid Monitoring'!E41=E4),IF(F4="All",TRUE(),'Bid Monitoring'!R41=F4)),'Bid Monitoring'!F41,"") | F51: =IF(AND('Bid Monitoring'!B41<>"",IF(B4="All",TRUE(),'Bid Monitoring'!N41=B4),IF(C4="All",TRUE(),'Bid Monitoring'!L41=C4),IF(D4="All",TRUE(),'Bid Monitoring'!F41=D4),IF(E4="All",TRUE(),'Bid Monitoring'!E41=E4),IF(F4="All",TRUE(),'Bid Monitoring'!R41=F4)),'Bid Monitoring'!H41,"") | G51: =IF(AND('Bid Monitoring'!B41<>"",IF(B4="All",TRUE(),'Bid Monitoring'!N41=B4),IF(C4="All",TRUE(),'Bid Monitoring'!L41=C4),IF(D4="All",TRUE(),'Bid Monitoring'!F41=D4),IF(E4="All",TRUE(),'Bid Monitoring'!E41=E4),IF(F4="All",TRUE(),'Bid Monitoring'!R41=F4)),'Bid Monitoring'!I41,"") | H51: =IF(AND('Bid Monitoring'!B41<>"",IF(B4="All",TRUE(),'Bid Monitoring'!N41=B4),IF(C4="All",TRUE(),'Bid Monitoring'!L41=C4),IF(D4="All",TRUE(),'Bid Monitoring'!F41=D4),IF(E4="All",TRUE(),'Bid Monitoring'!E41=E4),IF(F4="All",TRUE(),'Bid Monitoring'!R41=F4)),'Bid Monitoring'!K41,"") | I51: =IF(AND('Bid Monitoring'!B41<>"",IF(B4="All",TRUE(),'Bid Monitoring'!N41=B4),IF(C4="All",TRUE(),'Bid Monitoring'!L41=C4),IF(D4="All",TRUE(),'Bid Monitoring'!F41=D4),IF(E4="All",TRUE(),'Bid Monitoring'!E41=E4),IF(F4="All",TRUE(),'Bid Monitoring'!R41=F4)),'Bid Monitoring'!N41,"") | J51: =IF(AND('Bid Monitoring'!B41<>"",IF(B4="All",TRUE(),'Bid Monitoring'!N41=B4),IF(C4="All",TRUE(),'Bid Monitoring'!L41=C4),IF(D4="All",TRUE(),'Bid Monitoring'!F41=D4),IF(E4="All",TRUE(),'Bid Monitoring'!E41=E4),IF(F4="All",TRUE(),'Bid Monitoring'!R41=F4)),'Bid Monitoring'!L41,"")
A52: =IF(AND('Bid Monitoring'!B42<>"",IF(B4="All",TRUE(),'Bid Monitoring'!N42=B4),IF(C4="All",TRUE(),'Bid Monitoring'!L42=C4),IF(D4="All",TRUE(),'Bid Monitoring'!F42=D4),IF(E4="All",TRUE(),'Bid Monitoring'!E42=E4),IF(F4="All",TRUE(),'Bid Monitoring'!R42=F4)),'Bid Monitoring'!B42,"") | B52: =IF(AND('Bid Monitoring'!B42<>"",IF(B4="All",TRUE(),'Bid Monitoring'!N42=B4),IF(C4="All",TRUE(),'Bid Monitoring'!L42=C4),IF(D4="All",TRUE(),'Bid Monitoring'!F42=D4),IF(E4="All",TRUE(),'Bid Monitoring'!E42=E4),IF(F4="All",TRUE(),'Bid Monitoring'!R42=F4)),'Bid Monitoring'!D42,"") | C52: =IF(AND('Bid Monitoring'!B42<>"",IF(B4="All",TRUE(),'Bid Monitoring'!N42=B4),IF(C4="All",TRUE(),'Bid Monitoring'!L42=C4),IF(D4="All",TRUE(),'Bid Monitoring'!F42=D4),IF(E4="All",TRUE(),'Bid Monitoring'!E42=E4),IF(F4="All",TRUE(),'Bid Monitoring'!R42=F4)),'Bid Monitoring'!C42,"") | D52: =IF(AND('Bid Monitoring'!B42<>"",IF(B4="All",TRUE(),'Bid Monitoring'!N42=B4),IF(C4="All",TRUE(),'Bid Monitoring'!L42=C4),IF(D4="All",TRUE(),'Bid Monitoring'!F42=D4),IF(E4="All",TRUE(),'Bid Monitoring'!E42=E4),IF(F4="All",TRUE(),'Bid Monitoring'!R42=F4)),'Bid Monitoring'!E42,"") | E52: =IF(AND('Bid Monitoring'!B42<>"",IF(B4="All",TRUE(),'Bid Monitoring'!N42=B4),IF(C4="All",TRUE(),'Bid Monitoring'!L42=C4),IF(D4="All",TRUE(),'Bid Monitoring'!F42=D4),IF(E4="All",TRUE(),'Bid Monitoring'!E42=E4),IF(F4="All",TRUE(),'Bid Monitoring'!R42=F4)),'Bid Monitoring'!F42,"") | F52: =IF(AND('Bid Monitoring'!B42<>"",IF(B4="All",TRUE(),'Bid Monitoring'!N42=B4),IF(C4="All",TRUE(),'Bid Monitoring'!L42=C4),IF(D4="All",TRUE(),'Bid Monitoring'!F42=D4),IF(E4="All",TRUE(),'Bid Monitoring'!E42=E4),IF(F4="All",TRUE(),'Bid Monitoring'!R42=F4)),'Bid Monitoring'!H42,"") | G52: =IF(AND('Bid Monitoring'!B42<>"",IF(B4="All",TRUE(),'Bid Monitoring'!N42=B4),IF(C4="All",TRUE(),'Bid Monitoring'!L42=C4),IF(D4="All",TRUE(),'Bid Monitoring'!F42=D4),IF(E4="All",TRUE(),'Bid Monitoring'!E42=E4),IF(F4="All",TRUE(),'Bid Monitoring'!R42=F4)),'Bid Monitoring'!I42,"") | H52: =IF(AND('Bid Monitoring'!B42<>"",IF(B4="All",TRUE(),'Bid Monitoring'!N42=B4),IF(C4="All",TRUE(),'Bid Monitoring'!L42=C4),IF(D4="All",TRUE(),'Bid Monitoring'!F42=D4),IF(E4="All",TRUE(),'Bid Monitoring'!E42=E4),IF(F4="All",TRUE(),'Bid Monitoring'!R42=F4)),'Bid Monitoring'!K42,"") | I52: =IF(AND('Bid Monitoring'!B42<>"",IF(B4="All",TRUE(),'Bid Monitoring'!N42=B4),IF(C4="All",TRUE(),'Bid Monitoring'!L42=C4),IF(D4="All",TRUE(),'Bid Monitoring'!F42=D4),IF(E4="All",TRUE(),'Bid Monitoring'!E42=E4),IF(F4="All",TRUE(),'Bid Monitoring'!R42=F4)),'Bid Monitoring'!N42,"") | J52: =IF(AND('Bid Monitoring'!B42<>"",IF(B4="All",TRUE(),'Bid Monitoring'!N42=B4),IF(C4="All",TRUE(),'Bid Monitoring'!L42=C4),IF(D4="All",TRUE(),'Bid Monitoring'!F42=D4),IF(E4="All",TRUE(),'Bid Monitoring'!E42=E4),IF(F4="All",TRUE(),'Bid Monitoring'!R42=F4)),'Bid Monitoring'!L42,"")
A53: =IF(AND('Bid Monitoring'!B43<>"",IF(B4="All",TRUE(),'Bid Monitoring'!N43=B4),IF(C4="All",TRUE(),'Bid Monitoring'!L43=C4),IF(D4="All",TRUE(),'Bid Monitoring'!F43=D4),IF(E4="All",TRUE(),'Bid Monitoring'!E43=E4),IF(F4="All",TRUE(),'Bid Monitoring'!R43=F4)),'Bid Monitoring'!B43,"") | B53: =IF(AND('Bid Monitoring'!B43<>"",IF(B4="All",TRUE(),'Bid Monitoring'!N43=B4),IF(C4="All",TRUE(),'Bid Monitoring'!L43=C4),IF(D4="All",TRUE(),'Bid Monitoring'!F43=D4),IF(E4="All",TRUE(),'Bid Monitoring'!E43=E4),IF(F4="All",TRUE(),'Bid Monitoring'!R43=F4)),'Bid Monitoring'!D43,"") | C53: =IF(AND('Bid Monitoring'!B43<>"",IF(B4="All",TRUE(),'Bid Monitoring'!N43=B4),IF(C4="All",TRUE(),'Bid Monitoring'!L43=C4),IF(D4="All",TRUE(),'Bid Monitoring'!F43=D4),IF(E4="All",TRUE(),'Bid Monitoring'!E43=E4),IF(F4="All",TRUE(),'Bid Monitoring'!R43=F4)),'Bid Monitoring'!C43,"") | D53: =IF(AND('Bid Monitoring'!B43<>"",IF(B4="All",TRUE(),'Bid Monitoring'!N43=B4),IF(C4="All",TRUE(),'Bid Monitoring'!L43=C4),IF(D4="All",TRUE(),'Bid Monitoring'!F43=D4),IF(E4="All",TRUE(),'Bid Monitoring'!E43=E4),IF(F4="All",TRUE(),'Bid Monitoring'!R43=F4)),'Bid Monitoring'!E43,"") | E53: =IF(AND('Bid Monitoring'!B43<>"",IF(B4="All",TRUE(),'Bid Monitoring'!N43=B4),IF(C4="All",TRUE(),'Bid Monitoring'!L43=C4),IF(D4="All",TRUE(),'Bid Monitoring'!F43=D4),IF(E4="All",TRUE(),'Bid Monitoring'!E43=E4),IF(F4="All",TRUE(),'Bid Monitoring'!R43=F4)),'Bid Monitoring'!F43,"") | F53: =IF(AND('Bid Monitoring'!B43<>"",IF(B4="All",TRUE(),'Bid Monitoring'!N43=B4),IF(C4="All",TRUE(),'Bid Monitoring'!L43=C4),IF(D4="All",TRUE(),'Bid Monitoring'!F43=D4),IF(E4="All",TRUE(),'Bid Monitoring'!E43=E4),IF(F4="All",TRUE(),'Bid Monitoring'!R43=F4)),'Bid Monitoring'!H43,"") | G53: =IF(AND('Bid Monitoring'!B43<>"",IF(B4="All",TRUE(),'Bid Monitoring'!N43=B4),IF(C4="All",TRUE(),'Bid Monitoring'!L43=C4),IF(D4="All",TRUE(),'Bid Monitoring'!F43=D4),IF(E4="All",TRUE(),'Bid Monitoring'!E43=E4),IF(F4="All",TRUE(),'Bid Monitoring'!R43=F4)),'Bid Monitoring'!I43,"") | H53: =IF(AND('Bid Monitoring'!B43<>"",IF(B4="All",TRUE(),'Bid Monitoring'!N43=B4),IF(C4="All",TRUE(),'Bid Monitoring'!L43=C4),IF(D4="All",TRUE(),'Bid Monitoring'!F43=D4),IF(E4="All",TRUE(),'Bid Monitoring'!E43=E4),IF(F4="All",TRUE(),'Bid Monitoring'!R43=F4)),'Bid Monitoring'!K43,"") | I53: =IF(AND('Bid Monitoring'!B43<>"",IF(B4="All",TRUE(),'Bid Monitoring'!N43=B4),IF(C4="All",TRUE(),'Bid Monitoring'!L43=C4),IF(D4="All",TRUE(),'Bid Monitoring'!F43=D4),IF(E4="All",TRUE(),'Bid Monitoring'!E43=E4),IF(F4="All",TRUE(),'Bid Monitoring'!R43=F4)),'Bid Monitoring'!N43,"") | J53: =IF(AND('Bid Monitoring'!B43<>"",IF(B4="All",TRUE(),'Bid Monitoring'!N43=B4),IF(C4="All",TRUE(),'Bid Monitoring'!L43=C4),IF(D4="All",TRUE(),'Bid Monitoring'!F43=D4),IF(E4="All",TRUE(),'Bid Monitoring'!E43=E4),IF(F4="All",TRUE(),'Bid Monitoring'!R43=F4)),'Bid Monitoring'!L43,"")
A54: =IF(AND('Bid Monitoring'!B44<>"",IF(B4="All",TRUE(),'Bid Monitoring'!N44=B4),IF(C4="All",TRUE(),'Bid Monitoring'!L44=C4),IF(D4="All",TRUE(),'Bid Monitoring'!F44=D4),IF(E4="All",TRUE(),'Bid Monitoring'!E44=E4),IF(F4="All",TRUE(),'Bid Monitoring'!R44=F4)),'Bid Monitoring'!B44,"") | B54: =IF(AND('Bid Monitoring'!B44<>"",IF(B4="All",TRUE(),'Bid Monitoring'!N44=B4),IF(C4="All",TRUE(),'Bid Monitoring'!L44=C4),IF(D4="All",TRUE(),'Bid Monitoring'!F44=D4),IF(E4="All",TRUE(),'Bid Monitoring'!E44=E4),IF(F4="All",TRUE(),'Bid Monitoring'!R44=F4)),'Bid Monitoring'!D44,"") | C54: =IF(AND('Bid Monitoring'!B44<>"",IF(B4="All",TRUE(),'Bid Monitoring'!N44=B4),IF(C4="All",TRUE(),'Bid Monitoring'!L44=C4),IF(D4="All",TRUE(),'Bid Monitoring'!F44=D4),IF(E4="All",TRUE(),'Bid Monitoring'!E44=E4),IF(F4="All",TRUE(),'Bid Monitoring'!R44=F4)),'Bid Monitoring'!C44,"") | D54: =IF(AND('Bid Monitoring'!B44<>"",IF(B4="All",TRUE(),'Bid Monitoring'!N44=B4),IF(C4="All",TRUE(),'Bid Monitoring'!L44=C4),IF(D4="All",TRUE(),'Bid Monitoring'!F44=D4),IF(E4="All",TRUE(),'Bid Monitoring'!E44=E4),IF(F4="All",TRUE(),'Bid Monitoring'!R44=F4)),'Bid Monitoring'!E44,"") | E54: =IF(AND('Bid Monitoring'!B44<>"",IF(B4="All",TRUE(),'Bid Monitoring'!N44=B4),IF(C4="All",TRUE(),'Bid Monitoring'!L44=C4),IF(D4="All",TRUE(),'Bid Monitoring'!F44=D4),IF(E4="All",TRUE(),'Bid Monitoring'!E44=E4),IF(F4="All",TRUE(),'Bid Monitoring'!R44=F4)),'Bid Monitoring'!F44,"") | F54: =IF(AND('Bid Monitoring'!B44<>"",IF(B4="All",TRUE(),'Bid Monitoring'!N44=B4),IF(C4="All",TRUE(),'Bid Monitoring'!L44=C4),IF(D4="All",TRUE(),'Bid Monitoring'!F44=D4),IF(E4="All",TRUE(),'Bid Monitoring'!E44=E4),IF(F4="All",TRUE(),'Bid Monitoring'!R44=F4)),'Bid Monitoring'!H44,"") | G54: =IF(AND('Bid Monitoring'!B44<>"",IF(B4="All",TRUE(),'Bid Monitoring'!N44=B4),IF(C4="All",TRUE(),'Bid Monitoring'!L44=C4),IF(D4="All",TRUE(),'Bid Monitoring'!F44=D4),IF(E4="All",TRUE(),'Bid Monitoring'!E44=E4),IF(F4="All",TRUE(),'Bid Monitoring'!R44=F4)),'Bid Monitoring'!I44,"") | H54: =IF(AND('Bid Monitoring'!B44<>"",IF(B4="All",TRUE(),'Bid Monitoring'!N44=B4),IF(C4="All",TRUE(),'Bid Monitoring'!L44=C4),IF(D4="All",TRUE(),'Bid Monitoring'!F44=D4),IF(E4="All",TRUE(),'Bid Monitoring'!E44=E4),IF(F4="All",TRUE(),'Bid Monitoring'!R44=F4)),'Bid Monitoring'!K44,"") | I54: =IF(AND('Bid Monitoring'!B44<>"",IF(B4="All",TRUE(),'Bid Monitoring'!N44=B4),IF(C4="All",TRUE(),'Bid Monitoring'!L44=C4),IF(D4="All",TRUE(),'Bid Monitoring'!F44=D4),IF(E4="All",TRUE(),'Bid Monitoring'!E44=E4),IF(F4="All",TRUE(),'Bid Monitoring'!R44=F4)),'Bid Monitoring'!N44,"") | J54: =IF(AND('Bid Monitoring'!B44<>"",IF(B4="All",TRUE(),'Bid Monitoring'!N44=B4),IF(C4="All",TRUE(),'Bid Monitoring'!L44=C4),IF(D4="All",TRUE(),'Bid Monitoring'!F44=D4),IF(E4="All",TRUE(),'Bid Monitoring'!E44=E4),IF(F4="All",TRUE(),'Bid Monitoring'!R44=F4)),'Bid Monitoring'!L44,"")
A55: =IF(AND('Bid Monitoring'!B45<>"",IF(B4="All",TRUE(),'Bid Monitoring'!N45=B4),IF(C4="All",TRUE(),'Bid Monitoring'!L45=C4),IF(D4="All",TRUE(),'Bid Monitoring'!F45=D4),IF(E4="All",TRUE(),'Bid Monitoring'!E45=E4),IF(F4="All",TRUE(),'Bid Monitoring'!R45=F4)),'Bid Monitoring'!B45,"") | B55: =IF(AND('Bid Monitoring'!B45<>"",IF(B4="All",TRUE(),'Bid Monitoring'!N45=B4),IF(C4="All",TRUE(),'Bid Monitoring'!L45=C4),IF(D4="All",TRUE(),'Bid Monitoring'!F45=D4),IF(E4="All",TRUE(),'Bid Monitoring'!E45=E4),IF(F4="All",TRUE(),'Bid Monitoring'!R45=F4)),'Bid Monitoring'!D45,"") | C55: =IF(AND('Bid Monitoring'!B45<>"",IF(B4="All",TRUE(),'Bid Monitoring'!N45=B4),IF(C4="All",TRUE(),'Bid Monitoring'!L45=C4),IF(D4="All",TRUE(),'Bid Monitoring'!F45=D4),IF(E4="All",TRUE(),'Bid Monitoring'!E45=E4),IF(F4="All",TRUE(),'Bid Monitoring'!R45=F4)),'Bid Monitoring'!C45,"") | D55: =IF(AND('Bid Monitoring'!B45<>"",IF(B4="All",TRUE(),'Bid Monitoring'!N45=B4),IF(C4="All",TRUE(),'Bid Monitoring'!L45=C4),IF(D4="All",TRUE(),'Bid Monitoring'!F45=D4),IF(E4="All",TRUE(),'Bid Monitoring'!E45=E4),IF(F4="All",TRUE(),'Bid Monitoring'!R45=F4)),'Bid Monitoring'!E45,"") | E55: =IF(AND('Bid Monitoring'!B45<>"",IF(B4="All",TRUE(),'Bid Monitoring'!N45=B4),IF(C4="All",TRUE(),'Bid Monitoring'!L45=C4),IF(D4="All",TRUE(),'Bid Monitoring'!F45=D4),IF(E4="All",TRUE(),'Bid Monitoring'!E45=E4),IF(F4="All",TRUE(),'Bid Monitoring'!R45=F4)),'Bid Monitoring'!F45,"") | F55: =IF(AND('Bid Monitoring'!B45<>"",IF(B4="All",TRUE(),'Bid Monitoring'!N45=B4),IF(C4="All",TRUE(),'Bid Monitoring'!L45=C4),IF(D4="All",TRUE(),'Bid Monitoring'!F45=D4),IF(E4="All",TRUE(),'Bid Monitoring'!E45=E4),IF(F4="All",TRUE(),'Bid Monitoring'!R45=F4)),'Bid Monitoring'!H45,"") | G55: =IF(AND('Bid Monitoring'!B45<>"",IF(B4="All",TRUE(),'Bid Monitoring'!N45=B4),IF(C4="All",TRUE(),'Bid Monitoring'!L45=C4),IF(D4="All",TRUE(),'Bid Monitoring'!F45=D4),IF(E4="All",TRUE(),'Bid Monitoring'!E45=E4),IF(F4="All",TRUE(),'Bid Monitoring'!R45=F4)),'Bid Monitoring'!I45,"") | H55: =IF(AND('Bid Monitoring'!B45<>"",IF(B4="All",TRUE(),'Bid Monitoring'!N45=B4),IF(C4="All",TRUE(),'Bid Monitoring'!L45=C4),IF(D4="All",TRUE(),'Bid Monitoring'!F45=D4),IF(E4="All",TRUE(),'Bid Monitoring'!E45=E4),IF(F4="All",TRUE(),'Bid Monitoring'!R45=F4)),'Bid Monitoring'!K45,"") | I55: =IF(AND('Bid Monitoring'!B45<>"",IF(B4="All",TRUE(),'Bid Monitoring'!N45=B4),IF(C4="All",TRUE(),'Bid Monitoring'!L45=C4),IF(D4="All",TRUE(),'Bid Monitoring'!F45=D4),IF(E4="All",TRUE(),'Bid Monitoring'!E45=E4),IF(F4="All",TRUE(),'Bid Monitoring'!R45=F4)),'Bid Monitoring'!N45,"") | J55: =IF(AND('Bid Monitoring'!B45<>"",IF(B4="All",TRUE(),'Bid Monitoring'!N45=B4),IF(C4="All",TRUE(),'Bid Monitoring'!L45=C4),IF(D4="All",TRUE(),'Bid Monitoring'!F45=D4),IF(E4="All",TRUE(),'Bid Monitoring'!E45=E4),IF(F4="All",TRUE(),'Bid Monitoring'!R45=F4)),'Bid Monitoring'!L45,"")
A56: =IF(AND('Bid Monitoring'!B46<>"",IF(B4="All",TRUE(),'Bid Monitoring'!N46=B4),IF(C4="All",TRUE(),'Bid Monitoring'!L46=C4),IF(D4="All",TRUE(),'Bid Monitoring'!F46=D4),IF(E4="All",TRUE(),'Bid Monitoring'!E46=E4),IF(F4="All",TRUE(),'Bid Monitoring'!R46=F4)),'Bid Monitoring'!B46,"") | B56: =IF(AND('Bid Monitoring'!B46<>"",IF(B4="All",TRUE(),'Bid Monitoring'!N46=B4),IF(C4="All",TRUE(),'Bid Monitoring'!L46=C4),IF(D4="All",TRUE(),'Bid Monitoring'!F46=D4),IF(E4="All",TRUE(),'Bid Monitoring'!E46=E4),IF(F4="All",TRUE(),'Bid Monitoring'!R46=F4)),'Bid Monitoring'!D46,"") | C56: =IF(AND('Bid Monitoring'!B46<>"",IF(B4="All",TRUE(),'Bid Monitoring'!N46=B4),IF(C4="All",TRUE(),'Bid Monitoring'!L46=C4),IF(D4="All",TRUE(),'Bid Monitoring'!F46=D4),IF(E4="All",TRUE(),'Bid Monitoring'!E46=E4),IF(F4="All",TRUE(),'Bid Monitoring'!R46=F4)),'Bid Monitoring'!C46,"") | D56: =IF(AND('Bid Monitoring'!B46<>"",IF(B4="All",TRUE(),'Bid Monitoring'!N46=B4),IF(C4="All",TRUE(),'Bid Monitoring'!L46=C4),IF(D4="All",TRUE(),'Bid Monitoring'!F46=D4),IF(E4="All",TRUE(),'Bid Monitoring'!E46=E4),IF(F4="All",TRUE(),'Bid Monitoring'!R46=F4)),'Bid Monitoring'!E46,"") | E56: =IF(AND('Bid Monitoring'!B46<>"",IF(B4="All",TRUE(),'Bid Monitoring'!N46=B4),IF(C4="All",TRUE(),'Bid Monitoring'!L46=C4),IF(D4="All",TRUE(),'Bid Monitoring'!F46=D4),IF(E4="All",TRUE(),'Bid Monitoring'!E46=E4),IF(F4="All",TRUE(),'Bid Monitoring'!R46=F4)),'Bid Monitoring'!F46,"") | F56: =IF(AND('Bid Monitoring'!B46<>"",IF(B4="All",TRUE(),'Bid Monitoring'!N46=B4),IF(C4="All",TRUE(),'Bid Monitoring'!L46=C4),IF(D4="All",TRUE(),'Bid Monitoring'!F46=D4),IF(E4="All",TRUE(),'Bid Monitoring'!E46=E4),IF(F4="All",TRUE(),'Bid Monitoring'!R46=F4)),'Bid Monitoring'!H46,"") | G56: =IF(AND('Bid Monitoring'!B46<>"",IF(B4="All",TRUE(),'Bid Monitoring'!N46=B4),IF(C4="All",TRUE(),'Bid Monitoring'!L46=C4),IF(D4="All",TRUE(),'Bid Monitoring'!F46=D4),IF(E4="All",TRUE(),'Bid Monitoring'!E46=E4),IF(F4="All",TRUE(),'Bid Monitoring'!R46=F4)),'Bid Monitoring'!I46,"") | H56: =IF(AND('Bid Monitoring'!B46<>"",IF(B4="All",TRUE(),'Bid Monitoring'!N46=B4),IF(C4="All",TRUE(),'Bid Monitoring'!L46=C4),IF(D4="All",TRUE(),'Bid Monitoring'!F46=D4),IF(E4="All",TRUE(),'Bid Monitoring'!E46=E4),IF(F4="All",TRUE(),'Bid Monitoring'!R46=F4)),'Bid Monitoring'!K46,"") | I56: =IF(AND('Bid Monitoring'!B46<>"",IF(B4="All",TRUE(),'Bid Monitoring'!N46=B4),IF(C4="All",TRUE(),'Bid Monitoring'!L46=C4),IF(D4="All",TRUE(),'Bid Monitoring'!F46=D4),IF(E4="All",TRUE(),'Bid Monitoring'!E46=E4),IF(F4="All",TRUE(),'Bid Monitoring'!R46=F4)),'Bid Monitoring'!N46,"") | J56: =IF(AND('Bid Monitoring'!B46<>"",IF(B4="All",TRUE(),'Bid Monitoring'!N46=B4),IF(C4="All",TRUE(),'Bid Monitoring'!L46=C4),IF(D4="All",TRUE(),'Bid Monitoring'!F46=D4),IF(E4="All",TRUE(),'Bid Monitoring'!E46=E4),IF(F4="All",TRUE(),'Bid Monitoring'!R46=F4)),'Bid Monitoring'!L46,"")
A57: =IF(AND('Bid Monitoring'!B47<>"",IF(B4="All",TRUE(),'Bid Monitoring'!N47=B4),IF(C4="All",TRUE(),'Bid Monitoring'!L47=C4),IF(D4="All",TRUE(),'Bid Monitoring'!F47=D4),IF(E4="All",TRUE(),'Bid Monitoring'!E47=E4),IF(F4="All",TRUE(),'Bid Monitoring'!R47=F4)),'Bid Monitoring'!B47,"") | B57: =IF(AND('Bid Monitoring'!B47<>"",IF(B4="All",TRUE(),'Bid Monitoring'!N47=B4),IF(C4="All",TRUE(),'Bid Monitoring'!L47=C4),IF(D4="All",TRUE(),'Bid Monitoring'!F47=D4),IF(E4="All",TRUE(),'Bid Monitoring'!E47=E4),IF(F4="All",TRUE(),'Bid Monitoring'!R47=F4)),'Bid Monitoring'!D47,"") | C57: =IF(AND('Bid Monitoring'!B47<>"",IF(B4="All",TRUE(),'Bid Monitoring'!N47=B4),IF(C4="All",TRUE(),'Bid Monitoring'!L47=C4),IF(D4="All",TRUE(),'Bid Monitoring'!F47=D4),IF(E4="All",TRUE(),'Bid Monitoring'!E47=E4),IF(F4="All",TRUE(),'Bid Monitoring'!R47=F4)),'Bid Monitoring'!C47,"") | D57: =IF(AND('Bid Monitoring'!B47<>"",IF(B4="All",TRUE(),'Bid Monitoring'!N47=B4),IF(C4="All",TRUE(),'Bid Monitoring'!L47=C4),IF(D4="All",TRUE(),'Bid Monitoring'!F47=D4),IF(E4="All",TRUE(),'Bid Monitoring'!E47=E4),IF(F4="All",TRUE(),'Bid Monitoring'!R47=F4)),'Bid Monitoring'!E47,"") | E57: =IF(AND('Bid Monitoring'!B47<>"",IF(B4="All",TRUE(),'Bid Monitoring'!N47=B4),IF(C4="All",TRUE(),'Bid Monitoring'!L47=C4),IF(D4="All",TRUE(),'Bid Monitoring'!F47=D4),IF(E4="All",TRUE(),'Bid Monitoring'!E47=E4),IF(F4="All",TRUE(),'Bid Monitoring'!R47=F4)),'Bid Monitoring'!F47,"") | F57: =IF(AND('Bid Monitoring'!B47<>"",IF(B4="All",TRUE(),'Bid Monitoring'!N47=B4),IF(C4="All",TRUE(),'Bid Monitoring'!L47=C4),IF(D4="All",TRUE(),'Bid Monitoring'!F47=D4),IF(E4="All",TRUE(),'Bid Monitoring'!E47=E4),IF(F4="All",TRUE(),'Bid Monitoring'!R47=F4)),'Bid Monitoring'!H47,"") | G57: =IF(AND('Bid Monitoring'!B47<>"",IF(B4="All",TRUE(),'Bid Monitoring'!N47=B4),IF(C4="All",TRUE(),'Bid Monitoring'!L47=C4),IF(D4="All",TRUE(),'Bid Monitoring'!F47=D4),IF(E4="All",TRUE(),'Bid Monitoring'!E47=E4),IF(F4="All",TRUE(),'Bid Monitoring'!R47=F4)),'Bid Monitoring'!I47,"") | H57: =IF(AND('Bid Monitoring'!B47<>"",IF(B4="All",TRUE(),'Bid Monitoring'!N47=B4),IF(C4="All",TRUE(),'Bid Monitoring'!L47=C4),IF(D4="All",TRUE(),'Bid Monitoring'!F47=D4),IF(E4="All",TRUE(),'Bid Monitoring'!E47=E4),IF(F4="All",TRUE(),'Bid Monitoring'!R47=F4)),'Bid Monitoring'!K47,"") | I57: =IF(AND('Bid Monitoring'!B47<>"",IF(B4="All",TRUE(),'Bid Monitoring'!N47=B4),IF(C4="All",TRUE(),'Bid Monitoring'!L47=C4),IF(D4="All",TRUE(),'Bid Monitoring'!F47=D4),IF(E4="All",TRUE(),'Bid Monitoring'!E47=E4),IF(F4="All",TRUE(),'Bid Monitoring'!R47=F4)),'Bid Monitoring'!N47,"") | J57: =IF(AND('Bid Monitoring'!B47<>"",IF(B4="All",TRUE(),'Bid Monitoring'!N47=B4),IF(C4="All",TRUE(),'Bid Monitoring'!L47=C4),IF(D4="All",TRUE(),'Bid Monitoring'!F47=D4),IF(E4="All",TRUE(),'Bid Monitoring'!E47=E4),IF(F4="All",TRUE(),'Bid Monitoring'!R47=F4)),'Bid Monitoring'!L47,"")
A58: =IF(AND('Bid Monitoring'!B48<>"",IF(B4="All",TRUE(),'Bid Monitoring'!N48=B4),IF(C4="All",TRUE(),'Bid Monitoring'!L48=C4),IF(D4="All",TRUE(),'Bid Monitoring'!F48=D4),IF(E4="All",TRUE(),'Bid Monitoring'!E48=E4),IF(F4="All",TRUE(),'Bid Monitoring'!R48=F4)),'Bid Monitoring'!B48,"") | B58: =IF(AND('Bid Monitoring'!B48<>"",IF(B4="All",TRUE(),'Bid Monitoring'!N48=B4),IF(C4="All",TRUE(),'Bid Monitoring'!L48=C4),IF(D4="All",TRUE(),'Bid Monitoring'!F48=D4),IF(E4="All",TRUE(),'Bid Monitoring'!E48=E4),IF(F4="All",TRUE(),'Bid Monitoring'!R48=F4)),'Bid Monitoring'!D48,"") | C58: =IF(AND('Bid Monitoring'!B48<>"",IF(B4="All",TRUE(),'Bid Monitoring'!N48=B4),IF(C4="All",TRUE(),'Bid Monitoring'!L48=C4),IF(D4="All",TRUE(),'Bid Monitoring'!F48=D4),IF(E4="All",TRUE(),'Bid Monitoring'!E48=E4),IF(F4="All",TRUE(),'Bid Monitoring'!R48=F4)),'Bid Monitoring'!C48,"") | D58: =IF(AND('Bid Monitoring'!B48<>"",IF(B4="All",TRUE(),'Bid Monitoring'!N48=B4),IF(C4="All",TRUE(),'Bid Monitoring'!L48=C4),IF(D4="All",TRUE(),'Bid Monitoring'!F48=D4),IF(E4="All",TRUE(),'Bid Monitoring'!E48=E4),IF(F4="All",TRUE(),'Bid Monitoring'!R48=F4)),'Bid Monitoring'!E48,"") | E58: =IF(AND('Bid Monitoring'!B48<>"",IF(B4="All",TRUE(),'Bid Monitoring'!N48=B4),IF(C4="All",TRUE(),'Bid Monitoring'!L48=C4),IF(D4="All",TRUE(),'Bid Monitoring'!F48=D4),IF(E4="All",TRUE(),'Bid Monitoring'!E48=E4),IF(F4="All",TRUE(),'Bid Monitoring'!R48=F4)),'Bid Monitoring'!F48,"") | F58: =IF(AND('Bid Monitoring'!B48<>"",IF(B4="All",TRUE(),'Bid Monitoring'!N48=B4),IF(C4="All",TRUE(),'Bid Monitoring'!L48=C4),IF(D4="All",TRUE(),'Bid Monitoring'!F48=D4),IF(E4="All",TRUE(),'Bid Monitoring'!E48=E4),IF(F4="All",TRUE(),'Bid Monitoring'!R48=F4)),'Bid Monitoring'!H48,"") | G58: =IF(AND('Bid Monitoring'!B48<>"",IF(B4="All",TRUE(),'Bid Monitoring'!N48=B4),IF(C4="All",TRUE(),'Bid Monitoring'!L48=C4),IF(D4="All",TRUE(),'Bid Monitoring'!F48=D4),IF(E4="All",TRUE(),'Bid Monitoring'!E48=E4),IF(F4="All",TRUE(),'Bid Monitoring'!R48=F4)),'Bid Monitoring'!I48,"") | H58: =IF(AND('Bid Monitoring'!B48<>"",IF(B4="All",TRUE(),'Bid Monitoring'!N48=B4),IF(C4="All",TRUE(),'Bid Monitoring'!L48=C4),IF(D4="All",TRUE(),'Bid Monitoring'!F48=D4),IF(E4="All",TRUE(),'Bid Monitoring'!E48=E4),IF(F4="All",TRUE(),'Bid Monitoring'!R48=F4)),'Bid Monitoring'!K48,"") | I58: =IF(AND('Bid Monitoring'!B48<>"",IF(B4="All",TRUE(),'Bid Monitoring'!N48=B4),IF(C4="All",TRUE(),'Bid Monitoring'!L48=C4),IF(D4="All",TRUE(),'Bid Monitoring'!F48=D4),IF(E4="All",TRUE(),'Bid Monitoring'!E48=E4),IF(F4="All",TRUE(),'Bid Monitoring'!R48=F4)),'Bid Monitoring'!N48,"") | J58: =IF(AND('Bid Monitoring'!B48<>"",IF(B4="All",TRUE(),'Bid Monitoring'!N48=B4),IF(C4="All",TRUE(),'Bid Monitoring'!L48=C4),IF(D4="All",TRUE(),'Bid Monitoring'!F48=D4),IF(E4="All",TRUE(),'Bid Monitoring'!E48=E4),IF(F4="All",TRUE(),'Bid Monitoring'!R48=F4)),'Bid Monitoring'!L48,"")
A59: =IF(AND('Bid Monitoring'!B49<>"",IF(B4="All",TRUE(),'Bid Monitoring'!N49=B4),IF(C4="All",TRUE(),'Bid Monitoring'!L49=C4),IF(D4="All",TRUE(),'Bid Monitoring'!F49=D4),IF(E4="All",TRUE(),'Bid Monitoring'!E49=E4),IF(F4="All",TRUE(),'Bid Monitoring'!R49=F4)),'Bid Monitoring'!B49,"") | B59: =IF(AND('Bid Monitoring'!B49<>"",IF(B4="All",TRUE(),'Bid Monitoring'!N49=B4),IF(C4="All",TRUE(),'Bid Monitoring'!L49=C4),IF(D4="All",TRUE(),'Bid Monitoring'!F49=D4),IF(E4="All",TRUE(),'Bid Monitoring'!E49=E4),IF(F4="All",TRUE(),'Bid Monitoring'!R49=F4)),'Bid Monitoring'!D49,"") | C59: =IF(AND('Bid Monitoring'!B49<>"",IF(B4="All",TRUE(),'Bid Monitoring'!N49=B4),IF(C4="All",TRUE(),'Bid Monitoring'!L49=C4),IF(D4="All",TRUE(),'Bid Monitoring'!F49=D4),IF(E4="All",TRUE(),'Bid Monitoring'!E49=E4),IF(F4="All",TRUE(),'Bid Monitoring'!R49=F4)),'Bid Monitoring'!C49,"") | D59: =IF(AND('Bid Monitoring'!B49<>"",IF(B4="All",TRUE(),'Bid Monitoring'!N49=B4),IF(C4="All",TRUE(),'Bid Monitoring'!L49=C4),IF(D4="All",TRUE(),'Bid Monitoring'!F49=D4),IF(E4="All",TRUE(),'Bid Monitoring'!E49=E4),IF(F4="All",TRUE(),'Bid Monitoring'!R49=F4)),'Bid Monitoring'!E49,"") | E59: =IF(AND('Bid Monitoring'!B49<>"",IF(B4="All",TRUE(),'Bid Monitoring'!N49=B4),IF(C4="All",TRUE(),'Bid Monitoring'!L49=C4),IF(D4="All",TRUE(),'Bid Monitoring'!F49=D4),IF(E4="All",TRUE(),'Bid Monitoring'!E49=E4),IF(F4="All",TRUE(),'Bid Monitoring'!R49=F4)),'Bid Monitoring'!F49,"") | F59: =IF(AND('Bid Monitoring'!B49<>"",IF(B4="All",TRUE(),'Bid Monitoring'!N49=B4),IF(C4="All",TRUE(),'Bid Monitoring'!L49=C4),IF(D4="All",TRUE(),'Bid Monitoring'!F49=D4),IF(E4="All",TRUE(),'Bid Monitoring'!E49=E4),IF(F4="All",TRUE(),'Bid Monitoring'!R49=F4)),'Bid Monitoring'!H49,"") | G59: =IF(AND('Bid Monitoring'!B49<>"",IF(B4="All",TRUE(),'Bid Monitoring'!N49=B4),IF(C4="All",TRUE(),'Bid Monitoring'!L49=C4),IF(D4="All",TRUE(),'Bid Monitoring'!F49=D4),IF(E4="All",TRUE(),'Bid Monitoring'!E49=E4),IF(F4="All",TRUE(),'Bid Monitoring'!R49=F4)),'Bid Monitoring'!I49,"") | H59: =IF(AND('Bid Monitoring'!B49<>"",IF(B4="All",TRUE(),'Bid Monitoring'!N49=B4),IF(C4="All",TRUE(),'Bid Monitoring'!L49=C4),IF(D4="All",TRUE(),'Bid Monitoring'!F49=D4),IF(E4="All",TRUE(),'Bid Monitoring'!E49=E4),IF(F4="All",TRUE(),'Bid Monitoring'!R49=F4)),'Bid Monitoring'!K49,"") | I59: =IF(AND('Bid Monitoring'!B49<>"",IF(B4="All",TRUE(),'Bid Monitoring'!N49=B4),IF(C4="All",TRUE(),'Bid Monitoring'!L49=C4),IF(D4="All",TRUE(),'Bid Monitoring'!F49=D4),IF(E4="All",TRUE(),'Bid Monitoring'!E49=E4),IF(F4="All",TRUE(),'Bid Monitoring'!R49=F4)),'Bid Monitoring'!N49,"") | J59: =IF(AND('Bid Monitoring'!B49<>"",IF(B4="All",TRUE(),'Bid Monitoring'!N49=B4),IF(C4="All",TRUE(),'Bid Monitoring'!L49=C4),IF(D4="All",TRUE(),'Bid Monitoring'!F49=D4),IF(E4="All",TRUE(),'Bid Monitoring'!E49=E4),IF(F4="All",TRUE(),'Bid Monitoring'!R49=F4)),'Bid Monitoring'!L49,"")
A60: =IF(AND('Bid Monitoring'!B50<>"",IF(B4="All",TRUE(),'Bid Monitoring'!N50=B4),IF(C4="All",TRUE(),'Bid Monitoring'!L50=C4),IF(D4="All",TRUE(),'Bid Monitoring'!F50=D4),IF(E4="All",TRUE(),'Bid Monitoring'!E50=E4),IF(F4="All",TRUE(),'Bid Monitoring'!R50=F4)),'Bid Monitoring'!B50,"") | B60: =IF(AND('Bid Monitoring'!B50<>"",IF(B4="All",TRUE(),'Bid Monitoring'!N50=B4),IF(C4="All",TRUE(),'Bid Monitoring'!L50=C4),IF(D4="All",TRUE(),'Bid Monitoring'!F50=D4),IF(E4="All",TRUE(),'Bid Monitoring'!E50=E4),IF(F4="All",TRUE(),'Bid Monitoring'!R50=F4)),'Bid Monitoring'!D50,"") | C60: =IF(AND('Bid Monitoring'!B50<>"",IF(B4="All",TRUE(),'Bid Monitoring'!N50=B4),IF(C4="All",TRUE(),'Bid Monitoring'!L50=C4),IF(D4="All",TRUE(),'Bid Monitoring'!F50=D4),IF(E4="All",TRUE(),'Bid Monitoring'!E50=E4),IF(F4="All",TRUE(),'Bid Monitoring'!R50=F4)),'Bid Monitoring'!C50,"") | D60: =IF(AND('Bid Monitoring'!B50<>"",IF(B4="All",TRUE(),'Bid Monitoring'!N50=B4),IF(C4="All",TRUE(),'Bid Monitoring'!L50=C4),IF(D4="All",TRUE(),'Bid Monitoring'!F50=D4),IF(E4="All",TRUE(),'Bid Monitoring'!E50=E4),IF(F4="All",TRUE(),'Bid Monitoring'!R50=F4)),'Bid Monitoring'!E50,"") | E60: =IF(AND('Bid Monitoring'!B50<>"",IF(B4="All",TRUE(),'Bid Monitoring'!N50=B4),IF(C4="All",TRUE(),'Bid Monitoring'!L50=C4),IF(D4="All",TRUE(),'Bid Monitoring'!F50=D4),IF(E4="All",TRUE(),'Bid Monitoring'!E50=E4),IF(F4="All",TRUE(),'Bid Monitoring'!R50=F4)),'Bid Monitoring'!F50,"") | F60: =IF(AND('Bid Monitoring'!B50<>"",IF(B4="All",TRUE(),'Bid Monitoring'!N50=B4),IF(C4="All",TRUE(),'Bid Monitoring'!L50=C4),IF(D4="All",TRUE(),'Bid Monitoring'!F50=D4),IF(E4="All",TRUE(),'Bid Monitoring'!E50=E4),IF(F4="All",TRUE(),'Bid Monitoring'!R50=F4)),'Bid Monitoring'!H50,"") | G60: =IF(AND('Bid Monitoring'!B50<>"",IF(B4="All",TRUE(),'Bid Monitoring'!N50=B4),IF(C4="All",TRUE(),'Bid Monitoring'!L50=C4),IF(D4="All",TRUE(),'Bid Monitoring'!F50=D4),IF(E4="All",TRUE(),'Bid Monitoring'!E50=E4),IF(F4="All",TRUE(),'Bid Monitoring'!R50=F4)),'Bid Monitoring'!I50,"") | H60: =IF(AND('Bid Monitoring'!B50<>"",IF(B4="All",TRUE(),'Bid Monitoring'!N50=B4),IF(C4="All",TRUE(),'Bid Monitoring'!L50=C4),IF(D4="All",TRUE(),'Bid Monitoring'!F50=D4),IF(E4="All",TRUE(),'Bid Monitoring'!E50=E4),IF(F4="All",TRUE(),'Bid Monitoring'!R50=F4)),'Bid Monitoring'!K50,"") | I60: =IF(AND('Bid Monitoring'!B50<>"",IF(B4="All",TRUE(),'Bid Monitoring'!N50=B4),IF(C4="All",TRUE(),'Bid Monitoring'!L50=C4),IF(D4="All",TRUE(),'Bid Monitoring'!F50=D4),IF(E4="All",TRUE(),'Bid Monitoring'!E50=E4),IF(F4="All",TRUE(),'Bid Monitoring'!R50=F4)),'Bid Monitoring'!N50,"") | J60: =IF(AND('Bid Monitoring'!B50<>"",IF(B4="All",TRUE(),'Bid Monitoring'!N50=B4),IF(C4="All",TRUE(),'Bid Monitoring'!L50=C4),IF(D4="All",TRUE(),'Bid Monitoring'!F50=D4),IF(E4="All",TRUE(),'Bid Monitoring'!E50=E4),IF(F4="All",TRUE(),'Bid Monitoring'!R50=F4)),'Bid Monitoring'!L50,"")
A61: =IF(AND('Bid Monitoring'!B51<>"",IF(B4="All",TRUE(),'Bid Monitoring'!N51=B4),IF(C4="All",TRUE(),'Bid Monitoring'!L51=C4),IF(D4="All",TRUE(),'Bid Monitoring'!F51=D4),IF(E4="All",TRUE(),'Bid Monitoring'!E51=E4),IF(F4="All",TRUE(),'Bid Monitoring'!R51=F4)),'Bid Monitoring'!B51,"") | B61: =IF(AND('Bid Monitoring'!B51<>"",IF(B4="All",TRUE(),'Bid Monitoring'!N51=B4),IF(C4="All",TRUE(),'Bid Monitoring'!L51=C4),IF(D4="All",TRUE(),'Bid Monitoring'!F51=D4),IF(E4="All",TRUE(),'Bid Monitoring'!E51=E4),IF(F4="All",TRUE(),'Bid Monitoring'!R51=F4)),'Bid Monitoring'!D51,"") | C61: =IF(AND('Bid Monitoring'!B51<>"",IF(B4="All",TRUE(),'Bid Monitoring'!N51=B4),IF(C4="All",TRUE(),'Bid Monitoring'!L51=C4),IF(D4="All",TRUE(),'Bid Monitoring'!F51=D4),IF(E4="All",TRUE(),'Bid Monitoring'!E51=E4),IF(F4="All",TRUE(),'Bid Monitoring'!R51=F4)),'Bid Monitoring'!C51,"") | D61: =IF(AND('Bid Monitoring'!B51<>"",IF(B4="All",TRUE(),'Bid Monitoring'!N51=B4),IF(C4="All",TRUE(),'Bid Monitoring'!L51=C4),IF(D4="All",TRUE(),'Bid Monitoring'!F51=D4),IF(E4="All",TRUE(),'Bid Monitoring'!E51=E4),IF(F4="All",TRUE(),'Bid Monitoring'!R51=F4)),'Bid Monitoring'!E51,"") | E61: =IF(AND('Bid Monitoring'!B51<>"",IF(B4="All",TRUE(),'Bid Monitoring'!N51=B4),IF(C4="All",TRUE(),'Bid Monitoring'!L51=C4),IF(D4="All",TRUE(),'Bid Monitoring'!F51=D4),IF(E4="All",TRUE(),'Bid Monitoring'!E51=E4),IF(F4="All",TRUE(),'Bid Monitoring'!R51=F4)),'Bid Monitoring'!F51,"") | F61: =IF(AND('Bid Monitoring'!B51<>"",IF(B4="All",TRUE(),'Bid Monitoring'!N51=B4),IF(C4="All",TRUE(),'Bid Monitoring'!L51=C4),IF(D4="All",TRUE(),'Bid Monitoring'!F51=D4),IF(E4="All",TRUE(),'Bid Monitoring'!E51=E4),IF(F4="All",TRUE(),'Bid Monitoring'!R51=F4)),'Bid Monitoring'!H51,"") | G61: =IF(AND('Bid Monitoring'!B51<>"",IF(B4="All",TRUE(),'Bid Monitoring'!N51=B4),IF(C4="All",TRUE(),'Bid Monitoring'!L51=C4),IF(D4="All",TRUE(),'Bid Monitoring'!F51=D4),IF(E4="All",TRUE(),'Bid Monitoring'!E51=E4),IF(F4="All",TRUE(),'Bid Monitoring'!R51=F4)),'Bid Monitoring'!I51,"") | H61: =IF(AND('Bid Monitoring'!B51<>"",IF(B4="All",TRUE(),'Bid Monitoring'!N51=B4),IF(C4="All",TRUE(),'Bid Monitoring'!L51=C4),IF(D4="All",TRUE(),'Bid Monitoring'!F51=D4),IF(E4="All",TRUE(),'Bid Monitoring'!E51=E4),IF(F4="All",TRUE(),'Bid Monitoring'!R51=F4)),'Bid Monitoring'!K51,"") | I61: =IF(AND('Bid Monitoring'!B51<>"",IF(B4="All",TRUE(),'Bid Monitoring'!N51=B4),IF(C4="All",TRUE(),'Bid Monitoring'!L51=C4),IF(D4="All",TRUE(),'Bid Monitoring'!F51=D4),IF(E4="All",TRUE(),'Bid Monitoring'!E51=E4),IF(F4="All",TRUE(),'Bid Monitoring'!R51=F4)),'Bid Monitoring'!N51,"") | J61: =IF(AND('Bid Monitoring'!B51<>"",IF(B4="All",TRUE(),'Bid Monitoring'!N51=B4),IF(C4="All",TRUE(),'Bid Monitoring'!L51=C4),IF(D4="All",TRUE(),'Bid Monitoring'!F51=D4),IF(E4="All",TRUE(),'Bid Monitoring'!E51=E4),IF(F4="All",TRUE(),'Bid Monitoring'!R51=F4)),'Bid Monitoring'!L51,"")
A62: =IF(AND('Bid Monitoring'!B52<>"",IF(B4="All",TRUE(),'Bid Monitoring'!N52=B4),IF(C4="All",TRUE(),'Bid Monitoring'!L52=C4),IF(D4="All",TRUE(),'Bid Monitoring'!F52=D4),IF(E4="All",TRUE(),'Bid Monitoring'!E52=E4),IF(F4="All",TRUE(),'Bid Monitoring'!R52=F4)),'Bid Monitoring'!B52,"") | B62: =IF(AND('Bid Monitoring'!B52<>"",IF(B4="All",TRUE(),'Bid Monitoring'!N52=B4),IF(C4="All",TRUE(),'Bid Monitoring'!L52=C4),IF(D4="All",TRUE(),'Bid Monitoring'!F52=D4),IF(E4="All",TRUE(),'Bid Monitoring'!E52=E4),IF(F4="All",TRUE(),'Bid Monitoring'!R52=F4)),'Bid Monitoring'!D52,"") | C62: =IF(AND('Bid Monitoring'!B52<>"",IF(B4="All",TRUE(),'Bid Monitoring'!N52=B4),IF(C4="All",TRUE(),'Bid Monitoring'!L52=C4),IF(D4="All",TRUE(),'Bid Monitoring'!F52=D4),IF(E4="All",TRUE(),'Bid Monitoring'!E52=E4),IF(F4="All",TRUE(),'Bid Monitoring'!R52=F4)),'Bid Monitoring'!C52,"") | D62: =IF(AND('Bid Monitoring'!B52<>"",IF(B4="All",TRUE(),'Bid Monitoring'!N52=B4),IF(C4="All",TRUE(),'Bid Monitoring'!L52=C4),IF(D4="All",TRUE(),'Bid Monitoring'!F52=D4),IF(E4="All",TRUE(),'Bid Monitoring'!E52=E4),IF(F4="All",TRUE(),'Bid Monitoring'!R52=F4)),'Bid Monitoring'!E52,"") | E62: =IF(AND('Bid Monitoring'!B52<>"",IF(B4="All",TRUE(),'Bid Monitoring'!N52=B4),IF(C4="All",TRUE(),'Bid Monitoring'!L52=C4),IF(D4="All",TRUE(),'Bid Monitoring'!F52=D4),IF(E4="All",TRUE(),'Bid Monitoring'!E52=E4),IF(F4="All",TRUE(),'Bid Monitoring'!R52=F4)),'Bid Monitoring'!F52,"") | F62: =IF(AND('Bid Monitoring'!B52<>"",IF(B4="All",TRUE(),'Bid Monitoring'!N52=B4),IF(C4="All",TRUE(),'Bid Monitoring'!L52=C4),IF(D4="All",TRUE(),'Bid Monitoring'!F52=D4),IF(E4="All",TRUE(),'Bid Monitoring'!E52=E4),IF(F4="All",TRUE(),'Bid Monitoring'!R52=F4)),'Bid Monitoring'!H52,"") | G62: =IF(AND('Bid Monitoring'!B52<>"",IF(B4="All",TRUE(),'Bid Monitoring'!N52=B4),IF(C4="All",TRUE(),'Bid Monitoring'!L52=C4),IF(D4="All",TRUE(),'Bid Monitoring'!F52=D4),IF(E4="All",TRUE(),'Bid Monitoring'!E52=E4),IF(F4="All",TRUE(),'Bid Monitoring'!R52=F4)),'Bid Monitoring'!I52,"") | H62: =IF(AND('Bid Monitoring'!B52<>"",IF(B4="All",TRUE(),'Bid Monitoring'!N52=B4),IF(C4="All",TRUE(),'Bid Monitoring'!L52=C4),IF(D4="All",TRUE(),'Bid Monitoring'!F52=D4),IF(E4="All",TRUE(),'Bid Monitoring'!E52=E4),IF(F4="All",TRUE(),'Bid Monitoring'!R52=F4)),'Bid Monitoring'!K52,"") | I62: =IF(AND('Bid Monitoring'!B52<>"",IF(B4="All",TRUE(),'Bid Monitoring'!N52=B4),IF(C4="All",TRUE(),'Bid Monitoring'!L52=C4),IF(D4="All",TRUE(),'Bid Monitoring'!F52=D4),IF(E4="All",TRUE(),'Bid Monitoring'!E52=E4),IF(F4="All",TRUE(),'Bid Monitoring'!R52=F4)),'Bid Monitoring'!N52,"") | J62: =IF(AND('Bid Monitoring'!B52<>"",IF(B4="All",TRUE(),'Bid Monitoring'!N52=B4),IF(C4="All",TRUE(),'Bid Monitoring'!L52=C4),IF(D4="All",TRUE(),'Bid Monitoring'!F52=D4),IF(E4="All",TRUE(),'Bid Monitoring'!E52=E4),IF(F4="All",TRUE(),'Bid Monitoring'!R52=F4)),'Bid Monitoring'!L52,"")
A63: =IF(AND('Bid Monitoring'!B53<>"",IF(B4="All",TRUE(),'Bid Monitoring'!N53=B4),IF(C4="All",TRUE(),'Bid Monitoring'!L53=C4),IF(D4="All",TRUE(),'Bid Monitoring'!F53=D4),IF(E4="All",TRUE(),'Bid Monitoring'!E53=E4),IF(F4="All",TRUE(),'Bid Monitoring'!R53=F4)),'Bid Monitoring'!B53,"") | B63: =IF(AND('Bid Monitoring'!B53<>"",IF(B4="All",TRUE(),'Bid Monitoring'!N53=B4),IF(C4="All",TRUE(),'Bid Monitoring'!L53=C4),IF(D4="All",TRUE(),'Bid Monitoring'!F53=D4),IF(E4="All",TRUE(),'Bid Monitoring'!E53=E4),IF(F4="All",TRUE(),'Bid Monitoring'!R53=F4)),'Bid Monitoring'!D53,"") | C63: =IF(AND('Bid Monitoring'!B53<>"",IF(B4="All",TRUE(),'Bid Monitoring'!N53=B4),IF(C4="All",TRUE(),'Bid Monitoring'!L53=C4),IF(D4="All",TRUE(),'Bid Monitoring'!F53=D4),IF(E4="All",TRUE(),'Bid Monitoring'!E53=E4),IF(F4="All",TRUE(),'Bid Monitoring'!R53=F4)),'Bid Monitoring'!C53,"") | D63: =IF(AND('Bid Monitoring'!B53<>"",IF(B4="All",TRUE(),'Bid Monitoring'!N53=B4),IF(C4="All",TRUE(),'Bid Monitoring'!L53=C4),IF(D4="All",TRUE(),'Bid Monitoring'!F53=D4),IF(E4="All",TRUE(),'Bid Monitoring'!E53=E4),IF(F4="All",TRUE(),'Bid Monitoring'!R53=F4)),'Bid Monitoring'!E53,"") | E63: =IF(AND('Bid Monitoring'!B53<>"",IF(B4="All",TRUE(),'Bid Monitoring'!N53=B4),IF(C4="All",TRUE(),'Bid Monitoring'!L53=C4),IF(D4="All",TRUE(),'Bid Monitoring'!F53=D4),IF(E4="All",TRUE(),'Bid Monitoring'!E53=E4),IF(F4="All",TRUE(),'Bid Monitoring'!R53=F4)),'Bid Monitoring'!F53,"") | F63: =IF(AND('Bid Monitoring'!B53<>"",IF(B4="All",TRUE(),'Bid Monitoring'!N53=B4),IF(C4="All",TRUE(),'Bid Monitoring'!L53=C4),IF(D4="All",TRUE(),'Bid Monitoring'!F53=D4),IF(E4="All",TRUE(),'Bid Monitoring'!E53=E4),IF(F4="All",TRUE(),'Bid Monitoring'!R53=F4)),'Bid Monitoring'!H53,"") | G63: =IF(AND('Bid Monitoring'!B53<>"",IF(B4="All",TRUE(),'Bid Monitoring'!N53=B4),IF(C4="All",TRUE(),'Bid Monitoring'!L53=C4),IF(D4="All",TRUE(),'Bid Monitoring'!F53=D4),IF(E4="All",TRUE(),'Bid Monitoring'!E53=E4),IF(F4="All",TRUE(),'Bid Monitoring'!R53=F4)),'Bid Monitoring'!I53,"") | H63: =IF(AND('Bid Monitoring'!B53<>"",IF(B4="All",TRUE(),'Bid Monitoring'!N53=B4),IF(C4="All",TRUE(),'Bid Monitoring'!L53=C4),IF(D4="All",TRUE(),'Bid Monitoring'!F53=D4),IF(E4="All",TRUE(),'Bid Monitoring'!E53=E4),IF(F4="All",TRUE(),'Bid Monitoring'!R53=F4)),'Bid Monitoring'!K53,"") | I63: =IF(AND('Bid Monitoring'!B53<>"",IF(B4="All",TRUE(),'Bid Monitoring'!N53=B4),IF(C4="All",TRUE(),'Bid Monitoring'!L53=C4),IF(D4="All",TRUE(),'Bid Monitoring'!F53=D4),IF(E4="All",TRUE(),'Bid Monitoring'!E53=E4),IF(F4="All",TRUE(),'Bid Monitoring'!R53=F4)),'Bid Monitoring'!N53,"") | J63: =IF(AND('Bid Monitoring'!B53<>"",IF(B4="All",TRUE(),'Bid Monitoring'!N53=B4),IF(C4="All",TRUE(),'Bid Monitoring'!L53=C4),IF(D4="All",TRUE(),'Bid Monitoring'!F53=D4),IF(E4="All",TRUE(),'Bid Monitoring'!E53=E4),IF(F4="All",TRUE(),'Bid Monitoring'!R53=F4)),'Bid Monitoring'!L53,"")
A64: =IF(AND('Bid Monitoring'!B54<>"",IF(B4="All",TRUE(),'Bid Monitoring'!N54=B4),IF(C4="All",TRUE(),'Bid Monitoring'!L54=C4),IF(D4="All",TRUE(),'Bid Monitoring'!F54=D4),IF(E4="All",TRUE(),'Bid Monitoring'!E54=E4),IF(F4="All",TRUE(),'Bid Monitoring'!R54=F4)),'Bid Monitoring'!B54,"") | B64: =IF(AND('Bid Monitoring'!B54<>"",IF(B4="All",TRUE(),'Bid Monitoring'!N54=B4),IF(C4="All",TRUE(),'Bid Monitoring'!L54=C4),IF(D4="All",TRUE(),'Bid Monitoring'!F54=D4),IF(E4="All",TRUE(),'Bid Monitoring'!E54=E4),IF(F4="All",TRUE(),'Bid Monitoring'!R54=F4)),'Bid Monitoring'!D54,"") | C64: =IF(AND('Bid Monitoring'!B54<>"",IF(B4="All",TRUE(),'Bid Monitoring'!N54=B4),IF(C4="All",TRUE(),'Bid Monitoring'!L54=C4),IF(D4="All",TRUE(),'Bid Monitoring'!F54=D4),IF(E4="All",TRUE(),'Bid Monitoring'!E54=E4),IF(F4="All",TRUE(),'Bid Monitoring'!R54=F4)),'Bid Monitoring'!C54,"") | D64: =IF(AND('Bid Monitoring'!B54<>"",IF(B4="All",TRUE(),'Bid Monitoring'!N54=B4),IF(C4="All",TRUE(),'Bid Monitoring'!L54=C4),IF(D4="All",TRUE(),'Bid Monitoring'!F54=D4),IF(E4="All",TRUE(),'Bid Monitoring'!E54=E4),IF(F4="All",TRUE(),'Bid Monitoring'!R54=F4)),'Bid Monitoring'!E54,"") | E64: =IF(AND('Bid Monitoring'!B54<>"",IF(B4="All",TRUE(),'Bid Monitoring'!N54=B4),IF(C4="All",TRUE(),'Bid Monitoring'!L54=C4),IF(D4="All",TRUE(),'Bid Monitoring'!F54=D4),IF(E4="All",TRUE(),'Bid Monitoring'!E54=E4),IF(F4="All",TRUE(),'Bid Monitoring'!R54=F4)),'Bid Monitoring'!F54,"") | F64: =IF(AND('Bid Monitoring'!B54<>"",IF(B4="All",TRUE(),'Bid Monitoring'!N54=B4),IF(C4="All",TRUE(),'Bid Monitoring'!L54=C4),IF(D4="All",TRUE(),'Bid Monitoring'!F54=D4),IF(E4="All",TRUE(),'Bid Monitoring'!E54=E4),IF(F4="All",TRUE(),'Bid Monitoring'!R54=F4)),'Bid Monitoring'!H54,"") | G64: =IF(AND('Bid Monitoring'!B54<>"",IF(B4="All",TRUE(),'Bid Monitoring'!N54=B4),IF(C4="All",TRUE(),'Bid Monitoring'!L54=C4),IF(D4="All",TRUE(),'Bid Monitoring'!F54=D4),IF(E4="All",TRUE(),'Bid Monitoring'!E54=E4),IF(F4="All",TRUE(),'Bid Monitoring'!R54=F4)),'Bid Monitoring'!I54,"") | H64: =IF(AND('Bid Monitoring'!B54<>"",IF(B4="All",TRUE(),'Bid Monitoring'!N54=B4),IF(C4="All",TRUE(),'Bid Monitoring'!L54=C4),IF(D4="All",TRUE(),'Bid Monitoring'!F54=D4),IF(E4="All",TRUE(),'Bid Monitoring'!E54=E4),IF(F4="All",TRUE(),'Bid Monitoring'!R54=F4)),'Bid Monitoring'!K54,"") | I64: =IF(AND('Bid Monitoring'!B54<>"",IF(B4="All",TRUE(),'Bid Monitoring'!N54=B4),IF(C4="All",TRUE(),'Bid Monitoring'!L54=C4),IF(D4="All",TRUE(),'Bid Monitoring'!F54=D4),IF(E4="All",TRUE(),'Bid Monitoring'!E54=E4),IF(F4="All",TRUE(),'Bid Monitoring'!R54=F4)),'Bid Monitoring'!N54,"") | J64: =IF(AND('Bid Monitoring'!B54<>"",IF(B4="All",TRUE(),'Bid Monitoring'!N54=B4),IF(C4="All",TRUE(),'Bid Monitoring'!L54=C4),IF(D4="All",TRUE(),'Bid Monitoring'!F54=D4),IF(E4="All",TRUE(),'Bid Monitoring'!E54=E4),IF(F4="All",TRUE(),'Bid Monitoring'!R54=F4)),'Bid Monitoring'!L54,"")
A65: =IF(AND('Bid Monitoring'!B55<>"",IF(B4="All",TRUE(),'Bid Monitoring'!N55=B4),IF(C4="All",TRUE(),'Bid Monitoring'!L55=C4),IF(D4="All",TRUE(),'Bid Monitoring'!F55=D4),IF(E4="All",TRUE(),'Bid Monitoring'!E55=E4),IF(F4="All",TRUE(),'Bid Monitoring'!R55=F4)),'Bid Monitoring'!B55,"") | B65: =IF(AND('Bid Monitoring'!B55<>"",IF(B4="All",TRUE(),'Bid Monitoring'!N55=B4),IF(C4="All",TRUE(),'Bid Monitoring'!L55=C4),IF(D4="All",TRUE(),'Bid Monitoring'!F55=D4),IF(E4="All",TRUE(),'Bid Monitoring'!E55=E4),IF(F4="All",TRUE(),'Bid Monitoring'!R55=F4)),'Bid Monitoring'!D55,"") | C65: =IF(AND('Bid Monitoring'!B55<>"",IF(B4="All",TRUE(),'Bid Monitoring'!N55=B4),IF(C4="All",TRUE(),'Bid Monitoring'!L55=C4),IF(D4="All",TRUE(),'Bid Monitoring'!F55=D4),IF(E4="All",TRUE(),'Bid Monitoring'!E55=E4),IF(F4="All",TRUE(),'Bid Monitoring'!R55=F4)),'Bid Monitoring'!C55,"") | D65: =IF(AND('Bid Monitoring'!B55<>"",IF(B4="All",TRUE(),'Bid Monitoring'!N55=B4),IF(C4="All",TRUE(),'Bid Monitoring'!L55=C4),IF(D4="All",TRUE(),'Bid Monitoring'!F55=D4),IF(E4="All",TRUE(),'Bid Monitoring'!E55=E4),IF(F4="All",TRUE(),'Bid Monitoring'!R55=F4)),'Bid Monitoring'!E55,"") | E65: =IF(AND('Bid Monitoring'!B55<>"",IF(B4="All",TRUE(),'Bid Monitoring'!N55=B4),IF(C4="All",TRUE(),'Bid Monitoring'!L55=C4),IF(D4="All",TRUE(),'Bid Monitoring'!F55=D4),IF(E4="All",TRUE(),'Bid Monitoring'!E55=E4),IF(F4="All",TRUE(),'Bid Monitoring'!R55=F4)),'Bid Monitoring'!F55,"") | F65: =IF(AND('Bid Monitoring'!B55<>"",IF(B4="All",TRUE(),'Bid Monitoring'!N55=B4),IF(C4="All",TRUE(),'Bid Monitoring'!L55=C4),IF(D4="All",TRUE(),'Bid Monitoring'!F55=D4),IF(E4="All",TRUE(),'Bid Monitoring'!E55=E4),IF(F4="All",TRUE(),'Bid Monitoring'!R55=F4)),'Bid Monitoring'!H55,"") | G65: =IF(AND('Bid Monitoring'!B55<>"",IF(B4="All",TRUE(),'Bid Monitoring'!N55=B4),IF(C4="All",TRUE(),'Bid Monitoring'!L55=C4),IF(D4="All",TRUE(),'Bid Monitoring'!F55=D4),IF(E4="All",TRUE(),'Bid Monitoring'!E55=E4),IF(F4="All",TRUE(),'Bid Monitoring'!R55=F4)),'Bid Monitoring'!I55,"") | H65: =IF(AND('Bid Monitoring'!B55<>"",IF(B4="All",TRUE(),'Bid Monitoring'!N55=B4),IF(C4="All",TRUE(),'Bid Monitoring'!L55=C4),IF(D4="All",TRUE(),'Bid Monitoring'!F55=D4),IF(E4="All",TRUE(),'Bid Monitoring'!E55=E4),IF(F4="All",TRUE(),'Bid Monitoring'!R55=F4)),'Bid Monitoring'!K55,"") | I65: =IF(AND('Bid Monitoring'!B55<>"",IF(B4="All",TRUE(),'Bid Monitoring'!N55=B4),IF(C4="All",TRUE(),'Bid Monitoring'!L55=C4),IF(D4="All",TRUE(),'Bid Monitoring'!F55=D4),IF(E4="All",TRUE(),'Bid Monitoring'!E55=E4),IF(F4="All",TRUE(),'Bid Monitoring'!R55=F4)),'Bid Monitoring'!N55,"") | J65: =IF(AND('Bid Monitoring'!B55<>"",IF(B4="All",TRUE(),'Bid Monitoring'!N55=B4),IF(C4="All",TRUE(),'Bid Monitoring'!L55=C4),IF(D4="All",TRUE(),'Bid Monitoring'!F55=D4),IF(E4="All",TRUE(),'Bid Monitoring'!E55=E4),IF(F4="All",TRUE(),'Bid Monitoring'!R55=F4)),'Bid Monitoring'!L55,"")
A66: =IF(AND('Bid Monitoring'!B56<>"",IF(B4="All",TRUE(),'Bid Monitoring'!N56=B4),IF(C4="All",TRUE(),'Bid Monitoring'!L56=C4),IF(D4="All",TRUE(),'Bid Monitoring'!F56=D4),IF(E4="All",TRUE(),'Bid Monitoring'!E56=E4),IF(F4="All",TRUE(),'Bid Monitoring'!R56=F4)),'Bid Monitoring'!B56,"") | B66: =IF(AND('Bid Monitoring'!B56<>"",IF(B4="All",TRUE(),'Bid Monitoring'!N56=B4),IF(C4="All",TRUE(),'Bid Monitoring'!L56=C4),IF(D4="All",TRUE(),'Bid Monitoring'!F56=D4),IF(E4="All",TRUE(),'Bid Monitoring'!E56=E4),IF(F4="All",TRUE(),'Bid Monitoring'!R56=F4)),'Bid Monitoring'!D56,"") | C66: =IF(AND('Bid Monitoring'!B56<>"",IF(B4="All",TRUE(),'Bid Monitoring'!N56=B4),IF(C4="All",TRUE(),'Bid Monitoring'!L56=C4),IF(D4="All",TRUE(),'Bid Monitoring'!F56=D4),IF(E4="All",TRUE(),'Bid Monitoring'!E56=E4),IF(F4="All",TRUE(),'Bid Monitoring'!R56=F4)),'Bid Monitoring'!C56,"") | D66: =IF(AND('Bid Monitoring'!B56<>"",IF(B4="All",TRUE(),'Bid Monitoring'!N56=B4),IF(C4="All",TRUE(),'Bid Monitoring'!L56=C4),IF(D4="All",TRUE(),'Bid Monitoring'!F56=D4),IF(E4="All",TRUE(),'Bid Monitoring'!E56=E4),IF(F4="All",TRUE(),'Bid Monitoring'!R56=F4)),'Bid Monitoring'!E56,"") | E66: =IF(AND('Bid Monitoring'!B56<>"",IF(B4="All",TRUE(),'Bid Monitoring'!N56=B4),IF(C4="All",TRUE(),'Bid Monitoring'!L56=C4),IF(D4="All",TRUE(),'Bid Monitoring'!F56=D4),IF(E4="All",TRUE(),'Bid Monitoring'!E56=E4),IF(F4="All",TRUE(),'Bid Monitoring'!R56=F4)),'Bid Monitoring'!F56,"") | F66: =IF(AND('Bid Monitoring'!B56<>"",IF(B4="All",TRUE(),'Bid Monitoring'!N56=B4),IF(C4="All",TRUE(),'Bid Monitoring'!L56=C4),IF(D4="All",TRUE(),'Bid Monitoring'!F56=D4),IF(E4="All",TRUE(),'Bid Monitoring'!E56=E4),IF(F4="All",TRUE(),'Bid Monitoring'!R56=F4)),'Bid Monitoring'!H56,"") | G66: =IF(AND('Bid Monitoring'!B56<>"",IF(B4="All",TRUE(),'Bid Monitoring'!N56=B4),IF(C4="All",TRUE(),'Bid Monitoring'!L56=C4),IF(D4="All",TRUE(),'Bid Monitoring'!F56=D4),IF(E4="All",TRUE(),'Bid Monitoring'!E56=E4),IF(F4="All",TRUE(),'Bid Monitoring'!R56=F4)),'Bid Monitoring'!I56,"") | H66: =IF(AND('Bid Monitoring'!B56<>"",IF(B4="All",TRUE(),'Bid Monitoring'!N56=B4),IF(C4="All",TRUE(),'Bid Monitoring'!L56=C4),IF(D4="All",TRUE(),'Bid Monitoring'!F56=D4),IF(E4="All",TRUE(),'Bid Monitoring'!E56=E4),IF(F4="All",TRUE(),'Bid Monitoring'!R56=F4)),'Bid Monitoring'!K56,"") | I66: =IF(AND('Bid Monitoring'!B56<>"",IF(B4="All",TRUE(),'Bid Monitoring'!N56=B4),IF(C4="All",TRUE(),'Bid Monitoring'!L56=C4),IF(D4="All",TRUE(),'Bid Monitoring'!F56=D4),IF(E4="All",TRUE(),'Bid Monitoring'!E56=E4),IF(F4="All",TRUE(),'Bid Monitoring'!R56=F4)),'Bid Monitoring'!N56,"") | J66: =IF(AND('Bid Monitoring'!B56<>"",IF(B4="All",TRUE(),'Bid Monitoring'!N56=B4),IF(C4="All",TRUE(),'Bid Monitoring'!L56=C4),IF(D4="All",TRUE(),'Bid Monitoring'!F56=D4),IF(E4="All",TRUE(),'Bid Monitoring'!E56=E4),IF(F4="All",TRUE(),'Bid Monitoring'!R56=F4)),'Bid Monitoring'!L56,"")
A67: =IF(AND('Bid Monitoring'!B57<>"",IF(B4="All",TRUE(),'Bid Monitoring'!N57=B4),IF(C4="All",TRUE(),'Bid Monitoring'!L57=C4),IF(D4="All",TRUE(),'Bid Monitoring'!F57=D4),IF(E4="All",TRUE(),'Bid Monitoring'!E57=E4),IF(F4="All",TRUE(),'Bid Monitoring'!R57=F4)),'Bid Monitoring'!B57,"") | B67: =IF(AND('Bid Monitoring'!B57<>"",IF(B4="All",TRUE(),'Bid Monitoring'!N57=B4),IF(C4="All",TRUE(),'Bid Monitoring'!L57=C4),IF(D4="All",TRUE(),'Bid Monitoring'!F57=D4),IF(E4="All",TRUE(),'Bid Monitoring'!E57=E4),IF(F4="All",TRUE(),'Bid Monitoring'!R57=F4)),'Bid Monitoring'!D57,"") | C67: =IF(AND('Bid Monitoring'!B57<>"",IF(B4="All",TRUE(),'Bid Monitoring'!N57=B4),IF(C4="All",TRUE(),'Bid Monitoring'!L57=C4),IF(D4="All",TRUE(),'Bid Monitoring'!F57=D4),IF(E4="All",TRUE(),'Bid Monitoring'!E57=E4),IF(F4="All",TRUE(),'Bid Monitoring'!R57=F4)),'Bid Monitoring'!C57,"") | D67: =IF(AND('Bid Monitoring'!B57<>"",IF(B4="All",TRUE(),'Bid Monitoring'!N57=B4),IF(C4="All",TRUE(),'Bid Monitoring'!L57=C4),IF(D4="All",TRUE(),'Bid Monitoring'!F57=D4),IF(E4="All",TRUE(),'Bid Monitoring'!E57=E4),IF(F4="All",TRUE(),'Bid Monitoring'!R57=F4)),'Bid Monitoring'!E57,"") | E67: =IF(AND('Bid Monitoring'!B57<>"",IF(B4="All",TRUE(),'Bid Monitoring'!N57=B4),IF(C4="All",TRUE(),'Bid Monitoring'!L57=C4),IF(D4="All",TRUE(),'Bid Monitoring'!F57=D4),IF(E4="All",TRUE(),'Bid Monitoring'!E57=E4),IF(F4="All",TRUE(),'Bid Monitoring'!R57=F4)),'Bid Monitoring'!F57,"") | F67: =IF(AND('Bid Monitoring'!B57<>"",IF(B4="All",TRUE(),'Bid Monitoring'!N57=B4),IF(C4="All",TRUE(),'Bid Monitoring'!L57=C4),IF(D4="All",TRUE(),'Bid Monitoring'!F57=D4),IF(E4="All",TRUE(),'Bid Monitoring'!E57=E4),IF(F4="All",TRUE(),'Bid Monitoring'!R57=F4)),'Bid Monitoring'!H57,"") | G67: =IF(AND('Bid Monitoring'!B57<>"",IF(B4="All",TRUE(),'Bid Monitoring'!N57=B4),IF(C4="All",TRUE(),'Bid Monitoring'!L57=C4),IF(D4="All",TRUE(),'Bid Monitoring'!F57=D4),IF(E4="All",TRUE(),'Bid Monitoring'!E57=E4),IF(F4="All",TRUE(),'Bid Monitoring'!R57=F4)),'Bid Monitoring'!I57,"") | H67: =IF(AND('Bid Monitoring'!B57<>"",IF(B4="All",TRUE(),'Bid Monitoring'!N57=B4),IF(C4="All",TRUE(),'Bid Monitoring'!L57=C4),IF(D4="All",TRUE(),'Bid Monitoring'!F57=D4),IF(E4="All",TRUE(),'Bid Monitoring'!E57=E4),IF(F4="All",TRUE(),'Bid Monitoring'!R57=F4)),'Bid Monitoring'!K57,"") | I67: =IF(AND('Bid Monitoring'!B57<>"",IF(B4="All",TRUE(),'Bid Monitoring'!N57=B4),IF(C4="All",TRUE(),'Bid Monitoring'!L57=C4),IF(D4="All",TRUE(),'Bid Monitoring'!F57=D4),IF(E4="All",TRUE(),'Bid Monitoring'!E57=E4),IF(F4="All",TRUE(),'Bid Monitoring'!R57=F4)),'Bid Monitoring'!N57,"") | J67: =IF(AND('Bid Monitoring'!B57<>"",IF(B4="All",TRUE(),'Bid Monitoring'!N57=B4),IF(C4="All",TRUE(),'Bid Monitoring'!L57=C4),IF(D4="All",TRUE(),'Bid Monitoring'!F57=D4),IF(E4="All",TRUE(),'Bid Monitoring'!E57=E4),IF(F4="All",TRUE(),'Bid Monitoring'!R57=F4)),'Bid Monitoring'!L57,"")
A68: =IF(AND('Bid Monitoring'!B58<>"",IF(B4="All",TRUE(),'Bid Monitoring'!N58=B4),IF(C4="All",TRUE(),'Bid Monitoring'!L58=C4),IF(D4="All",TRUE(),'Bid Monitoring'!F58=D4),IF(E4="All",TRUE(),'Bid Monitoring'!E58=E4),IF(F4="All",TRUE(),'Bid Monitoring'!R58=F4)),'Bid Monitoring'!B58,"") | B68: =IF(AND('Bid Monitoring'!B58<>"",IF(B4="All",TRUE(),'Bid Monitoring'!N58=B4),IF(C4="All",TRUE(),'Bid Monitoring'!L58=C4),IF(D4="All",TRUE(),'Bid Monitoring'!F58=D4),IF(E4="All",TRUE(),'Bid Monitoring'!E58=E4),IF(F4="All",TRUE(),'Bid Monitoring'!R58=F4)),'Bid Monitoring'!D58,"") | C68: =IF(AND('Bid Monitoring'!B58<>"",IF(B4="All",TRUE(),'Bid Monitoring'!N58=B4),IF(C4="All",TRUE(),'Bid Monitoring'!L58=C4),IF(D4="All",TRUE(),'Bid Monitoring'!F58=D4),IF(E4="All",TRUE(),'Bid Monitoring'!E58=E4),IF(F4="All",TRUE(),'Bid Monitoring'!R58=F4)),'Bid Monitoring'!C58,"") | D68: =IF(AND('Bid Monitoring'!B58<>"",IF(B4="All",TRUE(),'Bid Monitoring'!N58=B4),IF(C4="All",TRUE(),'Bid Monitoring'!L58=C4),IF(D4="All",TRUE(),'Bid Monitoring'!F58=D4),IF(E4="All",TRUE(),'Bid Monitoring'!E58=E4),IF(F4="All",TRUE(),'Bid Monitoring'!R58=F4)),'Bid Monitoring'!E58,"") | E68: =IF(AND('Bid Monitoring'!B58<>"",IF(B4="All",TRUE(),'Bid Monitoring'!N58=B4),IF(C4="All",TRUE(),'Bid Monitoring'!L58=C4),IF(D4="All",TRUE(),'Bid Monitoring'!F58=D4),IF(E4="All",TRUE(),'Bid Monitoring'!E58=E4),IF(F4="All",TRUE(),'Bid Monitoring'!R58=F4)),'Bid Monitoring'!F58,"") | F68: =IF(AND('Bid Monitoring'!B58<>"",IF(B4="All",TRUE(),'Bid Monitoring'!N58=B4),IF(C4="All",TRUE(),'Bid Monitoring'!L58=C4),IF(D4="All",TRUE(),'Bid Monitoring'!F58=D4),IF(E4="All",TRUE(),'Bid Monitoring'!E58=E4),IF(F4="All",TRUE(),'Bid Monitoring'!R58=F4)),'Bid Monitoring'!H58,"") | G68: =IF(AND('Bid Monitoring'!B58<>"",IF(B4="All",TRUE(),'Bid Monitoring'!N58=B4),IF(C4="All",TRUE(),'Bid Monitoring'!L58=C4),IF(D4="All",TRUE(),'Bid Monitoring'!F58=D4),IF(E4="All",TRUE(),'Bid Monitoring'!E58=E4),IF(F4="All",TRUE(),'Bid Monitoring'!R58=F4)),'Bid Monitoring'!I58,"") | H68: =IF(AND('Bid Monitoring'!B58<>"",IF(B4="All",TRUE(),'Bid Monitoring'!N58=B4),IF(C4="All",TRUE(),'Bid Monitoring'!L58=C4),IF(D4="All",TRUE(),'Bid Monitoring'!F58=D4),IF(E4="All",TRUE(),'Bid Monitoring'!E58=E4),IF(F4="All",TRUE(),'Bid Monitoring'!R58=F4)),'Bid Monitoring'!K58,"") | I68: =IF(AND('Bid Monitoring'!B58<>"",IF(B4="All",TRUE(),'Bid Monitoring'!N58=B4),IF(C4="All",TRUE(),'Bid Monitoring'!L58=C4),IF(D4="All",TRUE(),'Bid Monitoring'!F58=D4),IF(E4="All",TRUE(),'Bid Monitoring'!E58=E4),IF(F4="All",TRUE(),'Bid Monitoring'!R58=F4)),'Bid Monitoring'!N58,"") | J68: =IF(AND('Bid Monitoring'!B58<>"",IF(B4="All",TRUE(),'Bid Monitoring'!N58=B4),IF(C4="All",TRUE(),'Bid Monitoring'!L58=C4),IF(D4="All",TRUE(),'Bid Monitoring'!F58=D4),IF(E4="All",TRUE(),'Bid Monitoring'!E58=E4),IF(F4="All",TRUE(),'Bid Monitoring'!R58=F4)),'Bid Monitoring'!L58,"")
